Workbook

Sheet START HERE
A1: COLLEGE MONEY OS | B1: COLLEGE MONEY OS | C1: COLLEGE MONEY OS | D1: COLLEGE MONEY OS | E1: COLLEGE MONEY OS | F1: COLLEGE MONEY OS | G1: COLLEGE MONEY OS | H1: COLLEGE MONEY OS | I1: COLLEGE MONEY OS | J1: COLLEGE MONEY OS
A2: COLLEGE MONEY OS | B2: COLLEGE MONEY OS | C2: COLLEGE MONEY OS | D2: COLLEGE MONEY OS | E2: COLLEGE MONEY OS | F2: COLLEGE MONEY OS | G2: COLLEGE MONEY OS | H2: COLLEGE MONEY OS | I2: COLLEGE MONEY OS | J2: COLLEGE MONEY OS
A3: A premium, formula-driven finance system for a first-year B.Tech CSE (AI & ML) hostel student. | B3: A premium, formula-driven finance system for a first-year B.Tech CSE (AI & ML) hostel student. | C3: A premium, formula-driven finance system for a first-year B.Tech CSE (AI & ML) hostel student. | D3: A premium, formula-driven finance system for a first-year B.Tech CSE (AI & ML) hostel student. | E3: A premium, formula-driven finance system for a first-year B.Tech CSE (AI & ML) hostel student. | F3: A premium, formula-driven finance system for a first-year B.Tech CSE (AI & ML) hostel student. | G3: A premium, formula-driven finance system for a first-year B.Tech CSE (AI & ML) hostel student. | H3: A premium, formula-driven finance system for a first-year B.Tech CSE (AI & ML) hostel student. | I3: A premium, formula-driven finance system for a first-year B.Tech CSE (AI & ML) hostel student. | J3: A premium, formula-driven finance system for a first-year B.Tech CSE (AI & ML) hostel student.
A5: Get started in 8 simple steps | B5: Get started in 8 simple steps | C5: Get started in 8 simple steps | D5: Get started in 8 simple steps | E5: Get started in 8 simple steps | F5: Get started in 8 simple steps | H5: Color key | I5: Color key | J5: Color key
A7: 1 | B7: Personalize | C7: Open SETTINGS and update the orange profile, year, semester dates and thresholds. | H7: ORANGE | I7: Editable inputs | J7: Type or choose from a dropdown
A8: 2 | B8: Set allowance | C8: Enter your default monthly allowance and savings rule in SETTINGS. | H8: BLUE | I8: Calculated/system | J8: Formula-driven; do not overwrite
A9: 3 | B9: Set budgets | C9: Review the category database and MONTHLY BUDGET. Override any month if needed. | H9: GREEN | I9: Healthy status | J9: On track, paid or reconciled
A10: 4 | B10: Opening balances | C10: Enter opening and actual balances on ACCOUNTS. | H10: RED | I10: Action required | J10: Over budget, overdue or invalid
A11: 5 | B11: Add transactions | C11: Use QUICK ENTRY. Enter each real-world transaction once; blue columns calculate automatically.
A12: 6 | B12: Review | C12: Use DASHBOARD, MONTHLY REPORT and INSIGHTS to spot trends, alerts and safe spending limits.
A13: 7 | B13: Reconcile weekly | C13: Compare calculated vs actual account balances and review duplicates or missing fields.
A14: 8 | B14: Close the month | C14: Complete the checklist and reflection on MONTHLY REPORT; never delete history.
A17: Demo data & privacy | B17: Demo data & privacy | C17: Demo data & privacy | D17: Demo data & privacy | E17: Demo data & privacy | F17: Demo data & privacy | G17: Demo data & privacy | H17: Demo data & privacy | I17: Demo data & privacy | J17: Demo data & privacy
A19: The sample rows on QUICK ENTRY are marked Demo = Yes. Keep Demo Mode = Yes to explore the workbook. Before entering real data, set SETTINGS > Demo Mode to No (demo rows are excluded instantly) or delete those clearly marked rows. Store only harmless account nicknames and transaction values—never bank passwords, UPI/ATM PINs, CVV, OTPs or internet-banking credentials. | B19: The sample rows on QUICK ENTRY are marked Demo = Yes. Keep Demo Mode = Yes to explore the workbook. Before entering real data, set SETTINGS > Demo Mode to No (demo rows are excluded instantly) or delete those clearly marked rows. Store only harmless account nicknames and transaction values—never bank passwords, UPI/ATM PINs, CVV, OTPs or internet-banking credentials. | C19: The sample rows on QUICK ENTRY are marked Demo = Yes. Keep Demo Mode = Yes to explore the workbook. Before entering real data, set SETTINGS > Demo Mode to No (demo rows are excluded instantly) or delete those clearly marked rows. Store only harmless account nicknames and transaction values—never bank passwords, UPI/ATM PINs, CVV, OTPs or internet-banking credentials. | D19: The sample rows on QUICK ENTRY are marked Demo = Yes. Keep Demo Mode = Yes to explore the workbook. Before entering real data, set SETTINGS > Demo Mode to No (demo rows are excluded instantly) or delete those clearly marked rows. Store only harmless account nicknames and transaction values—never bank passwords, UPI/ATM PINs, CVV, OTPs or internet-banking credentials. | E19: The sample rows on QUICK ENTRY are marked Demo = Yes. Keep Demo Mode = Yes to explore the workbook. Before entering real data, set SETTINGS > Demo Mode to No (demo rows are excluded instantly) or delete those clearly marked rows. Store only harmless account nicknames and transaction values—never bank passwords, UPI/ATM PINs, CVV, OTPs or internet-banking credentials. | F19: The sample rows on QUICK ENTRY are marked Demo = Yes. Keep Demo Mode = Yes to explore the workbook. Before entering real data, set SETTINGS > Demo Mode to No (demo rows are excluded instantly) or delete those clearly marked rows. Store only harmless account nicknames and transaction values—never bank passwords, UPI/ATM PINs, CVV, OTPs or internet-banking credentials. | G19: The sample rows on QUICK ENTRY are marked Demo = Yes. Keep Demo Mode = Yes to explore the workbook. Before entering real data, set SETTINGS > Demo Mode to No (demo rows are excluded instantly) or delete those clearly marked rows. Store only harmless account nicknames and transaction values—never bank passwords, UPI/ATM PINs, CVV, OTPs or internet-banking credentials. | H19: The sample rows on QUICK ENTRY are marked Demo = Yes. Keep Demo Mode = Yes to explore the workbook. Before entering real data, set SETTINGS > Demo Mode to No (demo rows are excluded instantly) or delete those clearly marked rows. Store only harmless account nicknames and transaction values—never bank passwords, UPI/ATM PINs, CVV, OTPs or internet-banking credentials. | I19: The sample rows on QUICK ENTRY are marked Demo = Yes. Keep Demo Mode = Yes to explore the workbook. Before entering real data, set SETTINGS > Demo Mode to No (demo rows are excluded instantly) or delete those clearly marked rows. Store only harmless account nicknames and transaction values—never bank passwords, UPI/ATM PINs, CVV, OTPs or internet-banking credentials. | J19: The sample rows on QUICK ENTRY are marked Demo = Yes. Keep Demo Mode = Yes to explore the workbook. Before entering real data, set SETTINGS > Demo Mode to No (demo rows are excluded instantly) or delete those clearly marked rows. Store only harmless account nicknames and transaction values—never bank passwords, UPI/ATM PINs, CVV, OTPs or internet-banking credentials.
A20: The sample rows on QUICK ENTRY are marked Demo = Yes. Keep Demo Mode = Yes to explore the workbook. Before entering real data, set SETTINGS > Demo Mode to No (demo rows are excluded instantly) or delete those clearly marked rows. Store only harmless account nicknames and transaction values—never bank passwords, UPI/ATM PINs, CVV, OTPs or internet-banking credentials. | B20: The sample rows on QUICK ENTRY are marked Demo = Yes. Keep Demo Mode = Yes to explore the workbook. Before entering real data, set SETTINGS > Demo Mode to No (demo rows are excluded instantly) or delete those clearly marked rows. Store only harmless account nicknames and transaction values—never bank passwords, UPI/ATM PINs, CVV, OTPs or internet-banking credentials. | C20: The sample rows on QUICK ENTRY are marked Demo = Yes. Keep Demo Mode = Yes to explore the workbook. Before entering real data, set SETTINGS > Demo Mode to No (demo rows are excluded instantly) or delete those clearly marked rows. Store only harmless account nicknames and transaction values—never bank passwords, UPI/ATM PINs, CVV, OTPs or internet-banking credentials. | D20: The sample rows on QUICK ENTRY are marked Demo = Yes. Keep Demo Mode = Yes to explore the workbook. Before entering real data, set SETTINGS > Demo Mode to No (demo rows are excluded instantly) or delete those clearly marked rows. Store only harmless account nicknames and transaction values—never bank passwords, UPI/ATM PINs, CVV, OTPs or internet-banking credentials. | E20: The sample rows on QUICK ENTRY are marked Demo = Yes. Keep Demo Mode = Yes to explore the workbook. Before entering real data, set SETTINGS > Demo Mode to No (demo rows are excluded instantly) or delete those clearly marked rows. Store only harmless account nicknames and transaction values—never bank passwords, UPI/ATM PINs, CVV, OTPs or internet-banking credentials. | F20: The sample rows on QUICK ENTRY are marked Demo = Yes. Keep Demo Mode = Yes to explore the workbook. Before entering real data, set SETTINGS > Demo Mode to No (demo rows are excluded instantly) or delete those clearly marked rows. Store only harmless account nicknames and transaction values—never bank passwords, UPI/ATM PINs, CVV, OTPs or internet-banking credentials. | G20: The sample rows on QUICK ENTRY are marked Demo = Yes. Keep Demo Mode = Yes to explore the workbook. Before entering real data, set SETTINGS > Demo Mode to No (demo rows are excluded instantly) or delete those clearly marked rows. Store only harmless account nicknames and transaction values—never bank passwords, UPI/ATM PINs, CVV, OTPs or internet-banking credentials. | H20: The sample rows on QUICK ENTRY are marked Demo = Yes. Keep Demo Mode = Yes to explore the workbook. Before entering real data, set SETTINGS > Demo Mode to No (demo rows are excluded instantly) or delete those clearly marked rows. Store only harmless account nicknames and transaction values—never bank passwords, UPI/ATM PINs, CVV, OTPs or internet-banking credentials. | I20: The sample rows on QUICK ENTRY are marked Demo = Yes. Keep Demo Mode = Yes to explore the workbook. Before entering real data, set SETTINGS > Demo Mode to No (demo rows are excluded instantly) or delete those clearly marked rows. Store only harmless account nicknames and transaction values—never bank passwords, UPI/ATM PINs, CVV, OTPs or internet-banking credentials. | J20: The sample rows on QUICK ENTRY are marked Demo = Yes. Keep Demo Mode = Yes to explore the workbook. Before entering real data, set SETTINGS > Demo Mode to No (demo rows are excluded instantly) or delete those clearly marked rows. Store only harmless account nicknames and transaction values—never bank passwords, UPI/ATM PINs, CVV, OTPs or internet-banking credentials.
A21: The sample rows on QUICK ENTRY are marked Demo = Yes. Keep Demo Mode = Yes to explore the workbook. Before entering real data, set SETTINGS > Demo Mode to No (demo rows are excluded instantly) or delete those clearly marked rows. Store only harmless account nicknames and transaction values—never bank passwords, UPI/ATM PINs, CVV, OTPs or internet-banking credentials. | B21: The sample rows on QUICK ENTRY are marked Demo = Yes. Keep Demo Mode = Yes to explore the workbook. Before entering real data, set SETTINGS > Demo Mode to No (demo rows are excluded instantly) or delete those clearly marked rows. Store only harmless account nicknames and transaction values—never bank passwords, UPI/ATM PINs, CVV, OTPs or internet-banking credentials. | C21: The sample rows on QUICK ENTRY are marked Demo = Yes. Keep Demo Mode = Yes to explore the workbook. Before entering real data, set SETTINGS > Demo Mode to No (demo rows are excluded instantly) or delete those clearly marked rows. Store only harmless account nicknames and transaction values—never bank passwords, UPI/ATM PINs, CVV, OTPs or internet-banking credentials. | D21: The sample rows on QUICK ENTRY are marked Demo = Yes. Keep Demo Mode = Yes to explore the workbook. Before entering real data, set SETTINGS > Demo Mode to No (demo rows are excluded instantly) or delete those clearly marked rows. Store only harmless account nicknames and transaction values—never bank passwords, UPI/ATM PINs, CVV, OTPs or internet-banking credentials. | E21: The sample rows on QUICK ENTRY are marked Demo = Yes. Keep Demo Mode = Yes to explore the workbook. Before entering real data, set SETTINGS > Demo Mode to No (demo rows are excluded instantly) or delete those clearly marked rows. Store only harmless account nicknames and transaction values—never bank passwords, UPI/ATM PINs, CVV, OTPs or internet-banking credentials. | F21: The sample rows on QUICK ENTRY are marked Demo = Yes. Keep Demo Mode = Yes to explore the workbook. Before entering real data, set SETTINGS > Demo Mode to No (demo rows are excluded instantly) or delete those clearly marked rows. Store only harmless account nicknames and transaction values—never bank passwords, UPI/ATM PINs, CVV, OTPs or internet-banking credentials. | G21: The sample rows on QUICK ENTRY are marked Demo = Yes. Keep Demo Mode = Yes to explore the workbook. Before entering real data, set SETTINGS > Demo Mode to No (demo rows are excluded instantly) or delete those clearly marked rows. Store only harmless account nicknames and transaction values—never bank passwords, UPI/ATM PINs, CVV, OTPs or internet-banking credentials. | H21: The sample rows on QUICK ENTRY are marked Demo = Yes. Keep Demo Mode = Yes to explore the workbook. Before entering real data, set SETTINGS > Demo Mode to No (demo rows are excluded instantly) or delete those clearly marked rows. Store only harmless account nicknames and transaction values—never bank passwords, UPI/ATM PINs, CVV, OTPs or internet-banking credentials. | I21: The sample rows on QUICK ENTRY are marked Demo = Yes. Keep Demo Mode = Yes to explore the workbook. Before entering real data, set SETTINGS > Demo Mode to No (demo rows are excluded instantly) or delete those clearly marked rows. Store only harmless account nicknames and transaction values—never bank passwords, UPI/ATM PINs, CVV, OTPs or internet-banking credentials. | J21: The sample rows on QUICK ENTRY are marked Demo = Yes. Keep Demo Mode = Yes to explore the workbook. Before entering real data, set SETTINGS > Demo Mode to No (demo rows are excluded instantly) or delete those clearly marked rows. Store only harmless account nicknames and transaction values—never bank passwords, UPI/ATM PINs, CVV, OTPs or internet-banking credentials.
A24: How the workbook flows | B24: How the workbook flows | C24: How the workbook flows | D24: How the workbook flows | E24: How the workbook flows | F24: How the workbook flows | G24: How the workbook flows | H24: How the workbook flows | I24: How the workbook flows | J24: How the workbook flows
A26: QUICK ENTRY (one master table) → MONTHLY BUDGET → DASHBOARD / REPORTS / INSIGHTS → ACCOUNTS / GOALS / FORECASTS Specialized tabs are planners and analyses. Record actual money movement only once in QUICK ENTRY to avoid double-counting. | B26: QUICK ENTRY (one master table) → MONTHLY BUDGET → DASHBOARD / REPORTS / INSIGHTS → ACCOUNTS / GOALS / FORECASTS Specialized tabs are planners and analyses. Record actual money movement only once in QUICK ENTRY to avoid double-counting. | C26: QUICK ENTRY (one master table) → MONTHLY BUDGET → DASHBOARD / REPORTS / INSIGHTS → ACCOUNTS / GOALS / FORECASTS Specialized tabs are planners and analyses. Record actual money movement only once in QUICK ENTRY to avoid double-counting. | D26: QUICK ENTRY (one master table) → MONTHLY BUDGET → DASHBOARD / REPORTS / INSIGHTS → ACCOUNTS / GOALS / FORECASTS Specialized tabs are planners and analyses. Record actual money movement only once in QUICK ENTRY to avoid double-counting. | E26: QUICK ENTRY (one master table) → MONTHLY BUDGET → DASHBOARD / REPORTS / INSIGHTS → ACCOUNTS / GOALS / FORECASTS Specialized tabs are planners and analyses. Record actual money movement only once in QUICK ENTRY to avoid double-counting. | F26: QUICK ENTRY (one master table) → MONTHLY BUDGET → DASHBOARD / REPORTS / INSIGHTS → ACCOUNTS / GOALS / FORECASTS Specialized tabs are planners and analyses. Record actual money movement only once in QUICK ENTRY to avoid double-counting. | G26: QUICK ENTRY (one master table) → MONTHLY BUDGET → DASHBOARD / REPORTS / INSIGHTS → ACCOUNTS / GOALS / FORECASTS Specialized tabs are planners and analyses. Record actual money movement only once in QUICK ENTRY to avoid double-counting. | H26: QUICK ENTRY (one master table) → MONTHLY BUDGET → DASHBOARD / REPORTS / INSIGHTS → ACCOUNTS / GOALS / FORECASTS Specialized tabs are planners and analyses. Record actual money movement only once in QUICK ENTRY to avoid double-counting. | I26: QUICK ENTRY (one master table) → MONTHLY BUDGET → DASHBOARD / REPORTS / INSIGHTS → ACCOUNTS / GOALS / FORECASTS Specialized tabs are planners and analyses. Record actual money movement only once in QUICK ENTRY to avoid double-counting. | J26: QUICK ENTRY (one master table) → MONTHLY BUDGET → DASHBOARD / REPORTS / INSIGHTS → ACCOUNTS / GOALS / FORECASTS Specialized tabs are planners and analyses. Record actual money movement only once in QUICK ENTRY to avoid double-counting.
A27: QUICK ENTRY (one master table) → MONTHLY BUDGET → DASHBOARD / REPORTS / INSIGHTS → ACCOUNTS / GOALS / FORECASTS Specialized tabs are planners and analyses. Record actual money movement only once in QUICK ENTRY to avoid double-counting. | B27: QUICK ENTRY (one master table) → MONTHLY BUDGET → DASHBOARD / REPORTS / INSIGHTS → ACCOUNTS / GOALS / FORECASTS Specialized tabs are planners and analyses. Record actual money movement only once in QUICK ENTRY to avoid double-counting. | C27: QUICK ENTRY (one master table) → MONTHLY BUDGET → DASHBOARD / REPORTS / INSIGHTS → ACCOUNTS / GOALS / FORECASTS Specialized tabs are planners and analyses. Record actual money movement only once in QUICK ENTRY to avoid double-counting. | D27: QUICK ENTRY (one master table) → MONTHLY BUDGET → DASHBOARD / REPORTS / INSIGHTS → ACCOUNTS / GOALS / FORECASTS Specialized tabs are planners and analyses. Record actual money movement only once in QUICK ENTRY to avoid double-counting. | E27: QUICK ENTRY (one master table) → MONTHLY BUDGET → DASHBOARD / REPORTS / INSIGHTS → ACCOUNTS / GOALS / FORECASTS Specialized tabs are planners and analyses. Record actual money movement only once in QUICK ENTRY to avoid double-counting. | F27: QUICK ENTRY (one master table) → MONTHLY BUDGET → DASHBOARD / REPORTS / INSIGHTS → ACCOUNTS / GOALS / FORECASTS Specialized tabs are planners and analyses. Record actual money movement only once in QUICK ENTRY to avoid double-counting. | G27: QUICK ENTRY (one master table) → MONTHLY BUDGET → DASHBOARD / REPORTS / INSIGHTS → ACCOUNTS / GOALS / FORECASTS Specialized tabs are planners and analyses. Record actual money movement only once in QUICK ENTRY to avoid double-counting. | H27: QUICK ENTRY (one master table) → MONTHLY BUDGET → DASHBOARD / REPORTS / INSIGHTS → ACCOUNTS / GOALS / FORECASTS Specialized tabs are planners and analyses. Record actual money movement only once in QUICK ENTRY to avoid double-counting. | I27: QUICK ENTRY (one master table) → MONTHLY BUDGET → DASHBOARD / REPORTS / INSIGHTS → ACCOUNTS / GOALS / FORECASTS Specialized tabs are planners and analyses. Record actual money movement only once in QUICK ENTRY to avoid double-counting. | J27: QUICK ENTRY (one master table) → MONTHLY BUDGET → DASHBOARD / REPORTS / INSIGHTS → ACCOUNTS / GOALS / FORECASTS Specialized tabs are planners and analyses. Record actual money movement only once in QUICK ENTRY to avoid double-counting.
A28: QUICK ENTRY (one master table) → MONTHLY BUDGET → DASHBOARD / REPORTS / INSIGHTS → ACCOUNTS / GOALS / FORECASTS Specialized tabs are planners and analyses. Record actual money movement only once in QUICK ENTRY to avoid double-counting. | B28: QUICK ENTRY (one master table) → MONTHLY BUDGET → DASHBOARD / REPORTS / INSIGHTS → ACCOUNTS / GOALS / FORECASTS Specialized tabs are planners and analyses. Record actual money movement only once in QUICK ENTRY to avoid double-counting. | C28: QUICK ENTRY (one master table) → MONTHLY BUDGET → DASHBOARD / REPORTS / INSIGHTS → ACCOUNTS / GOALS / FORECASTS Specialized tabs are planners and analyses. Record actual money movement only once in QUICK ENTRY to avoid double-counting. | D28: QUICK ENTRY (one master table) → MONTHLY BUDGET → DASHBOARD / REPORTS / INSIGHTS → ACCOUNTS / GOALS / FORECASTS Specialized tabs are planners and analyses. Record actual money movement only once in QUICK ENTRY to avoid double-counting. | E28: QUICK ENTRY (one master table) → MONTHLY BUDGET → DASHBOARD / REPORTS / INSIGHTS → ACCOUNTS / GOALS / FORECASTS Specialized tabs are planners and analyses. Record actual money movement only once in QUICK ENTRY to avoid double-counting. | F28: QUICK ENTRY (one master table) → MONTHLY BUDGET → DASHBOARD / REPORTS / INSIGHTS → ACCOUNTS / GOALS / FORECASTS Specialized tabs are planners and analyses. Record actual money movement only once in QUICK ENTRY to avoid double-counting. | G28: QUICK ENTRY (one master table) → MONTHLY BUDGET → DASHBOARD / REPORTS / INSIGHTS → ACCOUNTS / GOALS / FORECASTS Specialized tabs are planners and analyses. Record actual money movement only once in QUICK ENTRY to avoid double-counting. | H28: QUICK ENTRY (one master table) → MONTHLY BUDGET → DASHBOARD / REPORTS / INSIGHTS → ACCOUNTS / GOALS / FORECASTS Specialized tabs are planners and analyses. Record actual money movement only once in QUICK ENTRY to avoid double-counting. | I28: QUICK ENTRY (one master table) → MONTHLY BUDGET → DASHBOARD / REPORTS / INSIGHTS → ACCOUNTS / GOALS / FORECASTS Specialized tabs are planners and analyses. Record actual money movement only once in QUICK ENTRY to avoid double-counting. | J28: QUICK ENTRY (one master table) → MONTHLY BUDGET → DASHBOARD / REPORTS / INSIGHTS → ACCOUNTS / GOALS / FORECASTS Specialized tabs are planners and analyses. Record actual money movement only once in QUICK ENTRY to avoid double-counting.

Sheet DASHBOARD
A1: PERSONAL FINANCE DASHBOARD | B1: PERSONAL FINANCE DASHBOARD | C1: PERSONAL FINANCE DASHBOARD | D1: PERSONAL FINANCE DASHBOARD | E1: PERSONAL FINANCE DASHBOARD | F1: PERSONAL FINANCE DASHBOARD | G1: PERSONAL FINANCE DASHBOARD | H1: PERSONAL FINANCE DASHBOARD | I1: PERSONAL FINANCE DASHBOARD | J1: PERSONAL FINANCE DASHBOARD | K1: PERSONAL FINANCE DASHBOARD | L1: PERSONAL FINANCE DASHBOARD | M1: PERSONAL FINANCE DASHBOARD | N1: PERSONAL FINANCE DASHBOARD | O1: PERSONAL FINANCE DASHBOARD | P1: PERSONAL FINANCE DASHBOARD
A2: PERSONAL FINANCE DASHBOARD | B2: PERSONAL FINANCE DASHBOARD | C2: PERSONAL FINANCE DASHBOARD | D2: PERSONAL FINANCE DASHBOARD | E2: PERSONAL FINANCE DASHBOARD | F2: PERSONAL FINANCE DASHBOARD | G2: PERSONAL FINANCE DASHBOARD | H2: PERSONAL FINANCE DASHBOARD | I2: PERSONAL FINANCE DASHBOARD | J2: PERSONAL FINANCE DASHBOARD | K2: PERSONAL FINANCE DASHBOARD | L2: PERSONAL FINANCE DASHBOARD | M2: PERSONAL FINANCE DASHBOARD | N2: PERSONAL FINANCE DASHBOARD | O2: PERSONAL FINANCE DASHBOARD | P2: PERSONAL FINANCE DASHBOARD
A3: Month | B3: Month | C3: September | D3: September | E3: Selected month KPIs, alerts, trends and forecasts. Change only the orange controls below. | F3: ="Viewing "&$C$3&" "&TEXT($C$4,"0")&" • Demo Mode: "&SETTINGS!$B$16 -> Viewing September 2026 • Demo Mode: Yes | G3: Selected month KPIs, alerts, trends and forecasts. Change only the orange controls below. | H3: Selected month KPIs, alerts, trends and forecasts. Change only the orange controls below. | I3: Selected month KPIs, alerts, trends and forecasts. Change only the orange controls below. | J3: Selected month KPIs, alerts, trends and forecasts. Change only the orange controls below. | K3: Selected month KPIs, alerts, trends and forecasts. Change only the orange controls below. | L3: Selected month KPIs, alerts, trends and forecasts. Change only the orange controls below. | M3: Selected month KPIs, alerts, trends and forecasts. Change only the orange controls below. | N3: Selected month KPIs, alerts, trends and forecasts. Change only the orange controls below. | O3: Selected month KPIs, alerts, trends and forecasts. Change only the orange controls below. | P3: Selected month KPIs, alerts, trends and forecasts. Change only the orange controls below. | R3: Category | S3: Actual | U3: Month | V3: Income | W3: Expense | Y3: Month | Z3: Cumulative Savings | AB3: Cost Type | AC3: Actual | AE3: Payment Method | AF3: Spend
A4: Planning Year | B4: Planning Year | C4: 2026 | D4: 2026 | R4: =$A27 -> College Fees | S4: =IF($R4="Savings",0,$C27) -> 0 | U4: ='ANNUAL SUMMARY'!$A$8 -> January | V4: ='ANNUAL SUMMARY'!$C$8 -> 25000 | W4: ='ANNUAL SUMMARY'!$E$8 -> 8000 | Y4: ='ANNUAL SUMMARY'!$A$8 -> January | Z4: ='ANNUAL SUMMARY'!$T$8 -> 0 | AB4: Fixed | AC4: =SUMIF('MONTHLY BUDGET'!$C$8:$C$27,AB4,'MONTHLY BUDGET'!$T$8:$T$27) -> 3748 | AE4: Cash | AF4: =SUMIFS('QUICK ENTRY'!$E$8:$E$1007,'QUICK ENTRY'!$AF$8:$AF$1007,"Yes",'QUICK ENTRY'!$C$8:$C$1007,"Expense",'QUICK ENTRY'!$V$8:$V$1007,$C$3,'QUICK ENTRY'!$X$8:$X$1007,$C$4,'QUICK ENTRY'!$F$8:$F$1007,AE4) -> 280
R5: =$A28 -> Hostel | S5: =IF($R5="Savings",0,$C28) -> 3200 | U5: ='ANNUAL SUMMARY'!$A$9 -> February | V5: ='ANNUAL SUMMARY'!$C$9 -> 25000 | W5: ='ANNUAL SUMMARY'!$E$9 -> 4400 | Y5: ='ANNUAL SUMMARY'!$A$9 -> February | Z5: ='ANNUAL SUMMARY'!$T$9 -> 0 | AB5: Variable | AC5: =SUMIF('MONTHLY BUDGET'!$C$8:$C$27,AB5,'MONTHLY BUDGET'!$T$8:$T$27) -> 3449 | AE5: UPI | AF5: =SUMIFS('QUICK ENTRY'!$E$8:$E$1007,'QUICK ENTRY'!$AF$8:$AF$1007,"Yes",'QUICK ENTRY'!$C$8:$C$1007,"Expense",'QUICK ENTRY'!$V$8:$V$1007,$C$3,'QUICK ENTRY'!$X$8:$X$1007,$C$4,'QUICK ENTRY'!$F$8:$F$1007,AE5) -> 4448
A6: TOTAL MONEY RECEIVED | B6: TOTAL MONEY RECEIVED | C6: TOTAL MONEY RECEIVED | D6: TOTAL MONEY RECEIVED | E6: TOTAL SPENT | F6: TOTAL SPENT | G6: TOTAL SPENT | H6: TOTAL SPENT | I6: REMAINING BALANCE | J6: REMAINING BALANCE | K6: REMAINING BALANCE | L6: REMAINING BALANCE | M6: TOTAL SAVED | N6: TOTAL SAVED | O6: TOTAL SAVED | P6: TOTAL SAVED | R6: =$A29 -> Food | S6: =IF($R6="Savings",0,$C29) -> 620 | U6: ='ANNUAL SUMMARY'!$A$10 -> March | V6: ='ANNUAL SUMMARY'!$C$10 -> 25000 | W6: ='ANNUAL SUMMARY'!$E$10 -> 3099 | Y6: ='ANNUAL SUMMARY'!$A$10 -> March | Z6: ='ANNUAL SUMMARY'!$T$10 -> 0 | AB6: Savings | AC6: =SUMIF('MONTHLY BUDGET'!$C$8:$C$27,AB6,'MONTHLY BUDGET'!$T$8:$T$27) -> 2500 | AE6: GPay | AF6: =SUMIFS('QUICK ENTRY'!$E$8:$E$1007,'QUICK ENTRY'!$AF$8:$AF$1007,"Yes",'QUICK ENTRY'!$C$8:$C$1007,"Expense",'QUICK ENTRY'!$V$8:$V$1007,$C$3,'QUICK ENTRY'!$X$8:$X$1007,$C$4,'QUICK ENTRY'!$F$8:$F$1007,AE6) -> 620
A7: TOTAL MONEY RECEIVED | B7: TOTAL MONEY RECEIVED | C7: TOTAL MONEY RECEIVED | D7: TOTAL MONEY RECEIVED | E7: TOTAL SPENT | F7: TOTAL SPENT | G7: TOTAL SPENT | H7: TOTAL SPENT | I7: REMAINING BALANCE | J7: REMAINING BALANCE | K7: REMAINING BALANCE | L7: REMAINING BALANCE | M7: TOTAL SAVED | N7: TOTAL SAVED | O7: TOTAL SAVED | P7: TOTAL SAVED | R7: =$A30 -> Transport | S7: =IF($R7="Savings",0,$C30) -> 350 | U7: ='ANNUAL SUMMARY'!$A$11 -> April | V7: ='ANNUAL SUMMARY'!$C$11 -> 25000 | W7: ='ANNUAL SUMMARY'!$E$11 -> 4900 | Y7: ='ANNUAL SUMMARY'!$A$11 -> April | Z7: ='ANNUAL SUMMARY'!$T$11 -> 0 | AE7: PhonePe | AF7: =SUMIFS('QUICK ENTRY'!$E$8:$E$1007,'QUICK ENTRY'!$AF$8:$AF$1007,"Yes",'QUICK ENTRY'!$C$8:$C$1007,"Expense",'QUICK ENTRY'!$V$8:$V$1007,$C$3,'QUICK ENTRY'!$X$8:$X$1007,$C$4,'QUICK ENTRY'!$F$8:$F$1007,AE7) -> 350
A8: =SUMIFS('QUICK ENTRY'!$E$8:$E$1007,'QUICK ENTRY'!$AF$8:$AF$1007,"Yes",'QUICK ENTRY'!$C$8:$C$1007,"Income",'QUICK ENTRY'!$V$8:$V$1007,DASHBOARD!$C$3,'QUICK ENTRY'!$X$8:$X$1007,DASHBOARD!$C$4)+SUMIFS('QUICK ENTRY'!$E$8:$E$1007,'QUICK ENTRY'!$AF$8:$AF$1007,"Yes",'QUICK ENTRY'!$C$8:$C$1007,"Refund",'QUICK ENTRY'!$V$8:$V$1007,DASHBOARD!$C$3,'QUICK ENTRY'!$X$8:$X$1007,DASHBOARD!$C$4)+SUMIFS('QUICK ENTRY'!$E$8:$E$1007,'QUICK ENTRY'!$AF$8:$AF$1007,"Yes",'QUICK ENTRY'!$C$8:$C$1007,"Reimbursement",'QUICK ENTRY'!$V$8:$V$1007,DASHBOARD!$C$3,'QUICK ENTRY'!$X$8:$X$1007,DASHBOARD!$C$4) -> 25000 | E8: =SUMIFS('QUICK ENTRY'!$E$8:$E$1007,'QUICK ENTRY'!$AF$8:$AF$1007,"Yes",'QUICK ENTRY'!$C$8:$C$1007,"Expense",'QUICK ENTRY'!$V$8:$V$1007,DASHBOARD!$C$3,'QUICK ENTRY'!$X$8:$X$1007,DASHBOARD!$C$4) -> 7197 | I8: =A8-E8-M8 -> 15303 | M8: =SUMIFS('QUICK ENTRY'!$E$8:$E$1007,'QUICK ENTRY'!$AF$8:$AF$1007,"Yes",'QUICK ENTRY'!$C$8:$C$1007,"Savings Transfer",'QUICK ENTRY'!$V$8:$V$1007,DASHBOARD!$C$3,'QUICK ENTRY'!$X$8:$X$1007,DASHBOARD!$C$4) -> 2500 | R8: =$A31 -> Technology | S8: =IF($R8="Savings",0,$C31) -> 0 | U8: ='ANNUAL SUMMARY'!$A$12 -> May | V8: ='ANNUAL SUMMARY'!$C$12 -> 25000 | W8: ='ANNUAL SUMMARY'!$E$12 -> 3300 | Y8: ='ANNUAL SUMMARY'!$A$12 -> May | Z8: ='ANNUAL SUMMARY'!$T$12 -> 0 | AE8: Paytm | AF8: =SUMIFS('QUICK ENTRY'!$E$8:$E$1007,'QUICK ENTRY'!$AF$8:$AF$1007,"Yes",'QUICK ENTRY'!$C$8:$C$1007,"Expense",'QUICK ENTRY'!$V$8:$V$1007,$C$3,'QUICK ENTRY'!$X$8:$X$1007,$C$4,'QUICK ENTRY'!$F$8:$F$1007,AE8) -> 0
R9: =$A32 -> AI-ML Learning | S9: =IF($R9="Savings",0,$C32) -> 1499 | U9: ='ANNUAL SUMMARY'!$A$13 -> June | V9: ='ANNUAL SUMMARY'!$C$13 -> 25000 | W9: ='ANNUAL SUMMARY'!$E$13 -> 2649 | Y9: ='ANNUAL SUMMARY'!$A$13 -> June | Z9: ='ANNUAL SUMMARY'!$T$13 -> 0 | AE9: Debit Card | AF9: =SUMIFS('QUICK ENTRY'!$E$8:$E$1007,'QUICK ENTRY'!$AF$8:$AF$1007,"Yes",'QUICK ENTRY'!$C$8:$C$1007,"Expense",'QUICK ENTRY'!$V$8:$V$1007,$C$3,'QUICK ENTRY'!$X$8:$X$1007,$C$4,'QUICK ENTRY'!$F$8:$F$1007,AE9) -> 1499
R10: =$A33 -> Books & Stationery | S10: =IF($R10="Savings",0,$C33) -> 280 | U10: ='ANNUAL SUMMARY'!$A$14 -> July | V10: ='ANNUAL SUMMARY'!$C$14 -> 25000 | W10: ='ANNUAL SUMMARY'!$E$14 -> 8200 | Y10: ='ANNUAL SUMMARY'!$A$14 -> July | Z10: ='ANNUAL SUMMARY'!$T$14 -> 0 | AE10: Credit Card | AF10: =SUMIFS('QUICK ENTRY'!$E$8:$E$1007,'QUICK ENTRY'!$AF$8:$AF$1007,"Yes",'QUICK ENTRY'!$C$8:$C$1007,"Expense",'QUICK ENTRY'!$V$8:$V$1007,$C$3,'QUICK ENTRY'!$X$8:$X$1007,$C$4,'QUICK ENTRY'!$F$8:$F$1007,AE10) -> 0
A11: SAVINGS RATE | B11: SAVINGS RATE | C11: SAVINGS RATE | D11: SAVINGS RATE | E11: BUDGET USED | F11: BUDGET USED | G11: BUDGET USED | H11: BUDGET USED | I11: EMERGENCY FUND | J11: EMERGENCY FUND | K11: EMERGENCY FUND | L11: EMERGENCY FUND | M11: FINANCIAL SCORE | N11: FINANCIAL SCORE | O11: FINANCIAL SCORE | P11: FINANCIAL SCORE | R11: =$A34 -> Subscriptions | S11: =IF($R11="Savings",0,$C34) -> 199 | U11: ='ANNUAL SUMMARY'!$A$15 -> August | V11: ='ANNUAL SUMMARY'!$C$15 -> 30000 | W11: ='ANNUAL SUMMARY'!$E$15 -> 5200 | Y11: ='ANNUAL SUMMARY'!$A$15 -> August | Z11: ='ANNUAL SUMMARY'!$T$15 -> 2000 | AE11: Bank Transfer | AF11: =SUMIFS('QUICK ENTRY'!$E$8:$E$1007,'QUICK ENTRY'!$AF$8:$AF$1007,"Yes",'QUICK ENTRY'!$C$8:$C$1007,"Expense",'QUICK ENTRY'!$V$8:$V$1007,$C$3,'QUICK ENTRY'!$X$8:$X$1007,$C$4,'QUICK ENTRY'!$F$8:$F$1007,AE11) -> 0
A12: SAVINGS RATE | B12: SAVINGS RATE | C12: SAVINGS RATE | D12: SAVINGS RATE | E12: BUDGET USED | F12: BUDGET USED | G12: BUDGET USED | H12: BUDGET USED | I12: EMERGENCY FUND | J12: EMERGENCY FUND | K12: EMERGENCY FUND | L12: EMERGENCY FUND | M12: FINANCIAL SCORE | N12: FINANCIAL SCORE | O12: FINANCIAL SCORE | P12: FINANCIAL SCORE | R12: =$A35 -> Mobile & Internet | S12: =IF($R12="Savings",0,$C35) -> 349 | U12: ='ANNUAL SUMMARY'!$A$16 -> September | V12: ='ANNUAL SUMMARY'!$C$16 -> 25000 | W12: ='ANNUAL SUMMARY'!$E$16 -> 7197 | Y12: ='ANNUAL SUMMARY'!$A$16 -> September | Z12: ='ANNUAL SUMMARY'!$T$16 -> 4500
A13: =IFERROR(M8/A8,0) -> 0.1 | E13: =IFERROR((E8+M8)/'MONTHLY BUDGET'!$S$28,0) -> 0.36592453 | I13: ='EMERGENCY FUND'!$B$8 -> 9500 | M13: =INSIGHTS!$B$8 -> 83 | R13: =$A36 -> Personal Care | S13: =IF($R13="Savings",0,$C36) -> 0 | U13: ='ANNUAL SUMMARY'!$A$17 -> October | V13: ='ANNUAL SUMMARY'!$C$17 -> 0 | W13: ='ANNUAL SUMMARY'!$E$17 -> 0 | Y13: ='ANNUAL SUMMARY'!$A$17 -> October | Z13: ='ANNUAL SUMMARY'!$T$17 -> 4500
R14: =$A37 -> Clothing | S14: =IF($R14="Savings",0,$C37) -> 0 | U14: ='ANNUAL SUMMARY'!$A$18 -> November | V14: ='ANNUAL SUMMARY'!$C$18 -> 0 | W14: ='ANNUAL SUMMARY'!$E$18 -> 0 | Y14: ='ANNUAL SUMMARY'!$A$18 -> November | Z14: ='ANNUAL SUMMARY'!$T$18 -> 4500
R15: =$A38 -> Entertainment | S15: =IF($R15="Savings",0,$C38) -> 0 | U15: ='ANNUAL SUMMARY'!$A$19 -> December | V15: ='ANNUAL SUMMARY'!$C$19 -> 0 | W15: ='ANNUAL SUMMARY'!$E$19 -> 0 | Y15: ='ANNUAL SUMMARY'!$A$19 -> December | Z15: ='ANNUAL SUMMARY'!$T$19 -> 4500
A16: AVERAGE DAILY SPEND | B16: AVERAGE DAILY SPEND | C16: AVERAGE DAILY SPEND | D16: AVERAGE DAILY SPEND | E16: SAFE SPENDING TODAY | F16: SAFE SPENDING TODAY | G16: SAFE SPENDING TODAY | H16: SAFE SPENDING TODAY | I16: PROJECTED MONTH-END BALANCE | J16: PROJECTED MONTH-END BALANCE | K16: PROJECTED MONTH-END BALANCE | L16: PROJECTED MONTH-END BALANCE | M16: UPCOMING BILLS (7 DAYS) | N16: UPCOMING BILLS (7 DAYS) | O16: UPCOMING BILLS (7 DAYS) | P16: UPCOMING BILLS (7 DAYS) | R16: =$A39 -> Travel Home | S16: =IF($R16="Savings",0,$C39) -> 0
A17: AVERAGE DAILY SPEND | B17: AVERAGE DAILY SPEND | C17: AVERAGE DAILY SPEND | D17: AVERAGE DAILY SPEND | E17: SAFE SPENDING TODAY | F17: SAFE SPENDING TODAY | G17: SAFE SPENDING TODAY | H17: SAFE SPENDING TODAY | I17: PROJECTED MONTH-END BALANCE | J17: PROJECTED MONTH-END BALANCE | K17: PROJECTED MONTH-END BALANCE | L17: PROJECTED MONTH-END BALANCE | M17: UPCOMING BILLS (7 DAYS) | N17: UPCOMING BILLS (7 DAYS) | O17: UPCOMING BILLS (7 DAYS) | P17: UPCOMING BILLS (7 DAYS) | R17: =$A40 -> Health & Fitness | S17: =IF($R17="Savings",0,$C40) -> 700
A18: ='MONTHLY BUDGET'!$B$37 -> 239.9 | E18: ='MONTHLY BUDGET'!$B$43 -> 16803 | I18: ='MONTHLY BUDGET'!$B$44 -> 15303 | M18: =COUNTIFS('QUICK ENTRY'!$AF$8:$AF$1007,"Yes",'QUICK ENTRY'!$O$8:$O$1007,"<>Paid",'QUICK ENTRY'!$P$8:$P$1007,">="&TODAY(),'QUICK ENTRY'!$P$8:$P$1007,"<="&TODAY()+SETTINGS!$E$8) -> 0 | R18: =$A41 -> Shopping & Gifts | S18: =IF($R18="Savings",0,$C41) -> 0
R19: =$A42 -> Emergency | S19: =IF($R19="Savings",0,$C42) -> 0
R20: =$A43 -> Savings | S20: =IF($R20="Savings",0,$C43) -> 0
A21: =IF(E13>1,"Monthly budget exceeded by INR "&TEXT((E8+M8)-'MONTHLY BUDGET'!$S$28,"#,##0"),IF(E13>0.9,"Near budget limit — only INR "&TEXT('MONTHLY BUDGET'!$U$28,"#,##0")&" remains",IF('MONTHLY BUDGET'!$W$28>'MONTHLY BUDGET'!$S$28,"Projected spending may exceed budget",IF(I8<SETTINGS!$B$17,"Available balance is below the minimum safe level","You are within budget. Safe to spend INR "&TEXT(E18,"#,##0")&" today.")))) -> You are within budget. Safe to spend INR 16,803 today. | R21: =$A44 -> Miscellaneous | S21: =IF($R21="Savings",0,$C44) -> 0
R22: =$A45 -> Shared Expenses | S22: =IF($R22="Savings",0,$C45) -> 0
R23: =$A46 -> Career | S23: =IF($R23="Savings",0,$C46) -> 0
A26: Category | B26: Budget | C26: Actual | D26: Remaining | E26: % Used | F26: Status
A27: ='MONTHLY BUDGET'!$A$8 -> College Fees | B27: ='MONTHLY BUDGET'!$S$8 -> 4500 | C27: ='MONTHLY BUDGET'!$T$8 -> 0 | D27: ='MONTHLY BUDGET'!$U$8 -> 4500 | E27: ='MONTHLY BUDGET'!$V$8 -> 0 | F27: ='MONTHLY BUDGET'!$X$8 -> Safe
A28: ='MONTHLY BUDGET'!$A$9 -> Hostel | B28: ='MONTHLY BUDGET'!$S$9 -> 3500 | C28: ='MONTHLY BUDGET'!$T$9 -> 3200 | D28: ='MONTHLY BUDGET'!$U$9 -> 300 | E28: ='MONTHLY BUDGET'!$V$9 -> 0.91428571 | F28: ='MONTHLY BUDGET'!$X$9 -> Near Limit
A29: ='MONTHLY BUDGET'!$A$10 -> Food | B29: ='MONTHLY BUDGET'!$S$10 -> 4000 | C29: ='MONTHLY BUDGET'!$T$10 -> 620 | D29: ='MONTHLY BUDGET'!$U$10 -> 3380 | E29: ='MONTHLY BUDGET'!$V$10 -> 0.155 | F29: ='MONTHLY BUDGET'!$X$10 -> Safe
A30: ='MONTHLY BUDGET'!$A$11 -> Transport | B30: ='MONTHLY BUDGET'!$S$11 -> 1500 | C30: ='MONTHLY BUDGET'!$T$11 -> 350 | D30: ='MONTHLY BUDGET'!$U$11 -> 1150 | E30: ='MONTHLY BUDGET'!$V$11 -> 0.23333333 | F30: ='MONTHLY BUDGET'!$X$11 -> Safe
A31: ='MONTHLY BUDGET'!$A$12 -> Technology | B31: ='MONTHLY BUDGET'!$S$12 -> 1500 | C31: ='MONTHLY BUDGET'!$T$12 -> 0 | D31: ='MONTHLY BUDGET'!$U$12 -> 1500 | E31: ='MONTHLY BUDGET'!$V$12 -> 0 | F31: ='MONTHLY BUDGET'!$X$12 -> Safe
A32: ='MONTHLY BUDGET'!$A$13 -> AI-ML Learning | B32: ='MONTHLY BUDGET'!$S$13 -> 1000 | C32: ='MONTHLY BUDGET'!$T$13 -> 1499 | D32: ='MONTHLY BUDGET'!$U$13 -> -499 | E32: ='MONTHLY BUDGET'!$V$13 -> 1.499 | F32: ='MONTHLY BUDGET'!$X$13 -> Over Budget
A33: ='MONTHLY BUDGET'!$A$14 -> Books & Stationery | B33: ='MONTHLY BUDGET'!$S$14 -> 500 | C33: ='MONTHLY BUDGET'!$T$14 -> 280 | D33: ='MONTHLY BUDGET'!$U$14 -> 220 | E33: ='MONTHLY BUDGET'!$V$14 -> 0.56 | F33: ='MONTHLY BUDGET'!$X$14 -> Safe
A34: ='MONTHLY BUDGET'!$A$15 -> Subscriptions | B34: ='MONTHLY BUDGET'!$S$15 -> 600 | C34: ='MONTHLY BUDGET'!$T$15 -> 199 | D34: ='MONTHLY BUDGET'!$U$15 -> 401 | E34: ='MONTHLY BUDGET'!$V$15 -> 0.33166667 | F34: ='MONTHLY BUDGET'!$X$15 -> Safe
A35: ='MONTHLY BUDGET'!$A$16 -> Mobile & Internet | B35: ='MONTHLY BUDGET'!$S$16 -> 400 | C35: ='MONTHLY BUDGET'!$T$16 -> 349 | D35: ='MONTHLY BUDGET'!$U$16 -> 51 | E35: ='MONTHLY BUDGET'!$V$16 -> 0.8725 | F35: ='MONTHLY BUDGET'!$X$16 -> Watch Spending
A36: ='MONTHLY BUDGET'!$A$17 -> Personal Care | B36: ='MONTHLY BUDGET'!$S$17 -> 500 | C36: ='MONTHLY BUDGET'!$T$17 -> 0 | D36: ='MONTHLY BUDGET'!$U$17 -> 500 | E36: ='MONTHLY BUDGET'!$V$17 -> 0 | F36: ='MONTHLY BUDGET'!$X$17 -> Safe
A37: ='MONTHLY BUDGET'!$A$18 -> Clothing | B37: ='MONTHLY BUDGET'!$S$18 -> 500 | C37: ='MONTHLY BUDGET'!$T$18 -> 0 | D37: ='MONTHLY BUDGET'!$U$18 -> 500 | E37: ='MONTHLY BUDGET'!$V$18 -> 0 | F37: ='MONTHLY BUDGET'!$X$18 -> Safe
A38: ='MONTHLY BUDGET'!$A$19 -> Entertainment | B38: ='MONTHLY BUDGET'!$S$19 -> 1000 | C38: ='MONTHLY BUDGET'!$T$19 -> 0 | D38: ='MONTHLY BUDGET'!$U$19 -> 1000 | E38: ='MONTHLY BUDGET'!$V$19 -> 0 | F38: ='MONTHLY BUDGET'!$X$19 -> Safe
A39: ='MONTHLY BUDGET'!$A$20 -> Travel Home | B39: ='MONTHLY BUDGET'!$S$20 -> 1000 | C39: ='MONTHLY BUDGET'!$T$20 -> 0 | D39: ='MONTHLY BUDGET'!$U$20 -> 1000 | E39: ='MONTHLY BUDGET'!$V$20 -> 0 | F39: ='MONTHLY BUDGET'!$X$20 -> Safe
A40: ='MONTHLY BUDGET'!$A$21 -> Health & Fitness | B40: ='MONTHLY BUDGET'!$S$21 -> 700 | C40: ='MONTHLY BUDGET'!$T$21 -> 700 | D40: ='MONTHLY BUDGET'!$U$21 -> 0 | E40: ='MONTHLY BUDGET'!$V$21 -> 1 | F40: ='MONTHLY BUDGET'!$X$21 -> Near Limit
A41: ='MONTHLY BUDGET'!$A$22 -> Shopping & Gifts | B41: ='MONTHLY BUDGET'!$S$22 -> 1000 | C41: ='MONTHLY BUDGET'!$T$22 -> 0 | D41: ='MONTHLY BUDGET'!$U$22 -> 1000 | E41: ='MONTHLY BUDGET'!$V$22 -> 0 | F41: ='MONTHLY BUDGET'!$X$22 -> Safe
A42: ='MONTHLY BUDGET'!$A$23 -> Emergency | B42: ='MONTHLY BUDGET'!$S$23 -> 500 | C42: ='MONTHLY BUDGET'!$T$23 -> 0 | D42: ='MONTHLY BUDGET'!$U$23 -> 500 | E42: ='MONTHLY BUDGET'!$V$23 -> 0 | F42: ='MONTHLY BUDGET'!$X$23 -> Safe
A43: ='MONTHLY BUDGET'!$A$24 -> Savings | B43: ='MONTHLY BUDGET'!$S$24 -> 2000 | C43: ='MONTHLY BUDGET'!$T$24 -> 2500 | D43: ='MONTHLY BUDGET'!$U$24 -> -500 | E43: ='MONTHLY BUDGET'!$V$24 -> 1.25 | F43: ='MONTHLY BUDGET'!$X$24 -> Over Budget
A44: ='MONTHLY BUDGET'!$A$25 -> Miscellaneous | B44: ='MONTHLY BUDGET'!$S$25 -> 800 | C44: ='MONTHLY BUDGET'!$T$25 -> 0 | D44: ='MONTHLY BUDGET'!$U$25 -> 800 | E44: ='MONTHLY BUDGET'!$V$25 -> 0 | F44: ='MONTHLY BUDGET'!$X$25 -> Safe
A45: ='MONTHLY BUDGET'!$A$26 -> Shared Expenses | B45: ='MONTHLY BUDGET'!$S$26 -> 500 | C45: ='MONTHLY BUDGET'!$T$26 -> 0 | D45: ='MONTHLY BUDGET'!$U$26 -> 500 | E45: ='MONTHLY BUDGET'!$V$26 -> 0 | F45: ='MONTHLY BUDGET'!$X$26 -> Safe
A46: ='MONTHLY BUDGET'!$A$27 -> Career | B46: ='MONTHLY BUDGET'!$S$27 -> 500 | C46: ='MONTHLY BUDGET'!$T$27 -> 0 | D46: ='MONTHLY BUDGET'!$U$27 -> 500 | E46: ='MONTHLY BUDGET'!$V$27 -> 0 | F46: ='MONTHLY BUDGET'!$X$27 -> Safe

Sheet QUICK ENTRY
A1: QUICK ENTRY · MASTER TRANSACTIONS | B1: QUICK ENTRY · MASTER TRANSACTIONS | C1: QUICK ENTRY · MASTER TRANSACTIONS | D1: QUICK ENTRY · MASTER TRANSACTIONS | E1: QUICK ENTRY · MASTER TRANSACTIONS | F1: QUICK ENTRY · MASTER TRANSACTIONS | G1: QUICK ENTRY · MASTER TRANSACTIONS | H1: QUICK ENTRY · MASTER TRANSACTIONS | I1: QUICK ENTRY · MASTER TRANSACTIONS | J1: QUICK ENTRY · MASTER TRANSACTIONS | K1: QUICK ENTRY · MASTER TRANSACTIONS | L1: QUICK ENTRY · MASTER TRANSACTIONS | M1: QUICK ENTRY · MASTER TRANSACTIONS | N1: QUICK ENTRY · MASTER TRANSACTIONS | O1: QUICK ENTRY · MASTER TRANSACTIONS | P1: QUICK ENTRY · MASTER TRANSACTIONS | Q1: QUICK ENTRY · MASTER TRANSACTIONS | R1: QUICK ENTRY · MASTER TRANSACTIONS | S1: QUICK ENTRY · MASTER TRANSACTIONS | T1: QUICK ENTRY · MASTER TRANSACTIONS | U1: QUICK ENTRY · MASTER TRANSACTIONS | V1: QUICK ENTRY · MASTER TRANSACTIONS | W1: QUICK ENTRY · MASTER TRANSACTIONS | X1: QUICK ENTRY · MASTER TRANSACTIONS | Y1: QUICK ENTRY · MASTER TRANSACTIONS | Z1: QUICK ENTRY · MASTER TRANSACTIONS | AA1: QUICK ENTRY · MASTER TRANSACTIONS | AB1: QUICK ENTRY · MASTER TRANSACTIONS | AC1: QUICK ENTRY · MASTER TRANSACTIONS | AD1: QUICK ENTRY · MASTER TRANSACTIONS | AE1: QUICK ENTRY · MASTER TRANSACTIONS | AF1: QUICK ENTRY · MASTER TRANSACTIONS | AG1: QUICK ENTRY · MASTER TRANSACTIONS
A2: QUICK ENTRY · MASTER TRANSACTIONS | B2: QUICK ENTRY · MASTER TRANSACTIONS | C2: QUICK ENTRY · MASTER TRANSACTIONS | D2: QUICK ENTRY · MASTER TRANSACTIONS | E2: QUICK ENTRY · MASTER TRANSACTIONS | F2: QUICK ENTRY · MASTER TRANSACTIONS | G2: QUICK ENTRY · MASTER TRANSACTIONS | H2: QUICK ENTRY · MASTER TRANSACTIONS | I2: QUICK ENTRY · MASTER TRANSACTIONS | J2: QUICK ENTRY · MASTER TRANSACTIONS | K2: QUICK ENTRY · MASTER TRANSACTIONS | L2: QUICK ENTRY · MASTER TRANSACTIONS | M2: QUICK ENTRY · MASTER TRANSACTIONS | N2: QUICK ENTRY · MASTER TRANSACTIONS | O2: QUICK ENTRY · MASTER TRANSACTIONS | P2: QUICK ENTRY · MASTER TRANSACTIONS | Q2: QUICK ENTRY · MASTER TRANSACTIONS | R2: QUICK ENTRY · MASTER TRANSACTIONS | S2: QUICK ENTRY · MASTER TRANSACTIONS | T2: QUICK ENTRY · MASTER TRANSACTIONS | U2: QUICK ENTRY · MASTER TRANSACTIONS | V2: QUICK ENTRY · MASTER TRANSACTIONS | W2: QUICK ENTRY · MASTER TRANSACTIONS | X2: QUICK ENTRY · MASTER TRANSACTIONS | Y2: QUICK ENTRY · MASTER TRANSACTIONS | Z2: QUICK ENTRY · MASTER TRANSACTIONS | AA2: QUICK ENTRY · MASTER TRANSACTIONS | AB2: QUICK ENTRY · MASTER TRANSACTIONS | AC2: QUICK ENTRY · MASTER TRANSACTIONS | AD2: QUICK ENTRY · MASTER TRANSACTIONS | AE2: QUICK ENTRY · MASTER TRANSACTIONS | AF2: QUICK ENTRY · MASTER TRANSACTIONS | AG2: QUICK ENTRY · MASTER TRANSACTIONS
A3: Enter each transaction once. Keep the first seven columns together for phone-friendly entry; blue fields calculate automatically. | B3: Enter each transaction once. Keep the first seven columns together for phone-friendly entry; blue fields calculate automatically. | C3: Enter each transaction once. Keep the first seven columns together for phone-friendly entry; blue fields calculate automatically. | D3: Enter each transaction once. Keep the first seven columns together for phone-friendly entry; blue fields calculate automatically. | E3: Enter each transaction once. Keep the first seven columns together for phone-friendly entry; blue fields calculate automatically. | F3: Enter each transaction once. Keep the first seven columns together for phone-friendly entry; blue fields calculate automatically. | G3: Enter each transaction once. Keep the first seven columns together for phone-friendly entry; blue fields calculate automatically. | H3: Enter each transaction once. Keep the first seven columns together for phone-friendly entry; blue fields calculate automatically. | I3: Enter each transaction once. Keep the first seven columns together for phone-friendly entry; blue fields calculate automatically. | J3: Enter each transaction once. Keep the first seven columns together for phone-friendly entry; blue fields calculate automatically. | K3: Enter each transaction once. Keep the first seven columns together for phone-friendly entry; blue fields calculate automatically. | L3: Enter each transaction once. Keep the first seven columns together for phone-friendly entry; blue fields calculate automatically. | M3: Enter each transaction once. Keep the first seven columns together for phone-friendly entry; blue fields calculate automatically. | N3: Enter each transaction once. Keep the first seven columns together for phone-friendly entry; blue fields calculate automatically. | O3: Enter each transaction once. Keep the first seven columns together for phone-friendly entry; blue fields calculate automatically. | P3: Enter each transaction once. Keep the first seven columns together for phone-friendly entry; blue fields calculate automatically. | Q3: Enter each transaction once. Keep the first seven columns together for phone-friendly entry; blue fields calculate automatically. | R3: Enter each transaction once. Keep the first seven columns together for phone-friendly entry; blue fields calculate automatically. | S3: Enter each transaction once. Keep the first seven columns together for phone-friendly entry; blue fields calculate automatically. | T3: Enter each transaction once. Keep the first seven columns together for phone-friendly entry; blue fields calculate automatically. | U3: Enter each transaction once. Keep the first seven columns together for phone-friendly entry; blue fields calculate automatically. | V3: Enter each transaction once. Keep the first seven columns together for phone-friendly entry; blue fields calculate automatically. | W3: Enter each transaction once. Keep the first seven columns together for phone-friendly entry; blue fields calculate automatically. | X3: Enter each transaction once. Keep the first seven columns together for phone-friendly entry; blue fields calculate automatically. | Y3: Enter each transaction once. Keep the first seven columns together for phone-friendly entry; blue fields calculate automatically. | Z3: Enter each transaction once. Keep the first seven columns together for phone-friendly entry; blue fields calculate automatically. | AA3: Enter each transaction once. Keep the first seven columns together for phone-friendly entry; blue fields calculate automatically. | AB3: Enter each transaction once. Keep the first seven columns together for phone-friendly entry; blue fields calculate automatically. | AC3: Enter each transaction once. Keep the first seven columns together for phone-friendly entry; blue fields calculate automatically. | AD3: Enter each transaction once. Keep the first seven columns together for phone-friendly entry; blue fields calculate automatically. | AE3: Enter each transaction once. Keep the first seven columns together for phone-friendly entry; blue fields calculate automatically. | AF3: Enter each transaction once. Keep the first seven columns together for phone-friendly entry; blue fields calculate automatically. | AG3: Enter each transaction once. Keep the first seven columns together for phone-friendly entry; blue fields calculate automatically.
A5: CORE INPUTS — complete these first | B5: CORE INPUTS — complete these first | C5: CORE INPUTS — complete these first | D5: CORE INPUTS — complete these first | E5: CORE INPUTS — complete these first | F5: CORE INPUTS — complete these first | G5: CORE INPUTS — complete these first | H5: OPTIONAL DETAILS + AUTOMATIC SYSTEM FIELDS | I5: OPTIONAL DETAILS + AUTOMATIC SYSTEM FIELDS | J5: OPTIONAL DETAILS + AUTOMATIC SYSTEM FIELDS | K5: OPTIONAL DETAILS + AUTOMATIC SYSTEM FIELDS | L5: OPTIONAL DETAILS + AUTOMATIC SYSTEM FIELDS | M5: OPTIONAL DETAILS + AUTOMATIC SYSTEM FIELDS | N5: OPTIONAL DETAILS + AUTOMATIC SYSTEM FIELDS | O5: OPTIONAL DETAILS + AUTOMATIC SYSTEM FIELDS | P5: OPTIONAL DETAILS + AUTOMATIC SYSTEM FIELDS | Q5: OPTIONAL DETAILS + AUTOMATIC SYSTEM FIELDS | R5: OPTIONAL DETAILS + AUTOMATIC SYSTEM FIELDS | S5: OPTIONAL DETAILS + AUTOMATIC SYSTEM FIELDS | T5: OPTIONAL DETAILS + AUTOMATIC SYSTEM FIELDS | U5: OPTIONAL DETAILS + AUTOMATIC SYSTEM FIELDS | V5: OPTIONAL DETAILS + AUTOMATIC SYSTEM FIELDS | W5: OPTIONAL DETAILS + AUTOMATIC SYSTEM FIELDS | X5: OPTIONAL DETAILS + AUTOMATIC SYSTEM FIELDS | Y5: OPTIONAL DETAILS + AUTOMATIC SYSTEM FIELDS | Z5: OPTIONAL DETAILS + AUTOMATIC SYSTEM FIELDS | AA5: OPTIONAL DETAILS + AUTOMATIC SYSTEM FIELDS | AB5: OPTIONAL DETAILS + AUTOMATIC SYSTEM FIELDS | AC5: OPTIONAL DETAILS + AUTOMATIC SYSTEM FIELDS | AD5: OPTIONAL DETAILS + AUTOMATIC SYSTEM FIELDS | AE5: OPTIONAL DETAILS + AUTOMATIC SYSTEM FIELDS | AF5: OPTIONAL DETAILS + AUTOMATIC SYSTEM FIELDS | AG5: OPTIONAL DETAILS + AUTOMATIC SYSTEM FIELDS
A7: Include? | B7: Date | C7: Type | D7: Description | E7: Amount | F7: Payment Method | G7: Category Override | H7: Suggested Category | I7: Final Category | J7: Subcategory | K7: Merchant / Vendor | L7: Account | M7: Need / Want | N7: Recurring? | O7: Payment Status | P7: Due Date | Q7: Paid By | R7: Semester | S7: Tag | T7: Planned Amount | U7: Transaction ID | V7: Month | W7: Month No | X7: Year | Y7: Day | Z7: Day Type | AA7: Duplicate Check | AB7: Unusual Check | AC7: Demo? | AD7: Notes | AE7: Receipt / File Link | AF7: Report? | AG7: Data Quality
A8: Yes | B8: 46023 | C8: Income | D8: Monthly Allowance - January | E8: 25000 | F8: UPI | G8: Miscellaneous | H8: =IF(D8="","",IF(ISNUMBER(SEARCH(SETTINGS!$K$4,D8)),SETTINGS!$L$4,IF(ISNUMBER(SEARCH(SETTINGS!$K$5,D8)),SETTINGS!$L$5,IF(ISNUMBER(SEARCH(SETTINGS!$K$6,D8)),SETTINGS!$L$6,IF(ISNUMBER(SEARCH(SETTINGS!$K$7,D8)),SETTINGS!$L$7,IF(ISNUMBER(SEARCH(SETTINGS!$K$8,D8)),SETTINGS!$L$8,IF(ISNUMBER(SEARCH(SETTINGS!$K$9,D8)),SETTINGS!$L$9,IF(ISNUMBER(SEARCH(SETTINGS!$K$10,D8)),SETTINGS!$L$10,IF(ISNUMBER(SEARCH(SETTINGS!$K$11,D8)),SETTINGS!$L$11,IF(ISNUMBER(SEARCH(SETTINGS!$K$12,D8)),SETTINGS!$L$12,IF(ISNUMBER(SEARCH(SETTINGS!$K$13,D8)),SETTINGS!$L$13,IF(ISNUMBER(SEARCH(SETTINGS!$K$14,D8)),SETTINGS!$L$14,IF(ISNUMBER(SEARCH(SETTINGS!$K$15,D8)),SETTINGS!$L$15,IF(ISNUMBER(SEARCH(SETTINGS!$K$16,D8)),SETTINGS!$L$16,IF(ISNUMBER(SEARCH(SETTINGS!$K$17,D8)),SETTINGS!$L$17,IF(ISNUMBER(SEARCH(SETTINGS!$K$18,D8)),SETTINGS!$L$18,"Miscellaneous")))))))))))))))) -> Miscellaneous | I8: =IF(B8="","",IF(G8<>"",G8,H8)) -> Miscellaneous | J8: Monthly Allowance | L8: UPI-linked Bank | M8: Essential | N8: Recurring | O8: Paid | Q8: Self | R8: Not Applicable | S8: Home | U8: =IF(B8="","",IF(C8="Income","INC-",IF(C8="Expense","EXP-","TRX-"))&TEXT(YEAR(B8),"0000")&"-"&TEXT(ROW()-7,"0000")) -> INC-2026-0001 | V8: =IF(B8="","",TEXT(B8,"mmmm")) -> January | W8: =IF(B8="","",MONTH(B8)) -> 1 | X8: =IF(B8="","",YEAR(B8)) -> 2026 | Y8: =IF(B8="","",DAY(B8)) -> 1 | Z8: =IF(B8="","",IF(WEEKDAY(B8,2)>5,"Weekend","Weekday")) -> Weekday | AA8: =IF(B8="","",IF(COUNTIFS($B$8:$B$1007,B8,$E$8:$E$1007,E8,$D$8:$D$1007,D8,$I$8:$I$1007,I8)>1,"Possible Duplicate","OK")) -> OK | AB8: =IF(OR(B8="",C8<>"Expense"),"",IF(E8>IFERROR(AVERAGEIFS($E$8:$E$1007,$I$8:$I$1007,I8,$C$8:$C$1007,"Expense")*SETTINGS!$B$20,0),"Unusually High","Normal")) | AC8: Yes | AF8: =IF(A8<>"Yes","No",IF(AND(AC8="Yes",SETTINGS!$B$16="No"),"No","Yes")) -> Yes | AG8: =IF(A8<>"Yes","",IF(OR(B8="",D8="",E8<=0,F8="",I8=""),"Check Required Fields",IF(AA8="Possible Duplicate","Possible Duplicate",IF(E8>SETTINGS!$B$22,"Review Extreme Value","OK")))) -> OK
A9: Yes | B9: 46027 | C9: Expense | D9: Semester tuition installment | E9: 4500 | F9: Bank Transfer | G9: College Fees | H9: =IF(D9="","",IF(ISNUMBER(SEARCH(SETTINGS!$K$4,D9)),SETTINGS!$L$4,IF(ISNUMBER(SEARCH(SETTINGS!$K$5,D9)),SETTINGS!$L$5,IF(ISNUMBER(SEARCH(SETTINGS!$K$6,D9)),SETTINGS!$L$6,IF(ISNUMBER(SEARCH(SETTINGS!$K$7,D9)),SETTINGS!$L$7,IF(ISNUMBER(SEARCH(SETTINGS!$K$8,D9)),SETTINGS!$L$8,IF(ISNUMBER(SEARCH(SETTINGS!$K$9,D9)),SETTINGS!$L$9,IF(ISNUMBER(SEARCH(SETTINGS!$K$10,D9)),SETTINGS!$L$10,IF(ISNUMBER(SEARCH(SETTINGS!$K$11,D9)),SETTINGS!$L$11,IF(ISNUMBER(SEARCH(SETTINGS!$K$12,D9)),SETTINGS!$L$12,IF(ISNUMBER(SEARCH(SETTINGS!$K$13,D9)),SETTINGS!$L$13,IF(ISNUMBER(SEARCH(SETTINGS!$K$14,D9)),SETTINGS!$L$14,IF(ISNUMBER(SEARCH(SETTINGS!$K$15,D9)),SETTINGS!$L$15,IF(ISNUMBER(SEARCH(SETTINGS!$K$16,D9)),SETTINGS!$L$16,IF(ISNUMBER(SEARCH(SETTINGS!$K$17,D9)),SETTINGS!$L$17,IF(ISNUMBER(SEARCH(SETTINGS!$K$18,D9)),SETTINGS!$L$18,"Miscellaneous")))))))))))))))) -> College Fees | I9: =IF(B9="","",IF(G9<>"",G9,H9)) -> College Fees | J9: Tuition | K9: College | L9: UPI-linked Bank | M9: Essential | N9: One-Time | O9: Paid | Q9: Parents | R9: Semester 1 | S9: College | U9: =IF(B9="","",IF(C9="Income","INC-",IF(C9="Expense","EXP-","TRX-"))&TEXT(YEAR(B9),"0000")&"-"&TEXT(ROW()-7,"0000")) -> EXP-2026-0002 | V9: =IF(B9="","",TEXT(B9,"mmmm")) -> January | W9: =IF(B9="","",MONTH(B9)) -> 1 | X9: =IF(B9="","",YEAR(B9)) -> 2026 | Y9: =IF(B9="","",DAY(B9)) -> 5 | Z9: =IF(B9="","",IF(WEEKDAY(B9,2)>5,"Weekend","Weekday")) -> Weekday | AA9: =IF(B9="","",IF(COUNTIFS($B$8:$B$1007,B9,$E$8:$E$1007,E9,$D$8:$D$1007,D9,$I$8:$I$1007,I9)>1,"Possible Duplicate","OK")) -> OK | AB9: =IF(OR(B9="",C9<>"Expense"),"",IF(E9>IFERROR(AVERAGEIFS($E$8:$E$1007,$I$8:$I$1007,I9,$C$8:$C$1007,"Expense")*SETTINGS!$B$20,0),"Unusually High","Normal")) -> Normal | AC9: Yes | AF9: =IF(A9<>"Yes","No",IF(AND(AC9="Yes",SETTINGS!$B$16="No"),"No","Yes")) -> Yes | AG9: =IF(A9<>"Yes","",IF(OR(B9="",D9="",E9<=0,F9="",I9=""),"Check Required Fields",IF(AA9="Possible Duplicate","Possible Duplicate",IF(E9>SETTINGS!$B$22,"Review Extreme Value","OK")))) -> OK
A10: Yes | B10: 46030 | C10: Expense | D10: Hostel Fee | E10: 3500 | F10: Bank Transfer | G10: Hostel | H10: =IF(D10="","",IF(ISNUMBER(SEARCH(SETTINGS!$K$4,D10)),SETTINGS!$L$4,IF(ISNUMBER(SEARCH(SETTINGS!$K$5,D10)),SETTINGS!$L$5,IF(ISNUMBER(SEARCH(SETTINGS!$K$6,D10)),SETTINGS!$L$6,IF(ISNUMBER(SEARCH(SETTINGS!$K$7,D10)),SETTINGS!$L$7,IF(ISNUMBER(SEARCH(SETTINGS!$K$8,D10)),SETTINGS!$L$8,IF(ISNUMBER(SEARCH(SETTINGS!$K$9,D10)),SETTINGS!$L$9,IF(ISNUMBER(SEARCH(SETTINGS!$K$10,D10)),SETTINGS!$L$10,IF(ISNUMBER(SEARCH(SETTINGS!$K$11,D10)),SETTINGS!$L$11,IF(ISNUMBER(SEARCH(SETTINGS!$K$12,D10)),SETTINGS!$L$12,IF(ISNUMBER(SEARCH(SETTINGS!$K$13,D10)),SETTINGS!$L$13,IF(ISNUMBER(SEARCH(SETTINGS!$K$14,D10)),SETTINGS!$L$14,IF(ISNUMBER(SEARCH(SETTINGS!$K$15,D10)),SETTINGS!$L$15,IF(ISNUMBER(SEARCH(SETTINGS!$K$16,D10)),SETTINGS!$L$16,IF(ISNUMBER(SEARCH(SETTINGS!$K$17,D10)),SETTINGS!$L$17,IF(ISNUMBER(SEARCH(SETTINGS!$K$18,D10)),SETTINGS!$L$18,"Miscellaneous")))))))))))))))) -> Miscellaneous | I10: =IF(B10="","",IF(G10<>"",G10,H10)) -> Hostel | J10: Hostel Fee | K10: College Hostel | L10: UPI-linked Bank | M10: Essential | N10: One-Time | O10: Paid | Q10: Parents | R10: Semester 1 | S10: Hostel | U10: =IF(B10="","",IF(C10="Income","INC-",IF(C10="Expense","EXP-","TRX-"))&TEXT(YEAR(B10),"0000")&"-"&TEXT(ROW()-7,"0000")) -> EXP-2026-0003 | V10: =IF(B10="","",TEXT(B10,"mmmm")) -> January | W10: =IF(B10="","",MONTH(B10)) -> 1 | X10: =IF(B10="","",YEAR(B10)) -> 2026 | Y10: =IF(B10="","",DAY(B10)) -> 8 | Z10: =IF(B10="","",IF(WEEKDAY(B10,2)>5,"Weekend","Weekday")) -> Weekday | AA10: =IF(B10="","",IF(COUNTIFS($B$8:$B$1007,B10,$E$8:$E$1007,E10,$D$8:$D$1007,D10,$I$8:$I$1007,I10)>1,"Possible Duplicate","OK")) -> OK | AB10: =IF(OR(B10="",C10<>"Expense"),"",IF(E10>IFERROR(AVERAGEIFS($E$8:$E$1007,$I$8:$I$1007,I10,$C$8:$C$1007,"Expense")*SETTINGS!$B$20,0),"Unusually High","Normal")) -> Normal | AC10: Yes | AF10: =IF(A10<>"Yes","No",IF(AND(AC10="Yes",SETTINGS!$B$16="No"),"No","Yes")) -> Yes | AG10: =IF(A10<>"Yes","",IF(OR(B10="",D10="",E10<=0,F10="",I10=""),"Check Required Fields",IF(AA10="Possible Duplicate","Possible Duplicate",IF(E10>SETTINGS!$B$22,"Review Extreme Value","OK")))) -> OK
A11: Yes | B11: 46054 | C11: Income | D11: Monthly Allowance - February | E11: 25000 | F11: UPI | G11: Miscellaneous | H11: =IF(D11="","",IF(ISNUMBER(SEARCH(SETTINGS!$K$4,D11)),SETTINGS!$L$4,IF(ISNUMBER(SEARCH(SETTINGS!$K$5,D11)),SETTINGS!$L$5,IF(ISNUMBER(SEARCH(SETTINGS!$K$6,D11)),SETTINGS!$L$6,IF(ISNUMBER(SEARCH(SETTINGS!$K$7,D11)),SETTINGS!$L$7,IF(ISNUMBER(SEARCH(SETTINGS!$K$8,D11)),SETTINGS!$L$8,IF(ISNUMBER(SEARCH(SETTINGS!$K$9,D11)),SETTINGS!$L$9,IF(ISNUMBER(SEARCH(SETTINGS!$K$10,D11)),SETTINGS!$L$10,IF(ISNUMBER(SEARCH(SETTINGS!$K$11,D11)),SETTINGS!$L$11,IF(ISNUMBER(SEARCH(SETTINGS!$K$12,D11)),SETTINGS!$L$12,IF(ISNUMBER(SEARCH(SETTINGS!$K$13,D11)),SETTINGS!$L$13,IF(ISNUMBER(SEARCH(SETTINGS!$K$14,D11)),SETTINGS!$L$14,IF(ISNUMBER(SEARCH(SETTINGS!$K$15,D11)),SETTINGS!$L$15,IF(ISNUMBER(SEARCH(SETTINGS!$K$16,D11)),SETTINGS!$L$16,IF(ISNUMBER(SEARCH(SETTINGS!$K$17,D11)),SETTINGS!$L$17,IF(ISNUMBER(SEARCH(SETTINGS!$K$18,D11)),SETTINGS!$L$18,"Miscellaneous")))))))))))))))) -> Miscellaneous | I11: =IF(B11="","",IF(G11<>"",G11,H11)) -> Miscellaneous | J11: Monthly Allowance | L11: UPI-linked Bank | M11: Essential | N11: Recurring | O11: Paid | Q11: Self | R11: Not Applicable | S11: Home | U11: =IF(B11="","",IF(C11="Income","INC-",IF(C11="Expense","EXP-","TRX-"))&TEXT(YEAR(B11),"0000")&"-"&TEXT(ROW()-7,"0000")) -> INC-2026-0004 | V11: =IF(B11="","",TEXT(B11,"mmmm")) -> February | W11: =IF(B11="","",MONTH(B11)) -> 2 | X11: =IF(B11="","",YEAR(B11)) -> 2026 | Y11: =IF(B11="","",DAY(B11)) -> 1 | Z11: =IF(B11="","",IF(WEEKDAY(B11,2)>5,"Weekend","Weekday")) -> Weekend | AA11: =IF(B11="","",IF(COUNTIFS($B$8:$B$1007,B11,$E$8:$E$1007,E11,$D$8:$D$1007,D11,$I$8:$I$1007,I11)>1,"Possible Duplicate","OK")) -> OK | AB11: =IF(OR(B11="",C11<>"Expense"),"",IF(E11>IFERROR(AVERAGEIFS($E$8:$E$1007,$I$8:$I$1007,I11,$C$8:$C$1007,"Expense")*SETTINGS!$B$20,0),"Unusually High","Normal")) | AC11: Yes | AF11: =IF(A11<>"Yes","No",IF(AND(AC11="Yes",SETTINGS!$B$16="No"),"No","Yes")) -> Yes | AG11: =IF(A11<>"Yes","",IF(OR(B11="",D11="",E11<=0,F11="",I11=""),"Check Required Fields",IF(AA11="Possible Duplicate","Possible Duplicate",IF(E11>SETTINGS!$B$22,"Review Extreme Value","OK")))) -> OK
A12: Yes | B12: 46065 | C12: Expense | D12: Groceries and fruit | E12: 3200 | F12: UPI | G12: Food | H12: =IF(D12="","",IF(ISNUMBER(SEARCH(SETTINGS!$K$4,D12)),SETTINGS!$L$4,IF(ISNUMBER(SEARCH(SETTINGS!$K$5,D12)),SETTINGS!$L$5,IF(ISNUMBER(SEARCH(SETTINGS!$K$6,D12)),SETTINGS!$L$6,IF(ISNUMBER(SEARCH(SETTINGS!$K$7,D12)),SETTINGS!$L$7,IF(ISNUMBER(SEARCH(SETTINGS!$K$8,D12)),SETTINGS!$L$8,IF(ISNUMBER(SEARCH(SETTINGS!$K$9,D12)),SETTINGS!$L$9,IF(ISNUMBER(SEARCH(SETTINGS!$K$10,D12)),SETTINGS!$L$10,IF(ISNUMBER(SEARCH(SETTINGS!$K$11,D12)),SETTINGS!$L$11,IF(ISNUMBER(SEARCH(SETTINGS!$K$12,D12)),SETTINGS!$L$12,IF(ISNUMBER(SEARCH(SETTINGS!$K$13,D12)),SETTINGS!$L$13,IF(ISNUMBER(SEARCH(SETTINGS!$K$14,D12)),SETTINGS!$L$14,IF(ISNUMBER(SEARCH(SETTINGS!$K$15,D12)),SETTINGS!$L$15,IF(ISNUMBER(SEARCH(SETTINGS!$K$16,D12)),SETTINGS!$L$16,IF(ISNUMBER(SEARCH(SETTINGS!$K$17,D12)),SETTINGS!$L$17,IF(ISNUMBER(SEARCH(SETTINGS!$K$18,D12)),SETTINGS!$L$18,"Miscellaneous")))))))))))))))) -> Miscellaneous | I12: =IF(B12="","",IF(G12<>"",G12,H12)) -> Food | J12: Grocery | K12: Local Market | L12: UPI-linked Bank | M12: Essential | N12: One-Time | O12: Paid | Q12: Self | R12: Not Applicable | S12: Hostel | U12: =IF(B12="","",IF(C12="Income","INC-",IF(C12="Expense","EXP-","TRX-"))&TEXT(YEAR(B12),"0000")&"-"&TEXT(ROW()-7,"0000")) -> EXP-2026-0005 | V12: =IF(B12="","",TEXT(B12,"mmmm")) -> February | W12: =IF(B12="","",MONTH(B12)) -> 2 | X12: =IF(B12="","",YEAR(B12)) -> 2026 | Y12: =IF(B12="","",DAY(B12)) -> 12 | Z12: =IF(B12="","",IF(WEEKDAY(B12,2)>5,"Weekend","Weekday")) -> Weekday | AA12: =IF(B12="","",IF(COUNTIFS($B$8:$B$1007,B12,$E$8:$E$1007,E12,$D$8:$D$1007,D12,$I$8:$I$1007,I12)>1,"Possible Duplicate","OK")) -> OK | AB12: =IF(OR(B12="",C12<>"Expense"),"",IF(E12>IFERROR(AVERAGEIFS($E$8:$E$1007,$I$8:$I$1007,I12,$C$8:$C$1007,"Expense")*SETTINGS!$B$20,0),"Unusually High","Normal")) -> Normal | AC12: Yes | AF12: =IF(A12<>"Yes","No",IF(AND(AC12="Yes",SETTINGS!$B$16="No"),"No","Yes")) -> Yes | AG12: =IF(A12<>"Yes","",IF(OR(B12="",D12="",E12<=0,F12="",I12=""),"Check Required Fields",IF(AA12="Possible Duplicate","Possible Duplicate",IF(E12>SETTINGS!$B$22,"Review Extreme Value","OK")))) -> OK
A13: Yes | B13: 46071 | C13: Expense | D13: Bus and metro commute | E13: 1200 | F13: UPI | G13: Transport | H13: =IF(D13="","",IF(ISNUMBER(SEARCH(SETTINGS!$K$4,D13)),SETTINGS!$L$4,IF(ISNUMBER(SEARCH(SETTINGS!$K$5,D13)),SETTINGS!$L$5,IF(ISNUMBER(SEARCH(SETTINGS!$K$6,D13)),SETTINGS!$L$6,IF(ISNUMBER(SEARCH(SETTINGS!$K$7,D13)),SETTINGS!$L$7,IF(ISNUMBER(SEARCH(SETTINGS!$K$8,D13)),SETTINGS!$L$8,IF(ISNUMBER(SEARCH(SETTINGS!$K$9,D13)),SETTINGS!$L$9,IF(ISNUMBER(SEARCH(SETTINGS!$K$10,D13)),SETTINGS!$L$10,IF(ISNUMBER(SEARCH(SETTINGS!$K$11,D13)),SETTINGS!$L$11,IF(ISNUMBER(SEARCH(SETTINGS!$K$12,D13)),SETTINGS!$L$12,IF(ISNUMBER(SEARCH(SETTINGS!$K$13,D13)),SETTINGS!$L$13,IF(ISNUMBER(SEARCH(SETTINGS!$K$14,D13)),SETTINGS!$L$14,IF(ISNUMBER(SEARCH(SETTINGS!$K$15,D13)),SETTINGS!$L$15,IF(ISNUMBER(SEARCH(SETTINGS!$K$16,D13)),SETTINGS!$L$16,IF(ISNUMBER(SEARCH(SETTINGS!$K$17,D13)),SETTINGS!$L$17,IF(ISNUMBER(SEARCH(SETTINGS!$K$18,D13)),SETTINGS!$L$18,"Miscellaneous")))))))))))))))) -> Miscellaneous | I13: =IF(B13="","",IF(G13<>"",G13,H13)) -> Transport | J13: Metro | K13: Transit | L13: UPI-linked Bank | M13: Useful | N13: One-Time | O13: Paid | Q13: Self | R13: Not Applicable | S13: College | U13: =IF(B13="","",IF(C13="Income","INC-",IF(C13="Expense","EXP-","TRX-"))&TEXT(YEAR(B13),"0000")&"-"&TEXT(ROW()-7,"0000")) -> EXP-2026-0006 | V13: =IF(B13="","",TEXT(B13,"mmmm")) -> February | W13: =IF(B13="","",MONTH(B13)) -> 2 | X13: =IF(B13="","",YEAR(B13)) -> 2026 | Y13: =IF(B13="","",DAY(B13)) -> 18 | Z13: =IF(B13="","",IF(WEEKDAY(B13,2)>5,"Weekend","Weekday")) -> Weekday | AA13: =IF(B13="","",IF(COUNTIFS($B$8:$B$1007,B13,$E$8:$E$1007,E13,$D$8:$D$1007,D13,$I$8:$I$1007,I13)>1,"Possible Duplicate","OK")) -> OK | AB13: =IF(OR(B13="",C13<>"Expense"),"",IF(E13>IFERROR(AVERAGEIFS($E$8:$E$1007,$I$8:$I$1007,I13,$C$8:$C$1007,"Expense")*SETTINGS!$B$20,0),"Unusually High","Normal")) -> Normal | AC13: Yes | AF13: =IF(A13<>"Yes","No",IF(AND(AC13="Yes",SETTINGS!$B$16="No"),"No","Yes")) -> Yes | AG13: =IF(A13<>"Yes","",IF(OR(B13="",D13="",E13<=0,F13="",I13=""),"Check Required Fields",IF(AA13="Possible Duplicate","Possible Duplicate",IF(E13>SETTINGS!$B$22,"Review Extreme Value","OK")))) -> OK
A14: Yes | B14: 46082 | C14: Income | D14: Monthly Allowance - March | E14: 25000 | F14: UPI | G14: Miscellaneous | H14: =IF(D14="","",IF(ISNUMBER(SEARCH(SETTINGS!$K$4,D14)),SETTINGS!$L$4,IF(ISNUMBER(SEARCH(SETTINGS!$K$5,D14)),SETTINGS!$L$5,IF(ISNUMBER(SEARCH(SETTINGS!$K$6,D14)),SETTINGS!$L$6,IF(ISNUMBER(SEARCH(SETTINGS!$K$7,D14)),SETTINGS!$L$7,IF(ISNUMBER(SEARCH(SETTINGS!$K$8,D14)),SETTINGS!$L$8,IF(ISNUMBER(SEARCH(SETTINGS!$K$9,D14)),SETTINGS!$L$9,IF(ISNUMBER(SEARCH(SETTINGS!$K$10,D14)),SETTINGS!$L$10,IF(ISNUMBER(SEARCH(SETTINGS!$K$11,D14)),SETTINGS!$L$11,IF(ISNUMBER(SEARCH(SETTINGS!$K$12,D14)),SETTINGS!$L$12,IF(ISNUMBER(SEARCH(SETTINGS!$K$13,D14)),SETTINGS!$L$13,IF(ISNUMBER(SEARCH(SETTINGS!$K$14,D14)),SETTINGS!$L$14,IF(ISNUMBER(SEARCH(SETTINGS!$K$15,D14)),SETTINGS!$L$15,IF(ISNUMBER(SEARCH(SETTINGS!$K$16,D14)),SETTINGS!$L$16,IF(ISNUMBER(SEARCH(SETTINGS!$K$17,D14)),SETTINGS!$L$17,IF(ISNUMBER(SEARCH(SETTINGS!$K$18,D14)),SETTINGS!$L$18,"Miscellaneous")))))))))))))))) -> Miscellaneous | I14: =IF(B14="","",IF(G14<>"",G14,H14)) -> Miscellaneous | J14: Monthly Allowance | L14: UPI-linked Bank | M14: Essential | N14: Recurring | O14: Paid | Q14: Self | R14: Not Applicable | S14: Home | U14: =IF(B14="","",IF(C14="Income","INC-",IF(C14="Expense","EXP-","TRX-"))&TEXT(YEAR(B14),"0000")&"-"&TEXT(ROW()-7,"0000")) -> INC-2026-0007 | V14: =IF(B14="","",TEXT(B14,"mmmm")) -> March | W14: =IF(B14="","",MONTH(B14)) -> 3 | X14: =IF(B14="","",YEAR(B14)) -> 2026 | Y14: =IF(B14="","",DAY(B14)) -> 1 | Z14: =IF(B14="","",IF(WEEKDAY(B14,2)>5,"Weekend","Weekday")) -> Weekend | AA14: =IF(B14="","",IF(COUNTIFS($B$8:$B$1007,B14,$E$8:$E$1007,E14,$D$8:$D$1007,D14,$I$8:$I$1007,I14)>1,"Possible Duplicate","OK")) -> OK | AB14: =IF(OR(B14="",C14<>"Expense"),"",IF(E14>IFERROR(AVERAGEIFS($E$8:$E$1007,$I$8:$I$1007,I14,$C$8:$C$1007,"Expense")*SETTINGS!$B$20,0),"Unusually High","Normal")) | AC14: Yes | AF14: =IF(A14<>"Yes","No",IF(AND(AC14="Yes",SETTINGS!$B$16="No"),"No","Yes")) -> Yes | AG14: =IF(A14<>"Yes","",IF(OR(B14="",D14="",E14<=0,F14="",I14=""),"Check Required Fields",IF(AA14="Possible Duplicate","Possible Duplicate",IF(E14>SETTINGS!$B$22,"Review Extreme Value","OK")))) -> OK
A15: Yes | B15: 46091 | C15: Expense | D15: Laptop repair and SSD | E15: 2500 | F15: Debit Card | G15: Technology | H15: =IF(D15="","",IF(ISNUMBER(SEARCH(SETTINGS!$K$4,D15)),SETTINGS!$L$4,IF(ISNUMBER(SEARCH(SETTINGS!$K$5,D15)),SETTINGS!$L$5,IF(ISNUMBER(SEARCH(SETTINGS!$K$6,D15)),SETTINGS!$L$6,IF(ISNUMBER(SEARCH(SETTINGS!$K$7,D15)),SETTINGS!$L$7,IF(ISNUMBER(SEARCH(SETTINGS!$K$8,D15)),SETTINGS!$L$8,IF(ISNUMBER(SEARCH(SETTINGS!$K$9,D15)),SETTINGS!$L$9,IF(ISNUMBER(SEARCH(SETTINGS!$K$10,D15)),SETTINGS!$L$10,IF(ISNUMBER(SEARCH(SETTINGS!$K$11,D15)),SETTINGS!$L$11,IF(ISNUMBER(SEARCH(SETTINGS!$K$12,D15)),SETTINGS!$L$12,IF(ISNUMBER(SEARCH(SETTINGS!$K$13,D15)),SETTINGS!$L$13,IF(ISNUMBER(SEARCH(SETTINGS!$K$14,D15)),SETTINGS!$L$14,IF(ISNUMBER(SEARCH(SETTINGS!$K$15,D15)),SETTINGS!$L$15,IF(ISNUMBER(SEARCH(SETTINGS!$K$16,D15)),SETTINGS!$L$16,IF(ISNUMBER(SEARCH(SETTINGS!$K$17,D15)),SETTINGS!$L$17,IF(ISNUMBER(SEARCH(SETTINGS!$K$18,D15)),SETTINGS!$L$18,"Miscellaneous")))))))))))))))) -> Miscellaneous | I15: =IF(B15="","",IF(G15<>"",G15,H15)) -> Technology | J15: Hardware | K15: Computer Store | L15: UPI-linked Bank | M15: Essential | N15: One-Time | O15: Paid | Q15: Self | R15: Not Applicable | S15: College | U15: =IF(B15="","",IF(C15="Income","INC-",IF(C15="Expense","EXP-","TRX-"))&TEXT(YEAR(B15),"0000")&"-"&TEXT(ROW()-7,"0000")) -> EXP-2026-0008 | V15: =IF(B15="","",TEXT(B15,"mmmm")) -> March | W15: =IF(B15="","",MONTH(B15)) -> 3 | X15: =IF(B15="","",YEAR(B15)) -> 2026 | Y15: =IF(B15="","",DAY(B15)) -> 10 | Z15: =IF(B15="","",IF(WEEKDAY(B15,2)>5,"Weekend","Weekday")) -> Weekday | AA15: =IF(B15="","",IF(COUNTIFS($B$8:$B$1007,B15,$E$8:$E$1007,E15,$D$8:$D$1007,D15,$I$8:$I$1007,I15)>1,"Possible Duplicate","OK")) -> OK | AB15: =IF(OR(B15="",C15<>"Expense"),"",IF(E15>IFERROR(AVERAGEIFS($E$8:$E$1007,$I$8:$I$1007,I15,$C$8:$C$1007,"Expense")*SETTINGS!$B$20,0),"Unusually High","Normal")) -> Normal | AC15: Yes | AF15: =IF(A15<>"Yes","No",IF(AND(AC15="Yes",SETTINGS!$B$16="No"),"No","Yes")) -> Yes | AG15: =IF(A15<>"Yes","",IF(OR(B15="",D15="",E15<=0,F15="",I15=""),"Check Required Fields",IF(AA15="Possible Duplicate","Possible Duplicate",IF(E15>SETTINGS!$B$22,"Review Extreme Value","OK")))) -> OK
A16: Yes | B16: 46097 | C16: Expense | D16: Netflix and cloud subscriptions | E16: 599 | F16: UPI | G16: Subscriptions | H16: =IF(D16="","",IF(ISNUMBER(SEARCH(SETTINGS!$K$4,D16)),SETTINGS!$L$4,IF(ISNUMBER(SEARCH(SETTINGS!$K$5,D16)),SETTINGS!$L$5,IF(ISNUMBER(SEARCH(SETTINGS!$K$6,D16)),SETTINGS!$L$6,IF(ISNUMBER(SEARCH(SETTINGS!$K$7,D16)),SETTINGS!$L$7,IF(ISNUMBER(SEARCH(SETTINGS!$K$8,D16)),SETTINGS!$L$8,IF(ISNUMBER(SEARCH(SETTINGS!$K$9,D16)),SETTINGS!$L$9,IF(ISNUMBER(SEARCH(SETTINGS!$K$10,D16)),SETTINGS!$L$10,IF(ISNUMBER(SEARCH(SETTINGS!$K$11,D16)),SETTINGS!$L$11,IF(ISNUMBER(SEARCH(SETTINGS!$K$12,D16)),SETTINGS!$L$12,IF(ISNUMBER(SEARCH(SETTINGS!$K$13,D16)),SETTINGS!$L$13,IF(ISNUMBER(SEARCH(SETTINGS!$K$14,D16)),SETTINGS!$L$14,IF(ISNUMBER(SEARCH(SETTINGS!$K$15,D16)),SETTINGS!$L$15,IF(ISNUMBER(SEARCH(SETTINGS!$K$16,D16)),SETTINGS!$L$16,IF(ISNUMBER(SEARCH(SETTINGS!$K$17,D16)),SETTINGS!$L$17,IF(ISNUMBER(SEARCH(SETTINGS!$K$18,D16)),SETTINGS!$L$18,"Miscellaneous")))))))))))))))) -> Subscriptions | I16: =IF(B16="","",IF(G16<>"",G16,H16)) -> Subscriptions | J16: OTT | K16: Netflix | L16: UPI-linked Bank | M16: Optional | N16: Recurring | O16: Paid | Q16: Self | R16: Not Applicable | S16: Subscription | U16: =IF(B16="","",IF(C16="Income","INC-",IF(C16="Expense","EXP-","TRX-"))&TEXT(YEAR(B16),"0000")&"-"&TEXT(ROW()-7,"0000")) -> EXP-2026-0009 | V16: =IF(B16="","",TEXT(B16,"mmmm")) -> March | W16: =IF(B16="","",MONTH(B16)) -> 3 | X16: =IF(B16="","",YEAR(B16)) -> 2026 | Y16: =IF(B16="","",DAY(B16)) -> 16 | Z16: =IF(B16="","",IF(WEEKDAY(B16,2)>5,"Weekend","Weekday")) -> Weekday | AA16: =IF(B16="","",IF(COUNTIFS($B$8:$B$1007,B16,$E$8:$E$1007,E16,$D$8:$D$1007,D16,$I$8:$I$1007,I16)>1,"Possible Duplicate","OK")) -> OK | AB16: =IF(OR(B16="",C16<>"Expense"),"",IF(E16>IFERROR(AVERAGEIFS($E$8:$E$1007,$I$8:$I$1007,I16,$C$8:$C$1007,"Expense")*SETTINGS!$B$20,0),"Unusually High","Normal")) -> Normal | AC16: Yes | AF16: =IF(A16<>"Yes","No",IF(AND(AC16="Yes",SETTINGS!$B$16="No"),"No","Yes")) -> Yes | AG16: =IF(A16<>"Yes","",IF(OR(B16="",D16="",E16<=0,F16="",I16=""),"Check Required Fields",IF(AA16="Possible Duplicate","Possible Duplicate",IF(E16>SETTINGS!$B$22,"Review Extreme Value","OK")))) -> OK
A17: Yes | B17: 46113 | C17: Income | D17: Monthly Allowance - April | E17: 25000 | F17: UPI | G17: Miscellaneous | H17: =IF(D17="","",IF(ISNUMBER(SEARCH(SETTINGS!$K$4,D17)),SETTINGS!$L$4,IF(ISNUMBER(SEARCH(SETTINGS!$K$5,D17)),SETTINGS!$L$5,IF(ISNUMBER(SEARCH(SETTINGS!$K$6,D17)),SETTINGS!$L$6,IF(ISNUMBER(SEARCH(SETTINGS!$K$7,D17)),SETTINGS!$L$7,IF(ISNUMBER(SEARCH(SETTINGS!$K$8,D17)),SETTINGS!$L$8,IF(ISNUMBER(SEARCH(SETTINGS!$K$9,D17)),SETTINGS!$L$9,IF(ISNUMBER(SEARCH(SETTINGS!$K$10,D17)),SETTINGS!$L$10,IF(ISNUMBER(SEARCH(SETTINGS!$K$11,D17)),SETTINGS!$L$11,IF(ISNUMBER(SEARCH(SETTINGS!$K$12,D17)),SETTINGS!$L$12,IF(ISNUMBER(SEARCH(SETTINGS!$K$13,D17)),SETTINGS!$L$13,IF(ISNUMBER(SEARCH(SETTINGS!$K$14,D17)),SETTINGS!$L$14,IF(ISNUMBER(SEARCH(SETTINGS!$K$15,D17)),SETTINGS!$L$15,IF(ISNUMBER(SEARCH(SETTINGS!$K$16,D17)),SETTINGS!$L$16,IF(ISNUMBER(SEARCH(SETTINGS!$K$17,D17)),SETTINGS!$L$17,IF(ISNUMBER(SEARCH(SETTINGS!$K$18,D17)),SETTINGS!$L$18,"Miscellaneous")))))))))))))))) -> Miscellaneous | I17: =IF(B17="","",IF(G17<>"",G17,H17)) -> Miscellaneous | J17: Monthly Allowance | L17: UPI-linked Bank | M17: Essential | N17: Recurring | O17: Paid | Q17: Self | R17: Not Applicable | S17: Home | U17: =IF(B17="","",IF(C17="Income","INC-",IF(C17="Expense","EXP-","TRX-"))&TEXT(YEAR(B17),"0000")&"-"&TEXT(ROW()-7,"0000")) -> INC-2026-0010 | V17: =IF(B17="","",TEXT(B17,"mmmm")) -> April | W17: =IF(B17="","",MONTH(B17)) -> 4 | X17: =IF(B17="","",YEAR(B17)) -> 2026 | Y17: =IF(B17="","",DAY(B17)) -> 1 | Z17: =IF(B17="","",IF(WEEKDAY(B17,2)>5,"Weekend","Weekday")) -> Weekday | AA17: =IF(B17="","",IF(COUNTIFS($B$8:$B$1007,B17,$E$8:$E$1007,E17,$D$8:$D$1007,D17,$I$8:$I$1007,I17)>1,"Possible Duplicate","OK")) -> OK | AB17: =IF(OR(B17="",C17<>"Expense"),"",IF(E17>IFERROR(AVERAGEIFS($E$8:$E$1007,$I$8:$I$1007,I17,$C$8:$C$1007,"Expense")*SETTINGS!$B$20,0),"Unusually High","Normal")) | AC17: Yes | AF17: =IF(A17<>"Yes","No",IF(AND(AC17="Yes",SETTINGS!$B$16="No"),"No","Yes")) -> Yes | AG17: =IF(A17<>"Yes","",IF(OR(B17="",D17="",E17<=0,F17="",I17=""),"Check Required Fields",IF(AA17="Possible Duplicate","Possible Duplicate",IF(E17>SETTINGS!$B$22,"Review Extreme Value","OK")))) -> OK
A18: Yes | B18: 46126 | C18: Expense | D18: Mess and outside meals | E18: 3700 | F18: UPI | G18: Food | H18: =IF(D18="","",IF(ISNUMBER(SEARCH(SETTINGS!$K$4,D18)),SETTINGS!$L$4,IF(ISNUMBER(SEARCH(SETTINGS!$K$5,D18)),SETTINGS!$L$5,IF(ISNUMBER(SEARCH(SETTINGS!$K$6,D18)),SETTINGS!$L$6,IF(ISNUMBER(SEARCH(SETTINGS!$K$7,D18)),SETTINGS!$L$7,IF(ISNUMBER(SEARCH(SETTINGS!$K$8,D18)),SETTINGS!$L$8,IF(ISNUMBER(SEARCH(SETTINGS!$K$9,D18)),SETTINGS!$L$9,IF(ISNUMBER(SEARCH(SETTINGS!$K$10,D18)),SETTINGS!$L$10,IF(ISNUMBER(SEARCH(SETTINGS!$K$11,D18)),SETTINGS!$L$11,IF(ISNUMBER(SEARCH(SETTINGS!$K$12,D18)),SETTINGS!$L$12,IF(ISNUMBER(SEARCH(SETTINGS!$K$13,D18)),SETTINGS!$L$13,IF(ISNUMBER(SEARCH(SETTINGS!$K$14,D18)),SETTINGS!$L$14,IF(ISNUMBER(SEARCH(SETTINGS!$K$15,D18)),SETTINGS!$L$15,IF(ISNUMBER(SEARCH(SETTINGS!$K$16,D18)),SETTINGS!$L$16,IF(ISNUMBER(SEARCH(SETTINGS!$K$17,D18)),SETTINGS!$L$17,IF(ISNUMBER(SEARCH(SETTINGS!$K$18,D18)),SETTINGS!$L$18,"Miscellaneous")))))))))))))))) -> Miscellaneous | I18: =IF(B18="","",IF(G18<>"",G18,H18)) -> Food | J18: Mess | K18: Hostel Mess | L18: UPI-linked Bank | M18: Essential | N18: Recurring | O18: Paid | Q18: Self | R18: Not Applicable | S18: Hostel | U18: =IF(B18="","",IF(C18="Income","INC-",IF(C18="Expense","EXP-","TRX-"))&TEXT(YEAR(B18),"0000")&"-"&TEXT(ROW()-7,"0000")) -> EXP-2026-0011 | V18: =IF(B18="","",TEXT(B18,"mmmm")) -> April | W18: =IF(B18="","",MONTH(B18)) -> 4 | X18: =IF(B18="","",YEAR(B18)) -> 2026 | Y18: =IF(B18="","",DAY(B18)) -> 14 | Z18: =IF(B18="","",IF(WEEKDAY(B18,2)>5,"Weekend","Weekday")) -> Weekday | AA18: =IF(B18="","",IF(COUNTIFS($B$8:$B$1007,B18,$E$8:$E$1007,E18,$D$8:$D$1007,D18,$I$8:$I$1007,I18)>1,"Possible Duplicate","OK")) -> OK | AB18: =IF(OR(B18="",C18<>"Expense"),"",IF(E18>IFERROR(AVERAGEIFS($E$8:$E$1007,$I$8:$I$1007,I18,$C$8:$C$1007,"Expense")*SETTINGS!$B$20,0),"Unusually High","Normal")) -> Normal | AC18: Yes | AF18: =IF(A18<>"Yes","No",IF(AND(AC18="Yes",SETTINGS!$B$16="No"),"No","Yes")) -> Yes | AG18: =IF(A18<>"Yes","",IF(OR(B18="",D18="",E18<=0,F18="",I18=""),"Check Required Fields",IF(AA18="Possible Duplicate","Possible Duplicate",IF(E18>SETTINGS!$B$22,"Review Extreme Value","OK")))) -> OK
A19: Yes | B19: 46134 | C19: Expense | D19: Haircut and toiletries | E19: 1200 | F19: UPI | G19: Personal Care | H19: =IF(D19="","",IF(ISNUMBER(SEARCH(SETTINGS!$K$4,D19)),SETTINGS!$L$4,IF(ISNUMBER(SEARCH(SETTINGS!$K$5,D19)),SETTINGS!$L$5,IF(ISNUMBER(SEARCH(SETTINGS!$K$6,D19)),SETTINGS!$L$6,IF(ISNUMBER(SEARCH(SETTINGS!$K$7,D19)),SETTINGS!$L$7,IF(ISNUMBER(SEARCH(SETTINGS!$K$8,D19)),SETTINGS!$L$8,IF(ISNUMBER(SEARCH(SETTINGS!$K$9,D19)),SETTINGS!$L$9,IF(ISNUMBER(SEARCH(SETTINGS!$K$10,D19)),SETTINGS!$L$10,IF(ISNUMBER(SEARCH(SETTINGS!$K$11,D19)),SETTINGS!$L$11,IF(ISNUMBER(SEARCH(SETTINGS!$K$12,D19)),SETTINGS!$L$12,IF(ISNUMBER(SEARCH(SETTINGS!$K$13,D19)),SETTINGS!$L$13,IF(ISNUMBER(SEARCH(SETTINGS!$K$14,D19)),SETTINGS!$L$14,IF(ISNUMBER(SEARCH(SETTINGS!$K$15,D19)),SETTINGS!$L$15,IF(ISNUMBER(SEARCH(SETTINGS!$K$16,D19)),SETTINGS!$L$16,IF(ISNUMBER(SEARCH(SETTINGS!$K$17,D19)),SETTINGS!$L$17,IF(ISNUMBER(SEARCH(SETTINGS!$K$18,D19)),SETTINGS!$L$18,"Miscellaneous")))))))))))))))) -> Miscellaneous | I19: =IF(B19="","",IF(G19<>"",G19,H19)) -> Personal Care | J19: Other | K19: Local Shop | L19: UPI-linked Bank | M19: Useful | N19: One-Time | O19: Paid | Q19: Self | R19: Not Applicable | U19: =IF(B19="","",IF(C19="Income","INC-",IF(C19="Expense","EXP-","TRX-"))&TEXT(YEAR(B19),"0000")&"-"&TEXT(ROW()-7,"0000")) -> EXP-2026-0012 | V19: =IF(B19="","",TEXT(B19,"mmmm")) -> April | W19: =IF(B19="","",MONTH(B19)) -> 4 | X19: =IF(B19="","",YEAR(B19)) -> 2026 | Y19: =IF(B19="","",DAY(B19)) -> 22 | Z19: =IF(B19="","",IF(WEEKDAY(B19,2)>5,"Weekend","Weekday")) -> Weekday | AA19: =IF(B19="","",IF(COUNTIFS($B$8:$B$1007,B19,$E$8:$E$1007,E19,$D$8:$D$1007,D19,$I$8:$I$1007,I19)>1,"Possible Duplicate","OK")) -> OK | AB19: =IF(OR(B19="",C19<>"Expense"),"",IF(E19>IFERROR(AVERAGEIFS($E$8:$E$1007,$I$8:$I$1007,I19,$C$8:$C$1007,"Expense")*SETTINGS!$B$20,0),"Unusually High","Normal")) -> Normal | AC19: Yes | AF19: =IF(A19<>"Yes","No",IF(AND(AC19="Yes",SETTINGS!$B$16="No"),"No","Yes")) -> Yes | AG19: =IF(A19<>"Yes","",IF(OR(B19="",D19="",E19<=0,F19="",I19=""),"Check Required Fields",IF(AA19="Possible Duplicate","Possible Duplicate",IF(E19>SETTINGS!$B$22,"Review Extreme Value","OK")))) -> OK
A20: Yes | B20: 46143 | C20: Income | D20: Monthly Allowance - May | E20: 25000 | F20: UPI | G20: Miscellaneous | H20: =IF(D20="","",IF(ISNUMBER(SEARCH(SETTINGS!$K$4,D20)),SETTINGS!$L$4,IF(ISNUMBER(SEARCH(SETTINGS!$K$5,D20)),SETTINGS!$L$5,IF(ISNUMBER(SEARCH(SETTINGS!$K$6,D20)),SETTINGS!$L$6,IF(ISNUMBER(SEARCH(SETTINGS!$K$7,D20)),SETTINGS!$L$7,IF(ISNUMBER(SEARCH(SETTINGS!$K$8,D20)),SETTINGS!$L$8,IF(ISNUMBER(SEARCH(SETTINGS!$K$9,D20)),SETTINGS!$L$9,IF(ISNUMBER(SEARCH(SETTINGS!$K$10,D20)),SETTINGS!$L$10,IF(ISNUMBER(SEARCH(SETTINGS!$K$11,D20)),SETTINGS!$L$11,IF(ISNUMBER(SEARCH(SETTINGS!$K$12,D20)),SETTINGS!$L$12,IF(ISNUMBER(SEARCH(SETTINGS!$K$13,D20)),SETTINGS!$L$13,IF(ISNUMBER(SEARCH(SETTINGS!$K$14,D20)),SETTINGS!$L$14,IF(ISNUMBER(SEARCH(SETTINGS!$K$15,D20)),SETTINGS!$L$15,IF(ISNUMBER(SEARCH(SETTINGS!$K$16,D20)),SETTINGS!$L$16,IF(ISNUMBER(SEARCH(SETTINGS!$K$17,D20)),SETTINGS!$L$17,IF(ISNUMBER(SEARCH(SETTINGS!$K$18,D20)),SETTINGS!$L$18,"Miscellaneous")))))))))))))))) -> Miscellaneous | I20: =IF(B20="","",IF(G20<>"",G20,H20)) -> Miscellaneous | J20: Monthly Allowance | L20: UPI-linked Bank | M20: Essential | N20: Recurring | O20: Paid | Q20: Self | R20: Not Applicable | S20: Home | U20: =IF(B20="","",IF(C20="Income","INC-",IF(C20="Expense","EXP-","TRX-"))&TEXT(YEAR(B20),"0000")&"-"&TEXT(ROW()-7,"0000")) -> INC-2026-0013 | V20: =IF(B20="","",TEXT(B20,"mmmm")) -> May | W20: =IF(B20="","",MONTH(B20)) -> 5 | X20: =IF(B20="","",YEAR(B20)) -> 2026 | Y20: =IF(B20="","",DAY(B20)) -> 1 | Z20: =IF(B20="","",IF(WEEKDAY(B20,2)>5,"Weekend","Weekday")) -> Weekday | AA20: =IF(B20="","",IF(COUNTIFS($B$8:$B$1007,B20,$E$8:$E$1007,E20,$D$8:$D$1007,D20,$I$8:$I$1007,I20)>1,"Possible Duplicate","OK")) -> OK | AB20: =IF(OR(B20="",C20<>"Expense"),"",IF(E20>IFERROR(AVERAGEIFS($E$8:$E$1007,$I$8:$I$1007,I20,$C$8:$C$1007,"Expense")*SETTINGS!$B$20,0),"Unusually High","Normal")) | AC20: Yes | AF20: =IF(A20<>"Yes","No",IF(AND(AC20="Yes",SETTINGS!$B$16="No"),"No","Yes")) -> Yes | AG20: =IF(A20<>"Yes","",IF(OR(B20="",D20="",E20<=0,F20="",I20=""),"Check Required Fields",IF(AA20="Possible Duplicate","Possible Duplicate",IF(E20>SETTINGS!$B$22,"Review Extreme Value","OK")))) -> OK
A21: Yes | B21: 46154 | C21: Expense | D21: Train ticket home | E21: 2400 | F21: Debit Card | G21: Travel Home | H21: =IF(D21="","",IF(ISNUMBER(SEARCH(SETTINGS!$K$4,D21)),SETTINGS!$L$4,IF(ISNUMBER(SEARCH(SETTINGS!$K$5,D21)),SETTINGS!$L$5,IF(ISNUMBER(SEARCH(SETTINGS!$K$6,D21)),SETTINGS!$L$6,IF(ISNUMBER(SEARCH(SETTINGS!$K$7,D21)),SETTINGS!$L$7,IF(ISNUMBER(SEARCH(SETTINGS!$K$8,D21)),SETTINGS!$L$8,IF(ISNUMBER(SEARCH(SETTINGS!$K$9,D21)),SETTINGS!$L$9,IF(ISNUMBER(SEARCH(SETTINGS!$K$10,D21)),SETTINGS!$L$10,IF(ISNUMBER(SEARCH(SETTINGS!$K$11,D21)),SETTINGS!$L$11,IF(ISNUMBER(SEARCH(SETTINGS!$K$12,D21)),SETTINGS!$L$12,IF(ISNUMBER(SEARCH(SETTINGS!$K$13,D21)),SETTINGS!$L$13,IF(ISNUMBER(SEARCH(SETTINGS!$K$14,D21)),SETTINGS!$L$14,IF(ISNUMBER(SEARCH(SETTINGS!$K$15,D21)),SETTINGS!$L$15,IF(ISNUMBER(SEARCH(SETTINGS!$K$16,D21)),SETTINGS!$L$16,IF(ISNUMBER(SEARCH(SETTINGS!$K$17,D21)),SETTINGS!$L$17,IF(ISNUMBER(SEARCH(SETTINGS!$K$18,D21)),SETTINGS!$L$18,"Miscellaneous")))))))))))))))) -> Miscellaneous | I21: =IF(B21="","",IF(G21<>"",G21,H21)) -> Travel Home | J21: Train | K21: IRCTC | L21: UPI-linked Bank | M21: Essential | N21: One-Time | O21: Paid | Q21: Self | R21: Not Applicable | S21: Travel | U21: =IF(B21="","",IF(C21="Income","INC-",IF(C21="Expense","EXP-","TRX-"))&TEXT(YEAR(B21),"0000")&"-"&TEXT(ROW()-7,"0000")) -> EXP-2026-0014 | V21: =IF(B21="","",TEXT(B21,"mmmm")) -> May | W21: =IF(B21="","",MONTH(B21)) -> 5 | X21: =IF(B21="","",YEAR(B21)) -> 2026 | Y21: =IF(B21="","",DAY(B21)) -> 12 | Z21: =IF(B21="","",IF(WEEKDAY(B21,2)>5,"Weekend","Weekday")) -> Weekday | AA21: =IF(B21="","",IF(COUNTIFS($B$8:$B$1007,B21,$E$8:$E$1007,E21,$D$8:$D$1007,D21,$I$8:$I$1007,I21)>1,"Possible Duplicate","OK")) -> OK | AB21: =IF(OR(B21="",C21<>"Expense"),"",IF(E21>IFERROR(AVERAGEIFS($E$8:$E$1007,$I$8:$I$1007,I21,$C$8:$C$1007,"Expense")*SETTINGS!$B$20,0),"Unusually High","Normal")) -> Normal | AC21: Yes | AF21: =IF(A21<>"Yes","No",IF(AND(AC21="Yes",SETTINGS!$B$16="No"),"No","Yes")) -> Yes | AG21: =IF(A21<>"Yes","",IF(OR(B21="",D21="",E21<=0,F21="",I21=""),"Check Required Fields",IF(AA21="Possible Duplicate","Possible Duplicate",IF(E21>SETTINGS!$B$22,"Review Extreme Value","OK")))) -> OK
A22: Yes | B22: 46167 | C22: Expense | D22: Movie and cafe | E22: 900 | F22: UPI | G22: Entertainment | H22: =IF(D22="","",IF(ISNUMBER(SEARCH(SETTINGS!$K$4,D22)),SETTINGS!$L$4,IF(ISNUMBER(SEARCH(SETTINGS!$K$5,D22)),SETTINGS!$L$5,IF(ISNUMBER(SEARCH(SETTINGS!$K$6,D22)),SETTINGS!$L$6,IF(ISNUMBER(SEARCH(SETTINGS!$K$7,D22)),SETTINGS!$L$7,IF(ISNUMBER(SEARCH(SETTINGS!$K$8,D22)),SETTINGS!$L$8,IF(ISNUMBER(SEARCH(SETTINGS!$K$9,D22)),SETTINGS!$L$9,IF(ISNUMBER(SEARCH(SETTINGS!$K$10,D22)),SETTINGS!$L$10,IF(ISNUMBER(SEARCH(SETTINGS!$K$11,D22)),SETTINGS!$L$11,IF(ISNUMBER(SEARCH(SETTINGS!$K$12,D22)),SETTINGS!$L$12,IF(ISNUMBER(SEARCH(SETTINGS!$K$13,D22)),SETTINGS!$L$13,IF(ISNUMBER(SEARCH(SETTINGS!$K$14,D22)),SETTINGS!$L$14,IF(ISNUMBER(SEARCH(SETTINGS!$K$15,D22)),SETTINGS!$L$15,IF(ISNUMBER(SEARCH(SETTINGS!$K$16,D22)),SETTINGS!$L$16,IF(ISNUMBER(SEARCH(SETTINGS!$K$17,D22)),SETTINGS!$L$17,IF(ISNUMBER(SEARCH(SETTINGS!$K$18,D22)),SETTINGS!$L$18,"Miscellaneous")))))))))))))))) -> Miscellaneous | I22: =IF(B22="","",IF(G22<>"",G22,H22)) -> Entertainment | J22: Other | K22: Cinema | L22: UPI-linked Bank | M22: Optional | N22: One-Time | O22: Paid | Q22: Self | R22: Not Applicable | S22: Friends | U22: =IF(B22="","",IF(C22="Income","INC-",IF(C22="Expense","EXP-","TRX-"))&TEXT(YEAR(B22),"0000")&"-"&TEXT(ROW()-7,"0000")) -> EXP-2026-0015 | V22: =IF(B22="","",TEXT(B22,"mmmm")) -> May | W22: =IF(B22="","",MONTH(B22)) -> 5 | X22: =IF(B22="","",YEAR(B22)) -> 2026 | Y22: =IF(B22="","",DAY(B22)) -> 25 | Z22: =IF(B22="","",IF(WEEKDAY(B22,2)>5,"Weekend","Weekday")) -> Weekday | AA22: =IF(B22="","",IF(COUNTIFS($B$8:$B$1007,B22,$E$8:$E$1007,E22,$D$8:$D$1007,D22,$I$8:$I$1007,I22)>1,"Possible Duplicate","OK")) -> OK | AB22: =IF(OR(B22="",C22<>"Expense"),"",IF(E22>IFERROR(AVERAGEIFS($E$8:$E$1007,$I$8:$I$1007,I22,$C$8:$C$1007,"Expense")*SETTINGS!$B$20,0),"Unusually High","Normal")) -> Normal | AC22: Yes | AF22: =IF(A22<>"Yes","No",IF(AND(AC22="Yes",SETTINGS!$B$16="No"),"No","Yes")) -> Yes | AG22: =IF(A22<>"Yes","",IF(OR(B22="",D22="",E22<=0,F22="",I22=""),"Check Required Fields",IF(AA22="Possible Duplicate","Possible Duplicate",IF(E22>SETTINGS!$B$22,"Review Extreme Value","OK")))) -> OK
A23: Yes | B23: 46174 | C23: Income | D23: Monthly Allowance - June | E23: 25000 | F23: UPI | G23: Miscellaneous | H23: =IF(D23="","",IF(ISNUMBER(SEARCH(SETTINGS!$K$4,D23)),SETTINGS!$L$4,IF(ISNUMBER(SEARCH(SETTINGS!$K$5,D23)),SETTINGS!$L$5,IF(ISNUMBER(SEARCH(SETTINGS!$K$6,D23)),SETTINGS!$L$6,IF(ISNUMBER(SEARCH(SETTINGS!$K$7,D23)),SETTINGS!$L$7,IF(ISNUMBER(SEARCH(SETTINGS!$K$8,D23)),SETTINGS!$L$8,IF(ISNUMBER(SEARCH(SETTINGS!$K$9,D23)),SETTINGS!$L$9,IF(ISNUMBER(SEARCH(SETTINGS!$K$10,D23)),SETTINGS!$L$10,IF(ISNUMBER(SEARCH(SETTINGS!$K$11,D23)),SETTINGS!$L$11,IF(ISNUMBER(SEARCH(SETTINGS!$K$12,D23)),SETTINGS!$L$12,IF(ISNUMBER(SEARCH(SETTINGS!$K$13,D23)),SETTINGS!$L$13,IF(ISNUMBER(SEARCH(SETTINGS!$K$14,D23)),SETTINGS!$L$14,IF(ISNUMBER(SEARCH(SETTINGS!$K$15,D23)),SETTINGS!$L$15,IF(ISNUMBER(SEARCH(SETTINGS!$K$16,D23)),SETTINGS!$L$16,IF(ISNUMBER(SEARCH(SETTINGS!$K$17,D23)),SETTINGS!$L$17,IF(ISNUMBER(SEARCH(SETTINGS!$K$18,D23)),SETTINGS!$L$18,"Miscellaneous")))))))))))))))) -> Miscellaneous | I23: =IF(B23="","",IF(G23<>"",G23,H23)) -> Miscellaneous | J23: Monthly Allowance | L23: UPI-linked Bank | M23: Essential | N23: Recurring | O23: Paid | Q23: Self | R23: Not Applicable | S23: Home | U23: =IF(B23="","",IF(C23="Income","INC-",IF(C23="Expense","EXP-","TRX-"))&TEXT(YEAR(B23),"0000")&"-"&TEXT(ROW()-7,"0000")) -> INC-2026-0016 | V23: =IF(B23="","",TEXT(B23,"mmmm")) -> June | W23: =IF(B23="","",MONTH(B23)) -> 6 | X23: =IF(B23="","",YEAR(B23)) -> 2026 | Y23: =IF(B23="","",DAY(B23)) -> 1 | Z23: =IF(B23="","",IF(WEEKDAY(B23,2)>5,"Weekend","Weekday")) -> Weekday | AA23: =IF(B23="","",IF(COUNTIFS($B$8:$B$1007,B23,$E$8:$E$1007,E23,$D$8:$D$1007,D23,$I$8:$I$1007,I23)>1,"Possible Duplicate","OK")) -> OK | AB23: =IF(OR(B23="",C23<>"Expense"),"",IF(E23>IFERROR(AVERAGEIFS($E$8:$E$1007,$I$8:$I$1007,I23,$C$8:$C$1007,"Expense")*SETTINGS!$B$20,0),"Unusually High","Normal")) | AC23: Yes | AF23: =IF(A23<>"Yes","No",IF(AND(AC23="Yes",SETTINGS!$B$16="No"),"No","Yes")) -> Yes | AG23: =IF(A23<>"Yes","",IF(OR(B23="",D23="",E23<=0,F23="",I23=""),"Check Required Fields",IF(AA23="Possible Duplicate","Possible Duplicate",IF(E23>SETTINGS!$B$22,"Review Extreme Value","OK")))) -> OK
A24: Yes | B24: 46184 | C24: Expense | D24: Udemy Machine Learning course | E24: 1999 | F24: Debit Card | G24: AI-ML Learning | H24: =IF(D24="","",IF(ISNUMBER(SEARCH(SETTINGS!$K$4,D24)),SETTINGS!$L$4,IF(ISNUMBER(SEARCH(SETTINGS!$K$5,D24)),SETTINGS!$L$5,IF(ISNUMBER(SEARCH(SETTINGS!$K$6,D24)),SETTINGS!$L$6,IF(ISNUMBER(SEARCH(SETTINGS!$K$7,D24)),SETTINGS!$L$7,IF(ISNUMBER(SEARCH(SETTINGS!$K$8,D24)),SETTINGS!$L$8,IF(ISNUMBER(SEARCH(SETTINGS!$K$9,D24)),SETTINGS!$L$9,IF(ISNUMBER(SEARCH(SETTINGS!$K$10,D24)),SETTINGS!$L$10,IF(ISNUMBER(SEARCH(SETTINGS!$K$11,D24)),SETTINGS!$L$11,IF(ISNUMBER(SEARCH(SETTINGS!$K$12,D24)),SETTINGS!$L$12,IF(ISNUMBER(SEARCH(SETTINGS!$K$13,D24)),SETTINGS!$L$13,IF(ISNUMBER(SEARCH(SETTINGS!$K$14,D24)),SETTINGS!$L$14,IF(ISNUMBER(SEARCH(SETTINGS!$K$15,D24)),SETTINGS!$L$15,IF(ISNUMBER(SEARCH(SETTINGS!$K$16,D24)),SETTINGS!$L$16,IF(ISNUMBER(SEARCH(SETTINGS!$K$17,D24)),SETTINGS!$L$17,IF(ISNUMBER(SEARCH(SETTINGS!$K$18,D24)),SETTINGS!$L$18,"Miscellaneous")))))))))))))))) -> AI-ML Learning | I24: =IF(B24="","",IF(G24<>"",G24,H24)) -> AI-ML Learning | J24: Course | K24: Udemy | L24: UPI-linked Bank | M24: Essential | N24: One-Time | O24: Paid | Q24: Self | R24: Not Applicable | S24: College | U24: =IF(B24="","",IF(C24="Income","INC-",IF(C24="Expense","EXP-","TRX-"))&TEXT(YEAR(B24),"0000")&"-"&TEXT(ROW()-7,"0000")) -> EXP-2026-0017 | V24: =IF(B24="","",TEXT(B24,"mmmm")) -> June | W24: =IF(B24="","",MONTH(B24)) -> 6 | X24: =IF(B24="","",YEAR(B24)) -> 2026 | Y24: =IF(B24="","",DAY(B24)) -> 11 | Z24: =IF(B24="","",IF(WEEKDAY(B24,2)>5,"Weekend","Weekday")) -> Weekday | AA24: =IF(B24="","",IF(COUNTIFS($B$8:$B$1007,B24,$E$8:$E$1007,E24,$D$8:$D$1007,D24,$I$8:$I$1007,I24)>1,"Possible Duplicate","OK")) -> OK | AB24: =IF(OR(B24="",C24<>"Expense"),"",IF(E24>IFERROR(AVERAGEIFS($E$8:$E$1007,$I$8:$I$1007,I24,$C$8:$C$1007,"Expense")*SETTINGS!$B$20,0),"Unusually High","Normal")) -> Normal | AC24: Yes | AF24: =IF(A24<>"Yes","No",IF(AND(AC24="Yes",SETTINGS!$B$16="No"),"No","Yes")) -> Yes | AG24: =IF(A24<>"Yes","",IF(OR(B24="",D24="",E24<=0,F24="",I24=""),"Check Required Fields",IF(AA24="Possible Duplicate","Possible Duplicate",IF(E24>SETTINGS!$B$22,"Review Extreme Value","OK")))) -> OK
A25: Yes | B25: 46193 | C25: Expense | D25: Books and stationery | E25: 650 | F25: UPI | G25: Books & Stationery | H25: =IF(D25="","",IF(ISNUMBER(SEARCH(SETTINGS!$K$4,D25)),SETTINGS!$L$4,IF(ISNUMBER(SEARCH(SETTINGS!$K$5,D25)),SETTINGS!$L$5,IF(ISNUMBER(SEARCH(SETTINGS!$K$6,D25)),SETTINGS!$L$6,IF(ISNUMBER(SEARCH(SETTINGS!$K$7,D25)),SETTINGS!$L$7,IF(ISNUMBER(SEARCH(SETTINGS!$K$8,D25)),SETTINGS!$L$8,IF(ISNUMBER(SEARCH(SETTINGS!$K$9,D25)),SETTINGS!$L$9,IF(ISNUMBER(SEARCH(SETTINGS!$K$10,D25)),SETTINGS!$L$10,IF(ISNUMBER(SEARCH(SETTINGS!$K$11,D25)),SETTINGS!$L$11,IF(ISNUMBER(SEARCH(SETTINGS!$K$12,D25)),SETTINGS!$L$12,IF(ISNUMBER(SEARCH(SETTINGS!$K$13,D25)),SETTINGS!$L$13,IF(ISNUMBER(SEARCH(SETTINGS!$K$14,D25)),SETTINGS!$L$14,IF(ISNUMBER(SEARCH(SETTINGS!$K$15,D25)),SETTINGS!$L$15,IF(ISNUMBER(SEARCH(SETTINGS!$K$16,D25)),SETTINGS!$L$16,IF(ISNUMBER(SEARCH(SETTINGS!$K$17,D25)),SETTINGS!$L$17,IF(ISNUMBER(SEARCH(SETTINGS!$K$18,D25)),SETTINGS!$L$18,"Miscellaneous")))))))))))))))) -> Books & Stationery | I25: =IF(B25="","",IF(G25<>"",G25,H25)) -> Books & Stationery | J25: Books | K25: Book Shop | L25: UPI-linked Bank | M25: Essential | N25: One-Time | O25: Paid | Q25: Self | R25: Not Applicable | S25: College | U25: =IF(B25="","",IF(C25="Income","INC-",IF(C25="Expense","EXP-","TRX-"))&TEXT(YEAR(B25),"0000")&"-"&TEXT(ROW()-7,"0000")) -> EXP-2026-0018 | V25: =IF(B25="","",TEXT(B25,"mmmm")) -> June | W25: =IF(B25="","",MONTH(B25)) -> 6 | X25: =IF(B25="","",YEAR(B25)) -> 2026 | Y25: =IF(B25="","",DAY(B25)) -> 20 | Z25: =IF(B25="","",IF(WEEKDAY(B25,2)>5,"Weekend","Weekday")) -> Weekend | AA25: =IF(B25="","",IF(COUNTIFS($B$8:$B$1007,B25,$E$8:$E$1007,E25,$D$8:$D$1007,D25,$I$8:$I$1007,I25)>1,"Possible Duplicate","OK")) -> OK | AB25: =IF(OR(B25="",C25<>"Expense"),"",IF(E25>IFERROR(AVERAGEIFS($E$8:$E$1007,$I$8:$I$1007,I25,$C$8:$C$1007,"Expense")*SETTINGS!$B$20,0),"Unusually High","Normal")) -> Normal | AC25: Yes | AF25: =IF(A25<>"Yes","No",IF(AND(AC25="Yes",SETTINGS!$B$16="No"),"No","Yes")) -> Yes | AG25: =IF(A25<>"Yes","",IF(OR(B25="",D25="",E25<=0,F25="",I25=""),"Check Required Fields",IF(AA25="Possible Duplicate","Possible Duplicate",IF(E25>SETTINGS!$B$22,"Review Extreme Value","OK")))) -> OK
A26: Yes | B26: 46204 | C26: Income | D26: Monthly Allowance - July | E26: 25000 | F26: UPI | G26: Miscellaneous | H26: =IF(D26="","",IF(ISNUMBER(SEARCH(SETTINGS!$K$4,D26)),SETTINGS!$L$4,IF(ISNUMBER(SEARCH(SETTINGS!$K$5,D26)),SETTINGS!$L$5,IF(ISNUMBER(SEARCH(SETTINGS!$K$6,D26)),SETTINGS!$L$6,IF(ISNUMBER(SEARCH(SETTINGS!$K$7,D26)),SETTINGS!$L$7,IF(ISNUMBER(SEARCH(SETTINGS!$K$8,D26)),SETTINGS!$L$8,IF(ISNUMBER(SEARCH(SETTINGS!$K$9,D26)),SETTINGS!$L$9,IF(ISNUMBER(SEARCH(SETTINGS!$K$10,D26)),SETTINGS!$L$10,IF(ISNUMBER(SEARCH(SETTINGS!$K$11,D26)),SETTINGS!$L$11,IF(ISNUMBER(SEARCH(SETTINGS!$K$12,D26)),SETTINGS!$L$12,IF(ISNUMBER(SEARCH(SETTINGS!$K$13,D26)),SETTINGS!$L$13,IF(ISNUMBER(SEARCH(SETTINGS!$K$14,D26)),SETTINGS!$L$14,IF(ISNUMBER(SEARCH(SETTINGS!$K$15,D26)),SETTINGS!$L$15,IF(ISNUMBER(SEARCH(SETTINGS!$K$16,D26)),SETTINGS!$L$16,IF(ISNUMBER(SEARCH(SETTINGS!$K$17,D26)),SETTINGS!$L$17,IF(ISNUMBER(SEARCH(SETTINGS!$K$18,D26)),SETTINGS!$L$18,"Miscellaneous")))))))))))))))) -> Miscellaneous | I26: =IF(B26="","",IF(G26<>"",G26,H26)) -> Miscellaneous | J26: Monthly Allowance | L26: UPI-linked Bank | M26: Essential | N26: Recurring | O26: Paid | Q26: Self | R26: Not Applicable | S26: Home | U26: =IF(B26="","",IF(C26="Income","INC-",IF(C26="Expense","EXP-","TRX-"))&TEXT(YEAR(B26),"0000")&"-"&TEXT(ROW()-7,"0000")) -> INC-2026-0019 | V26: =IF(B26="","",TEXT(B26,"mmmm")) -> July | W26: =IF(B26="","",MONTH(B26)) -> 7 | X26: =IF(B26="","",YEAR(B26)) -> 2026 | Y26: =IF(B26="","",DAY(B26)) -> 1 | Z26: =IF(B26="","",IF(WEEKDAY(B26,2)>5,"Weekend","Weekday")) -> Weekday | AA26: =IF(B26="","",IF(COUNTIFS($B$8:$B$1007,B26,$E$8:$E$1007,E26,$D$8:$D$1007,D26,$I$8:$I$1007,I26)>1,"Possible Duplicate","OK")) -> OK | AB26: =IF(OR(B26="",C26<>"Expense"),"",IF(E26>IFERROR(AVERAGEIFS($E$8:$E$1007,$I$8:$I$1007,I26,$C$8:$C$1007,"Expense")*SETTINGS!$B$20,0),"Unusually High","Normal")) | AC26: Yes | AF26: =IF(A26<>"Yes","No",IF(AND(AC26="Yes",SETTINGS!$B$16="No"),"No","Yes")) -> Yes | AG26: =IF(A26<>"Yes","",IF(OR(B26="",D26="",E26<=0,F26="",I26=""),"Check Required Fields",IF(AA26="Possible Duplicate","Possible Duplicate",IF(E26>SETTINGS!$B$22,"Review Extreme Value","OK")))) -> OK
A27: Yes | B27: 46208 | C27: Expense | D27: Hostel and mess fee | E27: 4000 | F27: Bank Transfer | G27: Hostel | H27: =IF(D27="","",IF(ISNUMBER(SEARCH(SETTINGS!$K$4,D27)),SETTINGS!$L$4,IF(ISNUMBER(SEARCH(SETTINGS!$K$5,D27)),SETTINGS!$L$5,IF(ISNUMBER(SEARCH(SETTINGS!$K$6,D27)),SETTINGS!$L$6,IF(ISNUMBER(SEARCH(SETTINGS!$K$7,D27)),SETTINGS!$L$7,IF(ISNUMBER(SEARCH(SETTINGS!$K$8,D27)),SETTINGS!$L$8,IF(ISNUMBER(SEARCH(SETTINGS!$K$9,D27)),SETTINGS!$L$9,IF(ISNUMBER(SEARCH(SETTINGS!$K$10,D27)),SETTINGS!$L$10,IF(ISNUMBER(SEARCH(SETTINGS!$K$11,D27)),SETTINGS!$L$11,IF(ISNUMBER(SEARCH(SETTINGS!$K$12,D27)),SETTINGS!$L$12,IF(ISNUMBER(SEARCH(SETTINGS!$K$13,D27)),SETTINGS!$L$13,IF(ISNUMBER(SEARCH(SETTINGS!$K$14,D27)),SETTINGS!$L$14,IF(ISNUMBER(SEARCH(SETTINGS!$K$15,D27)),SETTINGS!$L$15,IF(ISNUMBER(SEARCH(SETTINGS!$K$16,D27)),SETTINGS!$L$16,IF(ISNUMBER(SEARCH(SETTINGS!$K$17,D27)),SETTINGS!$L$17,IF(ISNUMBER(SEARCH(SETTINGS!$K$18,D27)),SETTINGS!$L$18,"Miscellaneous")))))))))))))))) -> Miscellaneous | I27: =IF(B27="","",IF(G27<>"",G27,H27)) -> Hostel | J27: Hostel Fee | K27: College Hostel | L27: UPI-linked Bank | M27: Essential | N27: Recurring | O27: Paid | Q27: Self | R27: Semester 1 | S27: Hostel | U27: =IF(B27="","",IF(C27="Income","INC-",IF(C27="Expense","EXP-","TRX-"))&TEXT(YEAR(B27),"0000")&"-"&TEXT(ROW()-7,"0000")) -> EXP-2026-0020 | V27: =IF(B27="","",TEXT(B27,"mmmm")) -> July | W27: =IF(B27="","",MONTH(B27)) -> 7 | X27: =IF(B27="","",YEAR(B27)) -> 2026 | Y27: =IF(B27="","",DAY(B27)) -> 5 | Z27: =IF(B27="","",IF(WEEKDAY(B27,2)>5,"Weekend","Weekday")) -> Weekend | AA27: =IF(B27="","",IF(COUNTIFS($B$8:$B$1007,B27,$E$8:$E$1007,E27,$D$8:$D$1007,D27,$I$8:$I$1007,I27)>1,"Possible Duplicate","OK")) -> OK | AB27: =IF(OR(B27="",C27<>"Expense"),"",IF(E27>IFERROR(AVERAGEIFS($E$8:$E$1007,$I$8:$I$1007,I27,$C$8:$C$1007,"Expense")*SETTINGS!$B$20,0),"Unusually High","Normal")) -> Normal | AC27: Yes | AF27: =IF(A27<>"Yes","No",IF(AND(AC27="Yes",SETTINGS!$B$16="No"),"No","Yes")) -> Yes | AG27: =IF(A27<>"Yes","",IF(OR(B27="",D27="",E27<=0,F27="",I27=""),"Check Required Fields",IF(AA27="Possible Duplicate","Possible Duplicate",IF(E27>SETTINGS!$B$22,"Review Extreme Value","OK")))) -> OK
A28: Yes | B28: 46219 | C28: Expense | D28: Food and groceries | E28: 4200 | F28: UPI | G28: Food | H28: =IF(D28="","",IF(ISNUMBER(SEARCH(SETTINGS!$K$4,D28)),SETTINGS!$L$4,IF(ISNUMBER(SEARCH(SETTINGS!$K$5,D28)),SETTINGS!$L$5,IF(ISNUMBER(SEARCH(SETTINGS!$K$6,D28)),SETTINGS!$L$6,IF(ISNUMBER(SEARCH(SETTINGS!$K$7,D28)),SETTINGS!$L$7,IF(ISNUMBER(SEARCH(SETTINGS!$K$8,D28)),SETTINGS!$L$8,IF(ISNUMBER(SEARCH(SETTINGS!$K$9,D28)),SETTINGS!$L$9,IF(ISNUMBER(SEARCH(SETTINGS!$K$10,D28)),SETTINGS!$L$10,IF(ISNUMBER(SEARCH(SETTINGS!$K$11,D28)),SETTINGS!$L$11,IF(ISNUMBER(SEARCH(SETTINGS!$K$12,D28)),SETTINGS!$L$12,IF(ISNUMBER(SEARCH(SETTINGS!$K$13,D28)),SETTINGS!$L$13,IF(ISNUMBER(SEARCH(SETTINGS!$K$14,D28)),SETTINGS!$L$14,IF(ISNUMBER(SEARCH(SETTINGS!$K$15,D28)),SETTINGS!$L$15,IF(ISNUMBER(SEARCH(SETTINGS!$K$16,D28)),SETTINGS!$L$16,IF(ISNUMBER(SEARCH(SETTINGS!$K$17,D28)),SETTINGS!$L$17,IF(ISNUMBER(SEARCH(SETTINGS!$K$18,D28)),SETTINGS!$L$18,"Miscellaneous")))))))))))))))) -> Miscellaneous | I28: =IF(B28="","",IF(G28<>"",G28,H28)) -> Food | J28: Grocery | K28: Local Market | L28: UPI-linked Bank | M28: Essential | N28: One-Time | O28: Paid | Q28: Self | R28: Not Applicable | S28: Hostel | U28: =IF(B28="","",IF(C28="Income","INC-",IF(C28="Expense","EXP-","TRX-"))&TEXT(YEAR(B28),"0000")&"-"&TEXT(ROW()-7,"0000")) -> EXP-2026-0021 | V28: =IF(B28="","",TEXT(B28,"mmmm")) -> July | W28: =IF(B28="","",MONTH(B28)) -> 7 | X28: =IF(B28="","",YEAR(B28)) -> 2026 | Y28: =IF(B28="","",DAY(B28)) -> 16 | Z28: =IF(B28="","",IF(WEEKDAY(B28,2)>5,"Weekend","Weekday")) -> Weekday | AA28: =IF(B28="","",IF(COUNTIFS($B$8:$B$1007,B28,$E$8:$E$1007,E28,$D$8:$D$1007,D28,$I$8:$I$1007,I28)>1,"Possible Duplicate","OK")) -> OK | AB28: =IF(OR(B28="",C28<>"Expense"),"",IF(E28>IFERROR(AVERAGEIFS($E$8:$E$1007,$I$8:$I$1007,I28,$C$8:$C$1007,"Expense")*SETTINGS!$B$20,0),"Unusually High","Normal")) -> Normal | AC28: Yes | AF28: =IF(A28<>"Yes","No",IF(AND(AC28="Yes",SETTINGS!$B$16="No"),"No","Yes")) -> Yes | AG28: =IF(A28<>"Yes","",IF(OR(B28="",D28="",E28<=0,F28="",I28=""),"Check Required Fields",IF(AA28="Possible Duplicate","Possible Duplicate",IF(E28>SETTINGS!$B$22,"Review Extreme Value","OK")))) -> OK
A29: Yes | B29: 46235 | C29: Income | D29: Monthly Allowance - August | E29: 25000 | F29: UPI | G29: Miscellaneous | H29: =IF(D29="","",IF(ISNUMBER(SEARCH(SETTINGS!$K$4,D29)),SETTINGS!$L$4,IF(ISNUMBER(SEARCH(SETTINGS!$K$5,D29)),SETTINGS!$L$5,IF(ISNUMBER(SEARCH(SETTINGS!$K$6,D29)),SETTINGS!$L$6,IF(ISNUMBER(SEARCH(SETTINGS!$K$7,D29)),SETTINGS!$L$7,IF(ISNUMBER(SEARCH(SETTINGS!$K$8,D29)),SETTINGS!$L$8,IF(ISNUMBER(SEARCH(SETTINGS!$K$9,D29)),SETTINGS!$L$9,IF(ISNUMBER(SEARCH(SETTINGS!$K$10,D29)),SETTINGS!$L$10,IF(ISNUMBER(SEARCH(SETTINGS!$K$11,D29)),SETTINGS!$L$11,IF(ISNUMBER(SEARCH(SETTINGS!$K$12,D29)),SETTINGS!$L$12,IF(ISNUMBER(SEARCH(SETTINGS!$K$13,D29)),SETTINGS!$L$13,IF(ISNUMBER(SEARCH(SETTINGS!$K$14,D29)),SETTINGS!$L$14,IF(ISNUMBER(SEARCH(SETTINGS!$K$15,D29)),SETTINGS!$L$15,IF(ISNUMBER(SEARCH(SETTINGS!$K$16,D29)),SETTINGS!$L$16,IF(ISNUMBER(SEARCH(SETTINGS!$K$17,D29)),SETTINGS!$L$17,IF(ISNUMBER(SEARCH(SETTINGS!$K$18,D29)),SETTINGS!$L$18,"Miscellaneous")))))))))))))))) -> Miscellaneous | I29: =IF(B29="","",IF(G29<>"",G29,H29)) -> Miscellaneous | J29: Monthly Allowance | L29: UPI-linked Bank | M29: Essential | N29: Recurring | O29: Paid | Q29: Self | R29: Not Applicable | S29: Home | U29: =IF(B29="","",IF(C29="Income","INC-",IF(C29="Expense","EXP-","TRX-"))&TEXT(YEAR(B29),"0000")&"-"&TEXT(ROW()-7,"0000")) -> INC-2026-0022 | V29: =IF(B29="","",TEXT(B29,"mmmm")) -> August | W29: =IF(B29="","",MONTH(B29)) -> 8 | X29: =IF(B29="","",YEAR(B29)) -> 2026 | Y29: =IF(B29="","",DAY(B29)) -> 1 | Z29: =IF(B29="","",IF(WEEKDAY(B29,2)>5,"Weekend","Weekday")) -> Weekend | AA29: =IF(B29="","",IF(COUNTIFS($B$8:$B$1007,B29,$E$8:$E$1007,E29,$D$8:$D$1007,D29,$I$8:$I$1007,I29)>1,"Possible Duplicate","OK")) -> OK | AB29: =IF(OR(B29="",C29<>"Expense"),"",IF(E29>IFERROR(AVERAGEIFS($E$8:$E$1007,$I$8:$I$1007,I29,$C$8:$C$1007,"Expense")*SETTINGS!$B$20,0),"Unusually High","Normal")) | AC29: Yes | AF29: =IF(A29<>"Yes","No",IF(AND(AC29="Yes",SETTINGS!$B$16="No"),"No","Yes")) -> Yes | AG29: =IF(A29<>"Yes","",IF(OR(B29="",D29="",E29<=0,F29="",I29=""),"Check Required Fields",IF(AA29="Possible Duplicate","Possible Duplicate",IF(E29>SETTINGS!$B$22,"Review Extreme Value","OK")))) -> OK
A30: Yes | B30: 46254 | C30: Income | D30: Merit Scholarship | E30: 5000 | F30: Bank Transfer | G30: College Fees | H30: =IF(D30="","",IF(ISNUMBER(SEARCH(SETTINGS!$K$4,D30)),SETTINGS!$L$4,IF(ISNUMBER(SEARCH(SETTINGS!$K$5,D30)),SETTINGS!$L$5,IF(ISNUMBER(SEARCH(SETTINGS!$K$6,D30)),SETTINGS!$L$6,IF(ISNUMBER(SEARCH(SETTINGS!$K$7,D30)),SETTINGS!$L$7,IF(ISNUMBER(SEARCH(SETTINGS!$K$8,D30)),SETTINGS!$L$8,IF(ISNUMBER(SEARCH(SETTINGS!$K$9,D30)),SETTINGS!$L$9,IF(ISNUMBER(SEARCH(SETTINGS!$K$10,D30)),SETTINGS!$L$10,IF(ISNUMBER(SEARCH(SETTINGS!$K$11,D30)),SETTINGS!$L$11,IF(ISNUMBER(SEARCH(SETTINGS!$K$12,D30)),SETTINGS!$L$12,IF(ISNUMBER(SEARCH(SETTINGS!$K$13,D30)),SETTINGS!$L$13,IF(ISNUMBER(SEARCH(SETTINGS!$K$14,D30)),SETTINGS!$L$14,IF(ISNUMBER(SEARCH(SETTINGS!$K$15,D30)),SETTINGS!$L$15,IF(ISNUMBER(SEARCH(SETTINGS!$K$16,D30)),SETTINGS!$L$16,IF(ISNUMBER(SEARCH(SETTINGS!$K$17,D30)),SETTINGS!$L$17,IF(ISNUMBER(SEARCH(SETTINGS!$K$18,D30)),SETTINGS!$L$18,"Miscellaneous")))))))))))))))) -> Miscellaneous | I30: =IF(B30="","",IF(G30<>"",G30,H30)) -> College Fees | J30: Scholarship | K30: College | L30: UPI-linked Bank | M30: Essential | N30: One-Time | O30: Paid | Q30: Self | R30: Semester 1 | S30: College | U30: =IF(B30="","",IF(C30="Income","INC-",IF(C30="Expense","EXP-","TRX-"))&TEXT(YEAR(B30),"0000")&"-"&TEXT(ROW()-7,"0000")) -> INC-2026-0023 | V30: =IF(B30="","",TEXT(B30,"mmmm")) -> August | W30: =IF(B30="","",MONTH(B30)) -> 8 | X30: =IF(B30="","",YEAR(B30)) -> 2026 | Y30: =IF(B30="","",DAY(B30)) -> 20 | Z30: =IF(B30="","",IF(WEEKDAY(B30,2)>5,"Weekend","Weekday")) -> Weekday | AA30: =IF(B30="","",IF(COUNTIFS($B$8:$B$1007,B30,$E$8:$E$1007,E30,$D$8:$D$1007,D30,$I$8:$I$1007,I30)>1,"Possible Duplicate","OK")) -> OK | AB30: =IF(OR(B30="",C30<>"Expense"),"",IF(E30>IFERROR(AVERAGEIFS($E$8:$E$1007,$I$8:$I$1007,I30,$C$8:$C$1007,"Expense")*SETTINGS!$B$20,0),"Unusually High","Normal")) | AC30: Yes | AF30: =IF(A30<>"Yes","No",IF(AND(AC30="Yes",SETTINGS!$B$16="No"),"No","Yes")) -> Yes | AG30: =IF(A30<>"Yes","",IF(OR(B30="",D30="",E30<=0,F30="",I30=""),"Check Required Fields",IF(AA30="Possible Duplicate","Possible Duplicate",IF(E30>SETTINGS!$B$22,"Review Extreme Value","OK")))) -> OK
A31: Yes | B31: 46244 | C31: Expense | D31: Monthly food | E31: 3400 | F31: UPI | G31: Food | H31: =IF(D31="","",IF(ISNUMBER(SEARCH(SETTINGS!$K$4,D31)),SETTINGS!$L$4,IF(ISNUMBER(SEARCH(SETTINGS!$K$5,D31)),SETTINGS!$L$5,IF(ISNUMBER(SEARCH(SETTINGS!$K$6,D31)),SETTINGS!$L$6,IF(ISNUMBER(SEARCH(SETTINGS!$K$7,D31)),SETTINGS!$L$7,IF(ISNUMBER(SEARCH(SETTINGS!$K$8,D31)),SETTINGS!$L$8,IF(ISNUMBER(SEARCH(SETTINGS!$K$9,D31)),SETTINGS!$L$9,IF(ISNUMBER(SEARCH(SETTINGS!$K$10,D31)),SETTINGS!$L$10,IF(ISNUMBER(SEARCH(SETTINGS!$K$11,D31)),SETTINGS!$L$11,IF(ISNUMBER(SEARCH(SETTINGS!$K$12,D31)),SETTINGS!$L$12,IF(ISNUMBER(SEARCH(SETTINGS!$K$13,D31)),SETTINGS!$L$13,IF(ISNUMBER(SEARCH(SETTINGS!$K$14,D31)),SETTINGS!$L$14,IF(ISNUMBER(SEARCH(SETTINGS!$K$15,D31)),SETTINGS!$L$15,IF(ISNUMBER(SEARCH(SETTINGS!$K$16,D31)),SETTINGS!$L$16,IF(ISNUMBER(SEARCH(SETTINGS!$K$17,D31)),SETTINGS!$L$17,IF(ISNUMBER(SEARCH(SETTINGS!$K$18,D31)),SETTINGS!$L$18,"Miscellaneous")))))))))))))))) -> Miscellaneous | I31: =IF(B31="","",IF(G31<>"",G31,H31)) -> Food | J31: Mess | K31: Hostel Mess | L31: UPI-linked Bank | M31: Essential | N31: One-Time | O31: Paid | Q31: Self | R31: Not Applicable | S31: Hostel | U31: =IF(B31="","",IF(C31="Income","INC-",IF(C31="Expense","EXP-","TRX-"))&TEXT(YEAR(B31),"0000")&"-"&TEXT(ROW()-7,"0000")) -> EXP-2026-0024 | V31: =IF(B31="","",TEXT(B31,"mmmm")) -> August | W31: =IF(B31="","",MONTH(B31)) -> 8 | X31: =IF(B31="","",YEAR(B31)) -> 2026 | Y31: =IF(B31="","",DAY(B31)) -> 10 | Z31: =IF(B31="","",IF(WEEKDAY(B31,2)>5,"Weekend","Weekday")) -> Weekday | AA31: =IF(B31="","",IF(COUNTIFS($B$8:$B$1007,B31,$E$8:$E$1007,E31,$D$8:$D$1007,D31,$I$8:$I$1007,I31)>1,"Possible Duplicate","OK")) -> OK | AB31: =IF(OR(B31="",C31<>"Expense"),"",IF(E31>IFERROR(AVERAGEIFS($E$8:$E$1007,$I$8:$I$1007,I31,$C$8:$C$1007,"Expense")*SETTINGS!$B$20,0),"Unusually High","Normal")) -> Normal | AC31: Yes | AF31: =IF(A31<>"Yes","No",IF(AND(AC31="Yes",SETTINGS!$B$16="No"),"No","Yes")) -> Yes | AG31: =IF(A31<>"Yes","",IF(OR(B31="",D31="",E31<=0,F31="",I31=""),"Check Required Fields",IF(AA31="Possible Duplicate","Possible Duplicate",IF(E31>SETTINGS!$B$22,"Review Extreme Value","OK")))) -> OK
A32: Yes | B32: 46252 | C32: Expense | D32: Trip home by train | E32: 1800 | F32: UPI | G32: Travel Home | H32: =IF(D32="","",IF(ISNUMBER(SEARCH(SETTINGS!$K$4,D32)),SETTINGS!$L$4,IF(ISNUMBER(SEARCH(SETTINGS!$K$5,D32)),SETTINGS!$L$5,IF(ISNUMBER(SEARCH(SETTINGS!$K$6,D32)),SETTINGS!$L$6,IF(ISNUMBER(SEARCH(SETTINGS!$K$7,D32)),SETTINGS!$L$7,IF(ISNUMBER(SEARCH(SETTINGS!$K$8,D32)),SETTINGS!$L$8,IF(ISNUMBER(SEARCH(SETTINGS!$K$9,D32)),SETTINGS!$L$9,IF(ISNUMBER(SEARCH(SETTINGS!$K$10,D32)),SETTINGS!$L$10,IF(ISNUMBER(SEARCH(SETTINGS!$K$11,D32)),SETTINGS!$L$11,IF(ISNUMBER(SEARCH(SETTINGS!$K$12,D32)),SETTINGS!$L$12,IF(ISNUMBER(SEARCH(SETTINGS!$K$13,D32)),SETTINGS!$L$13,IF(ISNUMBER(SEARCH(SETTINGS!$K$14,D32)),SETTINGS!$L$14,IF(ISNUMBER(SEARCH(SETTINGS!$K$15,D32)),SETTINGS!$L$15,IF(ISNUMBER(SEARCH(SETTINGS!$K$16,D32)),SETTINGS!$L$16,IF(ISNUMBER(SEARCH(SETTINGS!$K$17,D32)),SETTINGS!$L$17,IF(ISNUMBER(SEARCH(SETTINGS!$K$18,D32)),SETTINGS!$L$18,"Miscellaneous")))))))))))))))) -> Miscellaneous | I32: =IF(B32="","",IF(G32<>"",G32,H32)) -> Travel Home | J32: Train | K32: IRCTC | L32: UPI-linked Bank | M32: Essential | N32: One-Time | O32: Paid | Q32: Self | R32: Not Applicable | S32: Travel | U32: =IF(B32="","",IF(C32="Income","INC-",IF(C32="Expense","EXP-","TRX-"))&TEXT(YEAR(B32),"0000")&"-"&TEXT(ROW()-7,"0000")) -> EXP-2026-0025 | V32: =IF(B32="","",TEXT(B32,"mmmm")) -> August | W32: =IF(B32="","",MONTH(B32)) -> 8 | X32: =IF(B32="","",YEAR(B32)) -> 2026 | Y32: =IF(B32="","",DAY(B32)) -> 18 | Z32: =IF(B32="","",IF(WEEKDAY(B32,2)>5,"Weekend","Weekday")) -> Weekday | AA32: =IF(B32="","",IF(COUNTIFS($B$8:$B$1007,B32,$E$8:$E$1007,E32,$D$8:$D$1007,D32,$I$8:$I$1007,I32)>1,"Possible Duplicate","OK")) -> OK | AB32: =IF(OR(B32="",C32<>"Expense"),"",IF(E32>IFERROR(AVERAGEIFS($E$8:$E$1007,$I$8:$I$1007,I32,$C$8:$C$1007,"Expense")*SETTINGS!$B$20,0),"Unusually High","Normal")) -> Normal | AC32: Yes | AF32: =IF(A32<>"Yes","No",IF(AND(AC32="Yes",SETTINGS!$B$16="No"),"No","Yes")) -> Yes | AG32: =IF(A32<>"Yes","",IF(OR(B32="",D32="",E32<=0,F32="",I32=""),"Check Required Fields",IF(AA32="Possible Duplicate","Possible Duplicate",IF(E32>SETTINGS!$B$22,"Review Extreme Value","OK")))) -> OK
A33: Yes | B33: 46262 | C33: Savings Transfer | D33: Emergency fund contribution | E33: 2000 | F33: Bank Transfer | G33: Savings | H33: =IF(D33="","",IF(ISNUMBER(SEARCH(SETTINGS!$K$4,D33)),SETTINGS!$L$4,IF(ISNUMBER(SEARCH(SETTINGS!$K$5,D33)),SETTINGS!$L$5,IF(ISNUMBER(SEARCH(SETTINGS!$K$6,D33)),SETTINGS!$L$6,IF(ISNUMBER(SEARCH(SETTINGS!$K$7,D33)),SETTINGS!$L$7,IF(ISNUMBER(SEARCH(SETTINGS!$K$8,D33)),SETTINGS!$L$8,IF(ISNUMBER(SEARCH(SETTINGS!$K$9,D33)),SETTINGS!$L$9,IF(ISNUMBER(SEARCH(SETTINGS!$K$10,D33)),SETTINGS!$L$10,IF(ISNUMBER(SEARCH(SETTINGS!$K$11,D33)),SETTINGS!$L$11,IF(ISNUMBER(SEARCH(SETTINGS!$K$12,D33)),SETTINGS!$L$12,IF(ISNUMBER(SEARCH(SETTINGS!$K$13,D33)),SETTINGS!$L$13,IF(ISNUMBER(SEARCH(SETTINGS!$K$14,D33)),SETTINGS!$L$14,IF(ISNUMBER(SEARCH(SETTINGS!$K$15,D33)),SETTINGS!$L$15,IF(ISNUMBER(SEARCH(SETTINGS!$K$16,D33)),SETTINGS!$L$16,IF(ISNUMBER(SEARCH(SETTINGS!$K$17,D33)),SETTINGS!$L$17,IF(ISNUMBER(SEARCH(SETTINGS!$K$18,D33)),SETTINGS!$L$18,"Miscellaneous")))))))))))))))) -> Miscellaneous | I33: =IF(B33="","",IF(G33<>"",G33,H33)) -> Savings | J33: Emergency Fund | L33: Savings Account | M33: Essential | N33: One-Time | O33: Paid | Q33: Self | R33: Not Applicable | S33: Emergency | U33: =IF(B33="","",IF(C33="Income","INC-",IF(C33="Expense","EXP-","TRX-"))&TEXT(YEAR(B33),"0000")&"-"&TEXT(ROW()-7,"0000")) -> TRX-2026-0026 | V33: =IF(B33="","",TEXT(B33,"mmmm")) -> August | W33: =IF(B33="","",MONTH(B33)) -> 8 | X33: =IF(B33="","",YEAR(B33)) -> 2026 | Y33: =IF(B33="","",DAY(B33)) -> 28 | Z33: =IF(B33="","",IF(WEEKDAY(B33,2)>5,"Weekend","Weekday")) -> Weekday | AA33: =IF(B33="","",IF(COUNTIFS($B$8:$B$1007,B33,$E$8:$E$1007,E33,$D$8:$D$1007,D33,$I$8:$I$1007,I33)>1,"Possible Duplicate","OK")) -> OK | AB33: =IF(OR(B33="",C33<>"Expense"),"",IF(E33>IFERROR(AVERAGEIFS($E$8:$E$1007,$I$8:$I$1007,I33,$C$8:$C$1007,"Expense")*SETTINGS!$B$20,0),"Unusually High","Normal")) | AC33: Yes | AF33: =IF(A33<>"Yes","No",IF(AND(AC33="Yes",SETTINGS!$B$16="No"),"No","Yes")) -> Yes | AG33: =IF(A33<>"Yes","",IF(OR(B33="",D33="",E33<=0,F33="",I33=""),"Check Required Fields",IF(AA33="Possible Duplicate","Possible Duplicate",IF(E33>SETTINGS!$B$22,"Review Extreme Value","OK")))) -> OK
A34: Yes | B34: 46266 | C34: Income | D34: Monthly Allowance - September | E34: 25000 | F34: Bank Transfer | G34: Miscellaneous | H34: =IF(D34="","",IF(ISNUMBER(SEARCH(SETTINGS!$K$4,D34)),SETTINGS!$L$4,IF(ISNUMBER(SEARCH(SETTINGS!$K$5,D34)),SETTINGS!$L$5,IF(ISNUMBER(SEARCH(SETTINGS!$K$6,D34)),SETTINGS!$L$6,IF(ISNUMBER(SEARCH(SETTINGS!$K$7,D34)),SETTINGS!$L$7,IF(ISNUMBER(SEARCH(SETTINGS!$K$8,D34)),SETTINGS!$L$8,IF(ISNUMBER(SEARCH(SETTINGS!$K$9,D34)),SETTINGS!$L$9,IF(ISNUMBER(SEARCH(SETTINGS!$K$10,D34)),SETTINGS!$L$10,IF(ISNUMBER(SEARCH(SETTINGS!$K$11,D34)),SETTINGS!$L$11,IF(ISNUMBER(SEARCH(SETTINGS!$K$12,D34)),SETTINGS!$L$12,IF(ISNUMBER(SEARCH(SETTINGS!$K$13,D34)),SETTINGS!$L$13,IF(ISNUMBER(SEARCH(SETTINGS!$K$14,D34)),SETTINGS!$L$14,IF(ISNUMBER(SEARCH(SETTINGS!$K$15,D34)),SETTINGS!$L$15,IF(ISNUMBER(SEARCH(SETTINGS!$K$16,D34)),SETTINGS!$L$16,IF(ISNUMBER(SEARCH(SETTINGS!$K$17,D34)),SETTINGS!$L$17,IF(ISNUMBER(SEARCH(SETTINGS!$K$18,D34)),SETTINGS!$L$18,"Miscellaneous")))))))))))))))) -> Miscellaneous | I34: =IF(B34="","",IF(G34<>"",G34,H34)) -> Miscellaneous | J34: Monthly Allowance | L34: Primary Bank | M34: Essential | N34: Recurring | O34: Paid | Q34: Self | R34: Not Applicable | S34: Home | U34: =IF(B34="","",IF(C34="Income","INC-",IF(C34="Expense","EXP-","TRX-"))&TEXT(YEAR(B34),"0000")&"-"&TEXT(ROW()-7,"0000")) -> INC-2026-0027 | V34: =IF(B34="","",TEXT(B34,"mmmm")) -> September | W34: =IF(B34="","",MONTH(B34)) -> 9 | X34: =IF(B34="","",YEAR(B34)) -> 2026 | Y34: =IF(B34="","",DAY(B34)) -> 1 | Z34: =IF(B34="","",IF(WEEKDAY(B34,2)>5,"Weekend","Weekday")) -> Weekday | AA34: =IF(B34="","",IF(COUNTIFS($B$8:$B$1007,B34,$E$8:$E$1007,E34,$D$8:$D$1007,D34,$I$8:$I$1007,I34)>1,"Possible Duplicate","OK")) -> OK | AB34: =IF(OR(B34="",C34<>"Expense"),"",IF(E34>IFERROR(AVERAGEIFS($E$8:$E$1007,$I$8:$I$1007,I34,$C$8:$C$1007,"Expense")*SETTINGS!$B$20,0),"Unusually High","Normal")) | AC34: Yes | AF34: =IF(A34<>"Yes","No",IF(AND(AC34="Yes",SETTINGS!$B$16="No"),"No","Yes")) -> Yes | AG34: =IF(A34<>"Yes","",IF(OR(B34="",D34="",E34<=0,F34="",I34=""),"Check Required Fields",IF(AA34="Possible Duplicate","Possible Duplicate",IF(E34>SETTINGS!$B$22,"Review Extreme Value","OK")))) -> OK
A35: Yes | B35: 46266 | C35: Expense | D35: Hostel Mess September | E35: 3200 | F35: UPI | G35: Hostel | H35: =IF(D35="","",IF(ISNUMBER(SEARCH(SETTINGS!$K$4,D35)),SETTINGS!$L$4,IF(ISNUMBER(SEARCH(SETTINGS!$K$5,D35)),SETTINGS!$L$5,IF(ISNUMBER(SEARCH(SETTINGS!$K$6,D35)),SETTINGS!$L$6,IF(ISNUMBER(SEARCH(SETTINGS!$K$7,D35)),SETTINGS!$L$7,IF(ISNUMBER(SEARCH(SETTINGS!$K$8,D35)),SETTINGS!$L$8,IF(ISNUMBER(SEARCH(SETTINGS!$K$9,D35)),SETTINGS!$L$9,IF(ISNUMBER(SEARCH(SETTINGS!$K$10,D35)),SETTINGS!$L$10,IF(ISNUMBER(SEARCH(SETTINGS!$K$11,D35)),SETTINGS!$L$11,IF(ISNUMBER(SEARCH(SETTINGS!$K$12,D35)),SETTINGS!$L$12,IF(ISNUMBER(SEARCH(SETTINGS!$K$13,D35)),SETTINGS!$L$13,IF(ISNUMBER(SEARCH(SETTINGS!$K$14,D35)),SETTINGS!$L$14,IF(ISNUMBER(SEARCH(SETTINGS!$K$15,D35)),SETTINGS!$L$15,IF(ISNUMBER(SEARCH(SETTINGS!$K$16,D35)),SETTINGS!$L$16,IF(ISNUMBER(SEARCH(SETTINGS!$K$17,D35)),SETTINGS!$L$17,IF(ISNUMBER(SEARCH(SETTINGS!$K$18,D35)),SETTINGS!$L$18,"Miscellaneous")))))))))))))))) -> Hostel | I35: =IF(B35="","",IF(G35<>"",G35,H35)) -> Hostel | J35: Mess | K35: Hostel Mess | L35: UPI-linked Bank | M35: Essential | N35: Recurring | O35: Paid | P35: 46266 | Q35: Self | R35: Semester 1 | S35: Hostel | U35: =IF(B35="","",IF(C35="Income","INC-",IF(C35="Expense","EXP-","TRX-"))&TEXT(YEAR(B35),"0000")&"-"&TEXT(ROW()-7,"0000")) -> EXP-2026-0028 | V35: =IF(B35="","",TEXT(B35,"mmmm")) -> September | W35: =IF(B35="","",MONTH(B35)) -> 9 | X35: =IF(B35="","",YEAR(B35)) -> 2026 | Y35: =IF(B35="","",DAY(B35)) -> 1 | Z35: =IF(B35="","",IF(WEEKDAY(B35,2)>5,"Weekend","Weekday")) -> Weekday | AA35: =IF(B35="","",IF(COUNTIFS($B$8:$B$1007,B35,$E$8:$E$1007,E35,$D$8:$D$1007,D35,$I$8:$I$1007,I35)>1,"Possible Duplicate","OK")) -> OK | AB35: =IF(OR(B35="",C35<>"Expense"),"",IF(E35>IFERROR(AVERAGEIFS($E$8:$E$1007,$I$8:$I$1007,I35,$C$8:$C$1007,"Expense")*SETTINGS!$B$20,0),"Unusually High","Normal")) -> Normal | AC35: Yes | AF35: =IF(A35<>"Yes","No",IF(AND(AC35="Yes",SETTINGS!$B$16="No"),"No","Yes")) -> Yes | AG35: =IF(A35<>"Yes","",IF(OR(B35="",D35="",E35<=0,F35="",I35=""),"Check Required Fields",IF(AA35="Possible Duplicate","Possible Duplicate",IF(E35>SETTINGS!$B$22,"Review Extreme Value","OK")))) -> OK
A36: Yes | B36: 46267 | C36: Expense | D36: Zomato dinner | E36: 620 | F36: GPay | G36: Food | H36: =IF(D36="","",IF(ISNUMBER(SEARCH(SETTINGS!$K$4,D36)),SETTINGS!$L$4,IF(ISNUMBER(SEARCH(SETTINGS!$K$5,D36)),SETTINGS!$L$5,IF(ISNUMBER(SEARCH(SETTINGS!$K$6,D36)),SETTINGS!$L$6,IF(ISNUMBER(SEARCH(SETTINGS!$K$7,D36)),SETTINGS!$L$7,IF(ISNUMBER(SEARCH(SETTINGS!$K$8,D36)),SETTINGS!$L$8,IF(ISNUMBER(SEARCH(SETTINGS!$K$9,D36)),SETTINGS!$L$9,IF(ISNUMBER(SEARCH(SETTINGS!$K$10,D36)),SETTINGS!$L$10,IF(ISNUMBER(SEARCH(SETTINGS!$K$11,D36)),SETTINGS!$L$11,IF(ISNUMBER(SEARCH(SETTINGS!$K$12,D36)),SETTINGS!$L$12,IF(ISNUMBER(SEARCH(SETTINGS!$K$13,D36)),SETTINGS!$L$13,IF(ISNUMBER(SEARCH(SETTINGS!$K$14,D36)),SETTINGS!$L$14,IF(ISNUMBER(SEARCH(SETTINGS!$K$15,D36)),SETTINGS!$L$15,IF(ISNUMBER(SEARCH(SETTINGS!$K$16,D36)),SETTINGS!$L$16,IF(ISNUMBER(SEARCH(SETTINGS!$K$17,D36)),SETTINGS!$L$17,IF(ISNUMBER(SEARCH(SETTINGS!$K$18,D36)),SETTINGS!$L$18,"Miscellaneous")))))))))))))))) -> Food | I36: =IF(B36="","",IF(G36<>"",G36,H36)) -> Food | J36: Dinner Outside | K36: Zomato | L36: UPI-linked Bank | M36: Optional | N36: One-Time | O36: Paid | Q36: Self | R36: Not Applicable | S36: Outside Meal | U36: =IF(B36="","",IF(C36="Income","INC-",IF(C36="Expense","EXP-","TRX-"))&TEXT(YEAR(B36),"0000")&"-"&TEXT(ROW()-7,"0000")) -> EXP-2026-0029 | V36: =IF(B36="","",TEXT(B36,"mmmm")) -> September | W36: =IF(B36="","",MONTH(B36)) -> 9 | X36: =IF(B36="","",YEAR(B36)) -> 2026 | Y36: =IF(B36="","",DAY(B36)) -> 2 | Z36: =IF(B36="","",IF(WEEKDAY(B36,2)>5,"Weekend","Weekday")) -> Weekday | AA36: =IF(B36="","",IF(COUNTIFS($B$8:$B$1007,B36,$E$8:$E$1007,E36,$D$8:$D$1007,D36,$I$8:$I$1007,I36)>1,"Possible Duplicate","OK")) -> OK | AB36: =IF(OR(B36="",C36<>"Expense"),"",IF(E36>IFERROR(AVERAGEIFS($E$8:$E$1007,$I$8:$I$1007,I36,$C$8:$C$1007,"Expense")*SETTINGS!$B$20,0),"Unusually High","Normal")) -> Normal | AC36: Yes | AF36: =IF(A36<>"Yes","No",IF(AND(AC36="Yes",SETTINGS!$B$16="No"),"No","Yes")) -> Yes | AG36: =IF(A36<>"Yes","",IF(OR(B36="",D36="",E36<=0,F36="",I36=""),"Check Required Fields",IF(AA36="Possible Duplicate","Possible Duplicate",IF(E36>SETTINGS!$B$22,"Review Extreme Value","OK")))) -> OK
A37: Yes | B37: 46267 | C37: Expense | D37: Uber to railway station | E37: 350 | F37: PhonePe | G37: Transport | H37: =IF(D37="","",IF(ISNUMBER(SEARCH(SETTINGS!$K$4,D37)),SETTINGS!$L$4,IF(ISNUMBER(SEARCH(SETTINGS!$K$5,D37)),SETTINGS!$L$5,IF(ISNUMBER(SEARCH(SETTINGS!$K$6,D37)),SETTINGS!$L$6,IF(ISNUMBER(SEARCH(SETTINGS!$K$7,D37)),SETTINGS!$L$7,IF(ISNUMBER(SEARCH(SETTINGS!$K$8,D37)),SETTINGS!$L$8,IF(ISNUMBER(SEARCH(SETTINGS!$K$9,D37)),SETTINGS!$L$9,IF(ISNUMBER(SEARCH(SETTINGS!$K$10,D37)),SETTINGS!$L$10,IF(ISNUMBER(SEARCH(SETTINGS!$K$11,D37)),SETTINGS!$L$11,IF(ISNUMBER(SEARCH(SETTINGS!$K$12,D37)),SETTINGS!$L$12,IF(ISNUMBER(SEARCH(SETTINGS!$K$13,D37)),SETTINGS!$L$13,IF(ISNUMBER(SEARCH(SETTINGS!$K$14,D37)),SETTINGS!$L$14,IF(ISNUMBER(SEARCH(SETTINGS!$K$15,D37)),SETTINGS!$L$15,IF(ISNUMBER(SEARCH(SETTINGS!$K$16,D37)),SETTINGS!$L$16,IF(ISNUMBER(SEARCH(SETTINGS!$K$17,D37)),SETTINGS!$L$17,IF(ISNUMBER(SEARCH(SETTINGS!$K$18,D37)),SETTINGS!$L$18,"Miscellaneous")))))))))))))))) -> Transport | I37: =IF(B37="","",IF(G37<>"",G37,H37)) -> Transport | J37: Cab | K37: Uber | L37: UPI-linked Bank | M37: Useful | N37: One-Time | O37: Paid | Q37: Self | R37: Not Applicable | S37: Travel | U37: =IF(B37="","",IF(C37="Income","INC-",IF(C37="Expense","EXP-","TRX-"))&TEXT(YEAR(B37),"0000")&"-"&TEXT(ROW()-7,"0000")) -> EXP-2026-0030 | V37: =IF(B37="","",TEXT(B37,"mmmm")) -> September | W37: =IF(B37="","",MONTH(B37)) -> 9 | X37: =IF(B37="","",YEAR(B37)) -> 2026 | Y37: =IF(B37="","",DAY(B37)) -> 2 | Z37: =IF(B37="","",IF(WEEKDAY(B37,2)>5,"Weekend","Weekday")) -> Weekday | AA37: =IF(B37="","",IF(COUNTIFS($B$8:$B$1007,B37,$E$8:$E$1007,E37,$D$8:$D$1007,D37,$I$8:$I$1007,I37)>1,"Possible Duplicate","OK")) -> OK | AB37: =IF(OR(B37="",C37<>"Expense"),"",IF(E37>IFERROR(AVERAGEIFS($E$8:$E$1007,$I$8:$I$1007,I37,$C$8:$C$1007,"Expense")*SETTINGS!$B$20,0),"Unusually High","Normal")) -> Normal | AC37: Yes | AF37: =IF(A37<>"Yes","No",IF(AND(AC37="Yes",SETTINGS!$B$16="No"),"No","Yes")) -> Yes | AG37: =IF(A37<>"Yes","",IF(OR(B37="",D37="",E37<=0,F37="",I37=""),"Check Required Fields",IF(AA37="Possible Duplicate","Possible Duplicate",IF(E37>SETTINGS!$B$22,"Review Extreme Value","OK")))) -> OK
A38: Yes | B38: 46267 | C38: Expense | D38: Udemy deep learning course | E38: 1499 | F38: Debit Card | G38: AI-ML Learning | H38: =IF(D38="","",IF(ISNUMBER(SEARCH(SETTINGS!$K$4,D38)),SETTINGS!$L$4,IF(ISNUMBER(SEARCH(SETTINGS!$K$5,D38)),SETTINGS!$L$5,IF(ISNUMBER(SEARCH(SETTINGS!$K$6,D38)),SETTINGS!$L$6,IF(ISNUMBER(SEARCH(SETTINGS!$K$7,D38)),SETTINGS!$L$7,IF(ISNUMBER(SEARCH(SETTINGS!$K$8,D38)),SETTINGS!$L$8,IF(ISNUMBER(SEARCH(SETTINGS!$K$9,D38)),SETTINGS!$L$9,IF(ISNUMBER(SEARCH(SETTINGS!$K$10,D38)),SETTINGS!$L$10,IF(ISNUMBER(SEARCH(SETTINGS!$K$11,D38)),SETTINGS!$L$11,IF(ISNUMBER(SEARCH(SETTINGS!$K$12,D38)),SETTINGS!$L$12,IF(ISNUMBER(SEARCH(SETTINGS!$K$13,D38)),SETTINGS!$L$13,IF(ISNUMBER(SEARCH(SETTINGS!$K$14,D38)),SETTINGS!$L$14,IF(ISNUMBER(SEARCH(SETTINGS!$K$15,D38)),SETTINGS!$L$15,IF(ISNUMBER(SEARCH(SETTINGS!$K$16,D38)),SETTINGS!$L$16,IF(ISNUMBER(SEARCH(SETTINGS!$K$17,D38)),SETTINGS!$L$17,IF(ISNUMBER(SEARCH(SETTINGS!$K$18,D38)),SETTINGS!$L$18,"Miscellaneous")))))))))))))))) -> AI-ML Learning | I38: =IF(B38="","",IF(G38<>"",G38,H38)) -> AI-ML Learning | J38: Course | K38: Udemy | L38: UPI-linked Bank | M38: Essential | N38: One-Time | O38: Paid | Q38: Self | R38: Not Applicable | S38: College | U38: =IF(B38="","",IF(C38="Income","INC-",IF(C38="Expense","EXP-","TRX-"))&TEXT(YEAR(B38),"0000")&"-"&TEXT(ROW()-7,"0000")) -> EXP-2026-0031 | V38: =IF(B38="","",TEXT(B38,"mmmm")) -> September | W38: =IF(B38="","",MONTH(B38)) -> 9 | X38: =IF(B38="","",YEAR(B38)) -> 2026 | Y38: =IF(B38="","",DAY(B38)) -> 2 | Z38: =IF(B38="","",IF(WEEKDAY(B38,2)>5,"Weekend","Weekday")) -> Weekday | AA38: =IF(B38="","",IF(COUNTIFS($B$8:$B$1007,B38,$E$8:$E$1007,E38,$D$8:$D$1007,D38,$I$8:$I$1007,I38)>1,"Possible Duplicate","OK")) -> OK | AB38: =IF(OR(B38="",C38<>"Expense"),"",IF(E38>IFERROR(AVERAGEIFS($E$8:$E$1007,$I$8:$I$1007,I38,$C$8:$C$1007,"Expense")*SETTINGS!$B$20,0),"Unusually High","Normal")) -> Normal | AC38: Yes | AF38: =IF(A38<>"Yes","No",IF(AND(AC38="Yes",SETTINGS!$B$16="No"),"No","Yes")) -> Yes | AG38: =IF(A38<>"Yes","",IF(OR(B38="",D38="",E38<=0,F38="",I38=""),"Check Required Fields",IF(AA38="Possible Duplicate","Possible Duplicate",IF(E38>SETTINGS!$B$22,"Review Extreme Value","OK")))) -> OK
A39: Yes | B39: 46267 | C39: Expense | D39: Mobile recharge | E39: 349 | F39: UPI | G39: Mobile & Internet | H39: =IF(D39="","",IF(ISNUMBER(SEARCH(SETTINGS!$K$4,D39)),SETTINGS!$L$4,IF(ISNUMBER(SEARCH(SETTINGS!$K$5,D39)),SETTINGS!$L$5,IF(ISNUMBER(SEARCH(SETTINGS!$K$6,D39)),SETTINGS!$L$6,IF(ISNUMBER(SEARCH(SETTINGS!$K$7,D39)),SETTINGS!$L$7,IF(ISNUMBER(SEARCH(SETTINGS!$K$8,D39)),SETTINGS!$L$8,IF(ISNUMBER(SEARCH(SETTINGS!$K$9,D39)),SETTINGS!$L$9,IF(ISNUMBER(SEARCH(SETTINGS!$K$10,D39)),SETTINGS!$L$10,IF(ISNUMBER(SEARCH(SETTINGS!$K$11,D39)),SETTINGS!$L$11,IF(ISNUMBER(SEARCH(SETTINGS!$K$12,D39)),SETTINGS!$L$12,IF(ISNUMBER(SEARCH(SETTINGS!$K$13,D39)),SETTINGS!$L$13,IF(ISNUMBER(SEARCH(SETTINGS!$K$14,D39)),SETTINGS!$L$14,IF(ISNUMBER(SEARCH(SETTINGS!$K$15,D39)),SETTINGS!$L$15,IF(ISNUMBER(SEARCH(SETTINGS!$K$16,D39)),SETTINGS!$L$16,IF(ISNUMBER(SEARCH(SETTINGS!$K$17,D39)),SETTINGS!$L$17,IF(ISNUMBER(SEARCH(SETTINGS!$K$18,D39)),SETTINGS!$L$18,"Miscellaneous")))))))))))))))) -> Mobile & Internet | I39: =IF(B39="","",IF(G39<>"",G39,H39)) -> Mobile & Internet | J39: Mobile Recharge | K39: Jio | L39: UPI-linked Bank | M39: Essential | N39: Recurring | O39: Paid | Q39: Self | R39: Not Applicable | S39: Subscription | U39: =IF(B39="","",IF(C39="Income","INC-",IF(C39="Expense","EXP-","TRX-"))&TEXT(YEAR(B39),"0000")&"-"&TEXT(ROW()-7,"0000")) -> EXP-2026-0032 | V39: =IF(B39="","",TEXT(B39,"mmmm")) -> September | W39: =IF(B39="","",MONTH(B39)) -> 9 | X39: =IF(B39="","",YEAR(B39)) -> 2026 | Y39: =IF(B39="","",DAY(B39)) -> 2 | Z39: =IF(B39="","",IF(WEEKDAY(B39,2)>5,"Weekend","Weekday")) -> Weekday | AA39: =IF(B39="","",IF(COUNTIFS($B$8:$B$1007,B39,$E$8:$E$1007,E39,$D$8:$D$1007,D39,$I$8:$I$1007,I39)>1,"Possible Duplicate","OK")) -> OK | AB39: =IF(OR(B39="",C39<>"Expense"),"",IF(E39>IFERROR(AVERAGEIFS($E$8:$E$1007,$I$8:$I$1007,I39,$C$8:$C$1007,"Expense")*SETTINGS!$B$20,0),"Unusually High","Normal")) -> Normal | AC39: Yes | AF39: =IF(A39<>"Yes","No",IF(AND(AC39="Yes",SETTINGS!$B$16="No"),"No","Yes")) -> Yes | AG39: =IF(A39<>"Yes","",IF(OR(B39="",D39="",E39<=0,F39="",I39=""),"Check Required Fields",IF(AA39="Possible Duplicate","Possible Duplicate",IF(E39>SETTINGS!$B$22,"Review Extreme Value","OK")))) -> OK
A40: Yes | B40: 46267 | C40: Expense | D40: Netflix monthly plan | E40: 199 | F40: UPI | G40: Subscriptions | H40: =IF(D40="","",IF(ISNUMBER(SEARCH(SETTINGS!$K$4,D40)),SETTINGS!$L$4,IF(ISNUMBER(SEARCH(SETTINGS!$K$5,D40)),SETTINGS!$L$5,IF(ISNUMBER(SEARCH(SETTINGS!$K$6,D40)),SETTINGS!$L$6,IF(ISNUMBER(SEARCH(SETTINGS!$K$7,D40)),SETTINGS!$L$7,IF(ISNUMBER(SEARCH(SETTINGS!$K$8,D40)),SETTINGS!$L$8,IF(ISNUMBER(SEARCH(SETTINGS!$K$9,D40)),SETTINGS!$L$9,IF(ISNUMBER(SEARCH(SETTINGS!$K$10,D40)),SETTINGS!$L$10,IF(ISNUMBER(SEARCH(SETTINGS!$K$11,D40)),SETTINGS!$L$11,IF(ISNUMBER(SEARCH(SETTINGS!$K$12,D40)),SETTINGS!$L$12,IF(ISNUMBER(SEARCH(SETTINGS!$K$13,D40)),SETTINGS!$L$13,IF(ISNUMBER(SEARCH(SETTINGS!$K$14,D40)),SETTINGS!$L$14,IF(ISNUMBER(SEARCH(SETTINGS!$K$15,D40)),SETTINGS!$L$15,IF(ISNUMBER(SEARCH(SETTINGS!$K$16,D40)),SETTINGS!$L$16,IF(ISNUMBER(SEARCH(SETTINGS!$K$17,D40)),SETTINGS!$L$17,IF(ISNUMBER(SEARCH(SETTINGS!$K$18,D40)),SETTINGS!$L$18,"Miscellaneous")))))))))))))))) -> Subscriptions | I40: =IF(B40="","",IF(G40<>"",G40,H40)) -> Subscriptions | J40: OTT | K40: Netflix | L40: UPI-linked Bank | M40: Optional | N40: Recurring | O40: Paid | Q40: Self | R40: Not Applicable | S40: Subscription | U40: =IF(B40="","",IF(C40="Income","INC-",IF(C40="Expense","EXP-","TRX-"))&TEXT(YEAR(B40),"0000")&"-"&TEXT(ROW()-7,"0000")) -> EXP-2026-0033 | V40: =IF(B40="","",TEXT(B40,"mmmm")) -> September | W40: =IF(B40="","",MONTH(B40)) -> 9 | X40: =IF(B40="","",YEAR(B40)) -> 2026 | Y40: =IF(B40="","",DAY(B40)) -> 2 | Z40: =IF(B40="","",IF(WEEKDAY(B40,2)>5,"Weekend","Weekday")) -> Weekday | AA40: =IF(B40="","",IF(COUNTIFS($B$8:$B$1007,B40,$E$8:$E$1007,E40,$D$8:$D$1007,D40,$I$8:$I$1007,I40)>1,"Possible Duplicate","OK")) -> OK | AB40: =IF(OR(B40="",C40<>"Expense"),"",IF(E40>IFERROR(AVERAGEIFS($E$8:$E$1007,$I$8:$I$1007,I40,$C$8:$C$1007,"Expense")*SETTINGS!$B$20,0),"Unusually High","Normal")) -> Normal | AC40: Yes | AF40: =IF(A40<>"Yes","No",IF(AND(AC40="Yes",SETTINGS!$B$16="No"),"No","Yes")) -> Yes | AG40: =IF(A40<>"Yes","",IF(OR(B40="",D40="",E40<=0,F40="",I40=""),"Check Required Fields",IF(AA40="Possible Duplicate","Possible Duplicate",IF(E40>SETTINGS!$B$22,"Review Extreme Value","OK")))) -> OK
A41: Yes | B41: 46267 | C41: Expense | D41: Notebook and pens | E41: 280 | F41: Cash | G41: Books & Stationery | H41: =IF(D41="","",IF(ISNUMBER(SEARCH(SETTINGS!$K$4,D41)),SETTINGS!$L$4,IF(ISNUMBER(SEARCH(SETTINGS!$K$5,D41)),SETTINGS!$L$5,IF(ISNUMBER(SEARCH(SETTINGS!$K$6,D41)),SETTINGS!$L$6,IF(ISNUMBER(SEARCH(SETTINGS!$K$7,D41)),SETTINGS!$L$7,IF(ISNUMBER(SEARCH(SETTINGS!$K$8,D41)),SETTINGS!$L$8,IF(ISNUMBER(SEARCH(SETTINGS!$K$9,D41)),SETTINGS!$L$9,IF(ISNUMBER(SEARCH(SETTINGS!$K$10,D41)),SETTINGS!$L$10,IF(ISNUMBER(SEARCH(SETTINGS!$K$11,D41)),SETTINGS!$L$11,IF(ISNUMBER(SEARCH(SETTINGS!$K$12,D41)),SETTINGS!$L$12,IF(ISNUMBER(SEARCH(SETTINGS!$K$13,D41)),SETTINGS!$L$13,IF(ISNUMBER(SEARCH(SETTINGS!$K$14,D41)),SETTINGS!$L$14,IF(ISNUMBER(SEARCH(SETTINGS!$K$15,D41)),SETTINGS!$L$15,IF(ISNUMBER(SEARCH(SETTINGS!$K$16,D41)),SETTINGS!$L$16,IF(ISNUMBER(SEARCH(SETTINGS!$K$17,D41)),SETTINGS!$L$17,IF(ISNUMBER(SEARCH(SETTINGS!$K$18,D41)),SETTINGS!$L$18,"Miscellaneous")))))))))))))))) -> Books & Stationery | I41: =IF(B41="","",IF(G41<>"",G41,H41)) -> Books & Stationery | J41: Stationery | K41: College Store | L41: UPI-linked Bank | M41: Essential | N41: One-Time | O41: Paid | Q41: Self | R41: Not Applicable | S41: College | U41: =IF(B41="","",IF(C41="Income","INC-",IF(C41="Expense","EXP-","TRX-"))&TEXT(YEAR(B41),"0000")&"-"&TEXT(ROW()-7,"0000")) -> EXP-2026-0034 | V41: =IF(B41="","",TEXT(B41,"mmmm")) -> September | W41: =IF(B41="","",MONTH(B41)) -> 9 | X41: =IF(B41="","",YEAR(B41)) -> 2026 | Y41: =IF(B41="","",DAY(B41)) -> 2 | Z41: =IF(B41="","",IF(WEEKDAY(B41,2)>5,"Weekend","Weekday")) -> Weekday | AA41: =IF(B41="","",IF(COUNTIFS($B$8:$B$1007,B41,$E$8:$E$1007,E41,$D$8:$D$1007,D41,$I$8:$I$1007,I41)>1,"Possible Duplicate","OK")) -> OK | AB41: =IF(OR(B41="",C41<>"Expense"),"",IF(E41>IFERROR(AVERAGEIFS($E$8:$E$1007,$I$8:$I$1007,I41,$C$8:$C$1007,"Expense")*SETTINGS!$B$20,0),"Unusually High","Normal")) -> Normal | AC41: Yes | AF41: =IF(A41<>"Yes","No",IF(AND(AC41="Yes",SETTINGS!$B$16="No"),"No","Yes")) -> Yes | AG41: =IF(A41<>"Yes","",IF(OR(B41="",D41="",E41<=0,F41="",I41=""),"Check Required Fields",IF(AA41="Possible Duplicate","Possible Duplicate",IF(E41>SETTINGS!$B$22,"Review Extreme Value","OK")))) -> OK
A42: Yes | B42: 46267 | C42: Expense | D42: Gym membership | E42: 700 | F42: UPI | G42: Health & Fitness | H42: =IF(D42="","",IF(ISNUMBER(SEARCH(SETTINGS!$K$4,D42)),SETTINGS!$L$4,IF(ISNUMBER(SEARCH(SETTINGS!$K$5,D42)),SETTINGS!$L$5,IF(ISNUMBER(SEARCH(SETTINGS!$K$6,D42)),SETTINGS!$L$6,IF(ISNUMBER(SEARCH(SETTINGS!$K$7,D42)),SETTINGS!$L$7,IF(ISNUMBER(SEARCH(SETTINGS!$K$8,D42)),SETTINGS!$L$8,IF(ISNUMBER(SEARCH(SETTINGS!$K$9,D42)),SETTINGS!$L$9,IF(ISNUMBER(SEARCH(SETTINGS!$K$10,D42)),SETTINGS!$L$10,IF(ISNUMBER(SEARCH(SETTINGS!$K$11,D42)),SETTINGS!$L$11,IF(ISNUMBER(SEARCH(SETTINGS!$K$12,D42)),SETTINGS!$L$12,IF(ISNUMBER(SEARCH(SETTINGS!$K$13,D42)),SETTINGS!$L$13,IF(ISNUMBER(SEARCH(SETTINGS!$K$14,D42)),SETTINGS!$L$14,IF(ISNUMBER(SEARCH(SETTINGS!$K$15,D42)),SETTINGS!$L$15,IF(ISNUMBER(SEARCH(SETTINGS!$K$16,D42)),SETTINGS!$L$16,IF(ISNUMBER(SEARCH(SETTINGS!$K$17,D42)),SETTINGS!$L$17,IF(ISNUMBER(SEARCH(SETTINGS!$K$18,D42)),SETTINGS!$L$18,"Miscellaneous")))))))))))))))) -> Health & Fitness | I42: =IF(B42="","",IF(G42<>"",G42,H42)) -> Health & Fitness | J42: Gym | K42: Campus Gym | L42: UPI-linked Bank | M42: Useful | N42: Recurring | O42: Paid | Q42: Self | R42: Not Applicable | U42: =IF(B42="","",IF(C42="Income","INC-",IF(C42="Expense","EXP-","TRX-"))&TEXT(YEAR(B42),"0000")&"-"&TEXT(ROW()-7,"0000")) -> EXP-2026-0035 | V42: =IF(B42="","",TEXT(B42,"mmmm")) -> September | W42: =IF(B42="","",MONTH(B42)) -> 9 | X42: =IF(B42="","",YEAR(B42)) -> 2026 | Y42: =IF(B42="","",DAY(B42)) -> 2 | Z42: =IF(B42="","",IF(WEEKDAY(B42,2)>5,"Weekend","Weekday")) -> Weekday | AA42: =IF(B42="","",IF(COUNTIFS($B$8:$B$1007,B42,$E$8:$E$1007,E42,$D$8:$D$1007,D42,$I$8:$I$1007,I42)>1,"Possible Duplicate","OK")) -> OK | AB42: =IF(OR(B42="",C42<>"Expense"),"",IF(E42>IFERROR(AVERAGEIFS($E$8:$E$1007,$I$8:$I$1007,I42,$C$8:$C$1007,"Expense")*SETTINGS!$B$20,0),"Unusually High","Normal")) -> Normal | AC42: Yes | AF42: =IF(A42<>"Yes","No",IF(AND(AC42="Yes",SETTINGS!$B$16="No"),"No","Yes")) -> Yes | AG42: =IF(A42<>"Yes","",IF(OR(B42="",D42="",E42<=0,F42="",I42=""),"Check Required Fields",IF(AA42="Possible Duplicate","Possible Duplicate",IF(E42>SETTINGS!$B$22,"Review Extreme Value","OK")))) -> OK
A43: Yes | B43: 46267 | C43: Savings Transfer | D43: Monthly savings contribution | E43: 2500 | F43: Bank Transfer | G43: Savings | H43: =IF(D43="","",IF(ISNUMBER(SEARCH(SETTINGS!$K$4,D43)),SETTINGS!$L$4,IF(ISNUMBER(SEARCH(SETTINGS!$K$5,D43)),SETTINGS!$L$5,IF(ISNUMBER(SEARCH(SETTINGS!$K$6,D43)),SETTINGS!$L$6,IF(ISNUMBER(SEARCH(SETTINGS!$K$7,D43)),SETTINGS!$L$7,IF(ISNUMBER(SEARCH(SETTINGS!$K$8,D43)),SETTINGS!$L$8,IF(ISNUMBER(SEARCH(SETTINGS!$K$9,D43)),SETTINGS!$L$9,IF(ISNUMBER(SEARCH(SETTINGS!$K$10,D43)),SETTINGS!$L$10,IF(ISNUMBER(SEARCH(SETTINGS!$K$11,D43)),SETTINGS!$L$11,IF(ISNUMBER(SEARCH(SETTINGS!$K$12,D43)),SETTINGS!$L$12,IF(ISNUMBER(SEARCH(SETTINGS!$K$13,D43)),SETTINGS!$L$13,IF(ISNUMBER(SEARCH(SETTINGS!$K$14,D43)),SETTINGS!$L$14,IF(ISNUMBER(SEARCH(SETTINGS!$K$15,D43)),SETTINGS!$L$15,IF(ISNUMBER(SEARCH(SETTINGS!$K$16,D43)),SETTINGS!$L$16,IF(ISNUMBER(SEARCH(SETTINGS!$K$17,D43)),SETTINGS!$L$17,IF(ISNUMBER(SEARCH(SETTINGS!$K$18,D43)),SETTINGS!$L$18,"Miscellaneous")))))))))))))))) -> Miscellaneous | I43: =IF(B43="","",IF(G43<>"",G43,H43)) -> Savings | J43: Emergency Fund | L43: Savings Account | M43: Essential | N43: One-Time | O43: Paid | Q43: Self | R43: Not Applicable | S43: Emergency | U43: =IF(B43="","",IF(C43="Income","INC-",IF(C43="Expense","EXP-","TRX-"))&TEXT(YEAR(B43),"0000")&"-"&TEXT(ROW()-7,"0000")) -> TRX-2026-0036 | V43: =IF(B43="","",TEXT(B43,"mmmm")) -> September | W43: =IF(B43="","",MONTH(B43)) -> 9 | X43: =IF(B43="","",YEAR(B43)) -> 2026 | Y43: =IF(B43="","",DAY(B43)) -> 2 | Z43: =IF(B43="","",IF(WEEKDAY(B43,2)>5,"Weekend","Weekday")) -> Weekday | AA43: =IF(B43="","",IF(COUNTIFS($B$8:$B$1007,B43,$E$8:$E$1007,E43,$D$8:$D$1007,D43,$I$8:$I$1007,I43)>1,"Possible Duplicate","OK")) -> OK | AB43: =IF(OR(B43="",C43<>"Expense"),"",IF(E43>IFERROR(AVERAGEIFS($E$8:$E$1007,$I$8:$I$1007,I43,$C$8:$C$1007,"Expense")*SETTINGS!$B$20,0),"Unusually High","Normal")) | AC43: Yes | AF43: =IF(A43<>"Yes","No",IF(AND(AC43="Yes",SETTINGS!$B$16="No"),"No","Yes")) -> Yes | AG43: =IF(A43<>"Yes","",IF(OR(B43="",D43="",E43<=0,F43="",I43=""),"Check Required Fields",IF(AA43="Possible Duplicate","Possible Duplicate",IF(E43>SETTINGS!$B$22,"Review Extreme Value","OK")))) -> OK
H44: =IF(D44="","",IF(ISNUMBER(SEARCH(SETTINGS!$K$4,D44)),SETTINGS!$L$4,IF(ISNUMBER(SEARCH(SETTINGS!$K$5,D44)),SETTINGS!$L$5,IF(ISNUMBER(SEARCH(SETTINGS!$K$6,D44)),SETTINGS!$L$6,IF(ISNUMBER(SEARCH(SETTINGS!$K$7,D44)),SETTINGS!$L$7,IF(ISNUMBER(SEARCH(SETTINGS!$K$8,D44)),SETTINGS!$L$8,IF(ISNUMBER(SEARCH(SETTINGS!$K$9,D44)),SETTINGS!$L$9,IF(ISNUMBER(SEARCH(SETTINGS!$K$10,D44)),SETTINGS!$L$10,IF(ISNUMBER(SEARCH(SETTINGS!$K$11,D44)),SETTINGS!$L$11,IF(ISNUMBER(SEARCH(SETTINGS!$K$12,D44)),SETTINGS!$L$12,IF(ISNUMBER(SEARCH(SETTINGS!$K$13,D44)),SETTINGS!$L$13,IF(ISNUMBER(SEARCH(SETTINGS!$K$14,D44)),SETTINGS!$L$14,IF(ISNUMBER(SEARCH(SETTINGS!$K$15,D44)),SETTINGS!$L$15,IF(ISNUMBER(SEARCH(SETTINGS!$K$16,D44)),SETTINGS!$L$16,IF(ISNUMBER(SEARCH(SETTINGS!$K$17,D44)),SETTINGS!$L$17,IF(ISNUMBER(SEARCH(SETTINGS!$K$18,D44)),SETTINGS!$L$18,"Miscellaneous")))))))))))))))) | I44: =IF(B44="","",IF(G44<>"",G44,H44)) | U44: =IF(B44="","",IF(C44="Income","INC-",IF(C44="Expense","EXP-","TRX-"))&TEXT(YEAR(B44),"0000")&"-"&TEXT(ROW()-7,"0000")) | V44: =IF(B44="","",TEXT(B44,"mmmm")) | W44: =IF(B44="","",MONTH(B44)) | X44: =IF(B44="","",YEAR(B44)) | Y44: =IF(B44="","",DAY(B44)) | Z44: =IF(B44="","",IF(WEEKDAY(B44,2)>5,"Weekend","Weekday")) | AA44: =IF(B44="","",IF(COUNTIFS($B$8:$B$1007,B44,$E$8:$E$1007,E44,$D$8:$D$1007,D44,$I$8:$I$1007,I44)>1,"Possible Duplicate","OK")) | AB44: =IF(OR(B44="",C44<>"Expense"),"",IF(E44>IFERROR(AVERAGEIFS($E$8:$E$1007,$I$8:$I$1007,I44,$C$8:$C$1007,"Expense")*SETTINGS!$B$20,0),"Unusually High","Normal")) | AF44: =IF(A44<>"Yes","No",IF(AND(AC44="Yes",SETTINGS!$B$16="No"),"No","Yes")) -> No | AG44: =IF(A44<>"Yes","",IF(OR(B44="",D44="",E44<=0,F44="",I44=""),"Check Required Fields",IF(AA44="Possible Duplicate","Possible Duplicate",IF(E44>SETTINGS!$B$22,"Review Extreme Value","OK"))))
H45: =IF(D45="","",IF(ISNUMBER(SEARCH(SETTINGS!$K$4,D45)),SETTINGS!$L$4,IF(ISNUMBER(SEARCH(SETTINGS!$K$5,D45)),SETTINGS!$L$5,IF(ISNUMBER(SEARCH(SETTINGS!$K$6,D45)),SETTINGS!$L$6,IF(ISNUMBER(SEARCH(SETTINGS!$K$7,D45)),SETTINGS!$L$7,IF(ISNUMBER(SEARCH(SETTINGS!$K$8,D45)),SETTINGS!$L$8,IF(ISNUMBER(SEARCH(SETTINGS!$K$9,D45)),SETTINGS!$L$9,IF(ISNUMBER(SEARCH(SETTINGS!$K$10,D45)),SETTINGS!$L$10,IF(ISNUMBER(SEARCH(SETTINGS!$K$11,D45)),SETTINGS!$L$11,IF(ISNUMBER(SEARCH(SETTINGS!$K$12,D45)),SETTINGS!$L$12,IF(ISNUMBER(SEARCH(SETTINGS!$K$13,D45)),SETTINGS!$L$13,IF(ISNUMBER(SEARCH(SETTINGS!$K$14,D45)),SETTINGS!$L$14,IF(ISNUMBER(SEARCH(SETTINGS!$K$15,D45)),SETTINGS!$L$15,IF(ISNUMBER(SEARCH(SETTINGS!$K$16,D45)),SETTINGS!$L$16,IF(ISNUMBER(SEARCH(SETTINGS!$K$17,D45)),SETTINGS!$L$17,IF(ISNUMBER(SEARCH(SETTINGS!$K$18,D45)),SETTINGS!$L$18,"Miscellaneous")))))))))))))))) | I45: =IF(B45="","",IF(G45<>"",G45,H45)) | U45: =IF(B45="","",IF(C45="Income","INC-",IF(C45="Expense","EXP-","TRX-"))&TEXT(YEAR(B45),"0000")&"-"&TEXT(ROW()-7,"0000")) | V45: =IF(B45="","",TEXT(B45,"mmmm")) | W45: =IF(B45="","",MONTH(B45)) | X45: =IF(B45="","",YEAR(B45)) | Y45: =IF(B45="","",DAY(B45)) | Z45: =IF(B45="","",IF(WEEKDAY(B45,2)>5,"Weekend","Weekday")) | AA45: =IF(B45="","",IF(COUNTIFS($B$8:$B$1007,B45,$E$8:$E$1007,E45,$D$8:$D$1007,D45,$I$8:$I$1007,I45)>1,"Possible Duplicate","OK")) | AB45: =IF(OR(B45="",C45<>"Expense"),"",IF(E45>IFERROR(AVERAGEIFS($E$8:$E$1007,$I$8:$I$1007,I45,$C$8:$C$1007,"Expense")*SETTINGS!$B$20,0),"Unusually High","Normal")) | AF45: =IF(A45<>"Yes","No",IF(AND(AC45="Yes",SETTINGS!$B$16="No"),"No","Yes")) -> No | AG45: =IF(A45<>"Yes","",IF(OR(B45="",D45="",E45<=0,F45="",I45=""),"Check Required Fields",IF(AA45="Possible Duplicate","Possible Duplicate",IF(E45>SETTINGS!$B$22,"Review Extreme Value","OK"))))
H46: =IF(D46="","",IF(ISNUMBER(SEARCH(SETTINGS!$K$4,D46)),SETTINGS!$L$4,IF(ISNUMBER(SEARCH(SETTINGS!$K$5,D46)),SETTINGS!$L$5,IF(ISNUMBER(SEARCH(SETTINGS!$K$6,D46)),SETTINGS!$L$6,IF(ISNUMBER(SEARCH(SETTINGS!$K$7,D46)),SETTINGS!$L$7,IF(ISNUMBER(SEARCH(SETTINGS!$K$8,D46)),SETTINGS!$L$8,IF(ISNUMBER(SEARCH(SETTINGS!$K$9,D46)),SETTINGS!$L$9,IF(ISNUMBER(SEARCH(SETTINGS!$K$10,D46)),SETTINGS!$L$10,IF(ISNUMBER(SEARCH(SETTINGS!$K$11,D46)),SETTINGS!$L$11,IF(ISNUMBER(SEARCH(SETTINGS!$K$12,D46)),SETTINGS!$L$12,IF(ISNUMBER(SEARCH(SETTINGS!$K$13,D46)),SETTINGS!$L$13,IF(ISNUMBER(SEARCH(SETTINGS!$K$14,D46)),SETTINGS!$L$14,IF(ISNUMBER(SEARCH(SETTINGS!$K$15,D46)),SETTINGS!$L$15,IF(ISNUMBER(SEARCH(SETTINGS!$K$16,D46)),SETTINGS!$L$16,IF(ISNUMBER(SEARCH(SETTINGS!$K$17,D46)),SETTINGS!$L$17,IF(ISNUMBER(SEARCH(SETTINGS!$K$18,D46)),SETTINGS!$L$18,"Miscellaneous")))))))))))))))) | I46: =IF(B46="","",IF(G46<>"",G46,H46)) | U46: =IF(B46="","",IF(C46="Income","INC-",IF(C46="Expense","EXP-","TRX-"))&TEXT(YEAR(B46),"0000")&"-"&TEXT(ROW()-7,"0000")) | V46: =IF(B46="","",TEXT(B46,"mmmm")) | W46: =IF(B46="","",MONTH(B46)) | X46: =IF(B46="","",YEAR(B46)) | Y46: =IF(B46="","",DAY(B46)) | Z46: =IF(B46="","",IF(WEEKDAY(B46,2)>5,"Weekend","Weekday")) | AA46: =IF(B46="","",IF(COUNTIFS($B$8:$B$1007,B46,$E$8:$E$1007,E46,$D$8:$D$1007,D46,$I$8:$I$1007,I46)>1,"Possible Duplicate","OK")) | AB46: =IF(OR(B46="",C46<>"Expense"),"",IF(E46>IFERROR(AVERAGEIFS($E$8:$E$1007,$I$8:$I$1007,I46,$C$8:$C$1007,"Expense")*SETTINGS!$B$20,0),"Unusually High","Normal")) | AF46: =IF(A46<>"Yes","No",IF(AND(AC46="Yes",SETTINGS!$B$16="No"),"No","Yes")) -> No | AG46: =IF(A46<>"Yes","",IF(OR(B46="",D46="",E46<=0,F46="",I46=""),"Check Required Fields",IF(AA46="Possible Duplicate","Possible Duplicate",IF(E46>SETTINGS!$B$22,"Review Extreme Value","OK"))))
H47: =IF(D47="","",IF(ISNUMBER(SEARCH(SETTINGS!$K$4,D47)),SETTINGS!$L$4,IF(ISNUMBER(SEARCH(SETTINGS!$K$5,D47)),SETTINGS!$L$5,IF(ISNUMBER(SEARCH(SETTINGS!$K$6,D47)),SETTINGS!$L$6,IF(ISNUMBER(SEARCH(SETTINGS!$K$7,D47)),SETTINGS!$L$7,IF(ISNUMBER(SEARCH(SETTINGS!$K$8,D47)),SETTINGS!$L$8,IF(ISNUMBER(SEARCH(SETTINGS!$K$9,D47)),SETTINGS!$L$9,IF(ISNUMBER(SEARCH(SETTINGS!$K$10,D47)),SETTINGS!$L$10,IF(ISNUMBER(SEARCH(SETTINGS!$K$11,D47)),SETTINGS!$L$11,IF(ISNUMBER(SEARCH(SETTINGS!$K$12,D47)),SETTINGS!$L$12,IF(ISNUMBER(SEARCH(SETTINGS!$K$13,D47)),SETTINGS!$L$13,IF(ISNUMBER(SEARCH(SETTINGS!$K$14,D47)),SETTINGS!$L$14,IF(ISNUMBER(SEARCH(SETTINGS!$K$15,D47)),SETTINGS!$L$15,IF(ISNUMBER(SEARCH(SETTINGS!$K$16,D47)),SETTINGS!$L$16,IF(ISNUMBER(SEARCH(SETTINGS!$K$17,D47)),SETTINGS!$L$17,IF(ISNUMBER(SEARCH(SETTINGS!$K$18,D47)),SETTINGS!$L$18,"Miscellaneous")))))))))))))))) | I47: =IF(B47="","",IF(G47<>"",G47,H47)) | U47: =IF(B47="","",IF(C47="Income","INC-",IF(C47="Expense","EXP-","TRX-"))&TEXT(YEAR(B47),"0000")&"-"&TEXT(ROW()-7,"0000")) | V47: =IF(B47="","",TEXT(B47,"mmmm")) | W47: =IF(B47="","",MONTH(B47)) | X47: =IF(B47="","",YEAR(B47)) | Y47: =IF(B47="","",DAY(B47)) | Z47: =IF(B47="","",IF(WEEKDAY(B47,2)>5,"Weekend","Weekday")) | AA47: =IF(B47="","",IF(COUNTIFS($B$8:$B$1007,B47,$E$8:$E$1007,E47,$D$8:$D$1007,D47,$I$8:$I$1007,I47)>1,"Possible Duplicate","OK")) | AB47: =IF(OR(B47="",C47<>"Expense"),"",IF(E47>IFERROR(AVERAGEIFS($E$8:$E$1007,$I$8:$I$1007,I47,$C$8:$C$1007,"Expense")*SETTINGS!$B$20,0),"Unusually High","Normal")) | AF47: =IF(A47<>"Yes","No",IF(AND(AC47="Yes",SETTINGS!$B$16="No"),"No","Yes")) -> No | AG47: =IF(A47<>"Yes","",IF(OR(B47="",D47="",E47<=0,F47="",I47=""),"Check Required Fields",IF(AA47="Possible Duplicate","Possible Duplicate",IF(E47>SETTINGS!$B$22,"Review Extreme Value","OK"))))
H48: =IF(D48="","",IF(ISNUMBER(SEARCH(SETTINGS!$K$4,D48)),SETTINGS!$L$4,IF(ISNUMBER(SEARCH(SETTINGS!$K$5,D48)),SETTINGS!$L$5,IF(ISNUMBER(SEARCH(SETTINGS!$K$6,D48)),SETTINGS!$L$6,IF(ISNUMBER(SEARCH(SETTINGS!$K$7,D48)),SETTINGS!$L$7,IF(ISNUMBER(SEARCH(SETTINGS!$K$8,D48)),SETTINGS!$L$8,IF(ISNUMBER(SEARCH(SETTINGS!$K$9,D48)),SETTINGS!$L$9,IF(ISNUMBER(SEARCH(SETTINGS!$K$10,D48)),SETTINGS!$L$10,IF(ISNUMBER(SEARCH(SETTINGS!$K$11,D48)),SETTINGS!$L$11,IF(ISNUMBER(SEARCH(SETTINGS!$K$12,D48)),SETTINGS!$L$12,IF(ISNUMBER(SEARCH(SETTINGS!$K$13,D48)),SETTINGS!$L$13,IF(ISNUMBER(SEARCH(SETTINGS!$K$14,D48)),SETTINGS!$L$14,IF(ISNUMBER(SEARCH(SETTINGS!$K$15,D48)),SETTINGS!$L$15,IF(ISNUMBER(SEARCH(SETTINGS!$K$16,D48)),SETTINGS!$L$16,IF(ISNUMBER(SEARCH(SETTINGS!$K$17,D48)),SETTINGS!$L$17,IF(ISNUMBER(SEARCH(SETTINGS!$K$18,D48)),SETTINGS!$L$18,"Miscellaneous")))))))))))))))) | I48: =IF(B48="","",IF(G48<>"",G48,H48)) | U48: =IF(B48="","",IF(C48="Income","INC-",IF(C48="Expense","EXP-","TRX-"))&TEXT(YEAR(B48),"0000")&"-"&TEXT(ROW()-7,"0000")) | V48: =IF(B48="","",TEXT(B48,"mmmm")) | W48: =IF(B48="","",MONTH(B48)) | X48: =IF(B48="","",YEAR(B48)) | Y48: =IF(B48="","",DAY(B48)) | Z48: =IF(B48="","",IF(WEEKDAY(B48,2)>5,"Weekend","Weekday")) | AA48: =IF(B48="","",IF(COUNTIFS($B$8:$B$1007,B48,$E$8:$E$1007,E48,$D$8:$D$1007,D48,$I$8:$I$1007,I48)>1,"Possible Duplicate","OK")) | AB48: =IF(OR(B48="",C48<>"Expense"),"",IF(E48>IFERROR(AVERAGEIFS($E$8:$E$1007,$I$8:$I$1007,I48,$C$8:$C$1007,"Expense")*SETTINGS!$B$20,0),"Unusually High","Normal")) | AF48: =IF(A48<>"Yes","No",IF(AND(AC48="Yes",SETTINGS!$B$16="No"),"No","Yes")) -> No | AG48: =IF(A48<>"Yes","",IF(OR(B48="",D48="",E48<=0,F48="",I48=""),"Check Required Fields",IF(AA48="Possible Duplicate","Possible Duplicate",IF(E48>SETTINGS!$B$22,"Review Extreme Value","OK"))))
H49: =IF(D49="","",IF(ISNUMBER(SEARCH(SETTINGS!$K$4,D49)),SETTINGS!$L$4,IF(ISNUMBER(SEARCH(SETTINGS!$K$5,D49)),SETTINGS!$L$5,IF(ISNUMBER(SEARCH(SETTINGS!$K$6,D49)),SETTINGS!$L$6,IF(ISNUMBER(SEARCH(SETTINGS!$K$7,D49)),SETTINGS!$L$7,IF(ISNUMBER(SEARCH(SETTINGS!$K$8,D49)),SETTINGS!$L$8,IF(ISNUMBER(SEARCH(SETTINGS!$K$9,D49)),SETTINGS!$L$9,IF(ISNUMBER(SEARCH(SETTINGS!$K$10,D49)),SETTINGS!$L$10,IF(ISNUMBER(SEARCH(SETTINGS!$K$11,D49)),SETTINGS!$L$11,IF(ISNUMBER(SEARCH(SETTINGS!$K$12,D49)),SETTINGS!$L$12,IF(ISNUMBER(SEARCH(SETTINGS!$K$13,D49)),SETTINGS!$L$13,IF(ISNUMBER(SEARCH(SETTINGS!$K$14,D49)),SETTINGS!$L$14,IF(ISNUMBER(SEARCH(SETTINGS!$K$15,D49)),SETTINGS!$L$15,IF(ISNUMBER(SEARCH(SETTINGS!$K$16,D49)),SETTINGS!$L$16,IF(ISNUMBER(SEARCH(SETTINGS!$K$17,D49)),SETTINGS!$L$17,IF(ISNUMBER(SEARCH(SETTINGS!$K$18,D49)),SETTINGS!$L$18,"Miscellaneous")))))))))))))))) | I49: =IF(B49="","",IF(G49<>"",G49,H49)) | U49: =IF(B49="","",IF(C49="Income","INC-",IF(C49="Expense","EXP-","TRX-"))&TEXT(YEAR(B49),"0000")&"-"&TEXT(ROW()-7,"0000")) | V49: =IF(B49="","",TEXT(B49,"mmmm")) | W49: =IF(B49="","",MONTH(B49)) | X49: =IF(B49="","",YEAR(B49)) | Y49: =IF(B49="","",DAY(B49)) | Z49: =IF(B49="","",IF(WEEKDAY(B49,2)>5,"Weekend","Weekday")) | AA49: =IF(B49="","",IF(COUNTIFS($B$8:$B$1007,B49,$E$8:$E$1007,E49,$D$8:$D$1007,D49,$I$8:$I$1007,I49)>1,"Possible Duplicate","OK")) | AB49: =IF(OR(B49="",C49<>"Expense"),"",IF(E49>IFERROR(AVERAGEIFS($E$8:$E$1007,$I$8:$I$1007,I49,$C$8:$C$1007,"Expense")*SETTINGS!$B$20,0),"Unusually High","Normal")) | AF49: =IF(A49<>"Yes","No",IF(AND(AC49="Yes",SETTINGS!$B$16="No"),"No","Yes")) -> No | AG49: =IF(A49<>"Yes","",IF(OR(B49="",D49="",E49<=0,F49="",I49=""),"Check Required Fields",IF(AA49="Possible Duplicate","Possible Duplicate",IF(E49>SETTINGS!$B$22,"Review Extreme Value","OK"))))
H50: =IF(D50="","",IF(ISNUMBER(SEARCH(SETTINGS!$K$4,D50)),SETTINGS!$L$4,IF(ISNUMBER(SEARCH(SETTINGS!$K$5,D50)),SETTINGS!$L$5,IF(ISNUMBER(SEARCH(SETTINGS!$K$6,D50)),SETTINGS!$L$6,IF(ISNUMBER(SEARCH(SETTINGS!$K$7,D50)),SETTINGS!$L$7,IF(ISNUMBER(SEARCH(SETTINGS!$K$8,D50)),SETTINGS!$L$8,IF(ISNUMBER(SEARCH(SETTINGS!$K$9,D50)),SETTINGS!$L$9,IF(ISNUMBER(SEARCH(SETTINGS!$K$10,D50)),SETTINGS!$L$10,IF(ISNUMBER(SEARCH(SETTINGS!$K$11,D50)),SETTINGS!$L$11,IF(ISNUMBER(SEARCH(SETTINGS!$K$12,D50)),SETTINGS!$L$12,IF(ISNUMBER(SEARCH(SETTINGS!$K$13,D50)),SETTINGS!$L$13,IF(ISNUMBER(SEARCH(SETTINGS!$K$14,D50)),SETTINGS!$L$14,IF(ISNUMBER(SEARCH(SETTINGS!$K$15,D50)),SETTINGS!$L$15,IF(ISNUMBER(SEARCH(SETTINGS!$K$16,D50)),SETTINGS!$L$16,IF(ISNUMBER(SEARCH(SETTINGS!$K$17,D50)),SETTINGS!$L$17,IF(ISNUMBER(SEARCH(SETTINGS!$K$18,D50)),SETTINGS!$L$18,"Miscellaneous")))))))))))))))) | I50: =IF(B50="","",IF(G50<>"",G50,H50)) | U50: =IF(B50="","",IF(C50="Income","INC-",IF(C50="Expense","EXP-","TRX-"))&TEXT(YEAR(B50),"0000")&"-"&TEXT(ROW()-7,"0000")) | V50: =IF(B50="","",TEXT(B50,"mmmm")) | W50: =IF(B50="","",MONTH(B50)) | X50: =IF(B50="","",YEAR(B50)) | Y50: =IF(B50="","",DAY(B50)) | Z50: =IF(B50="","",IF(WEEKDAY(B50,2)>5,"Weekend","Weekday")) | AA50: =IF(B50="","",IF(COUNTIFS($B$8:$B$1007,B50,$E$8:$E$1007,E50,$D$8:$D$1007,D50,$I$8:$I$1007,I50)>1,"Possible Duplicate","OK")) | AB50: =IF(OR(B50="",C50<>"Expense"),"",IF(E50>IFERROR(AVERAGEIFS($E$8:$E$1007,$I$8:$I$1007,I50,$C$8:$C$1007,"Expense")*SETTINGS!$B$20,0),"Unusually High","Normal")) | AF50: =IF(A50<>"Yes","No",IF(AND(AC50="Yes",SETTINGS!$B$16="No"),"No","Yes")) -> No | AG50: =IF(A50<>"Yes","",IF(OR(B50="",D50="",E50<=0,F50="",I50=""),"Check Required Fields",IF(AA50="Possible Duplicate","Possible Duplicate",IF(E50>SETTINGS!$B$22,"Review Extreme Value","OK"))))
H51: =IF(D51="","",IF(ISNUMBER(SEARCH(SETTINGS!$K$4,D51)),SETTINGS!$L$4,IF(ISNUMBER(SEARCH(SETTINGS!$K$5,D51)),SETTINGS!$L$5,IF(ISNUMBER(SEARCH(SETTINGS!$K$6,D51)),SETTINGS!$L$6,IF(ISNUMBER(SEARCH(SETTINGS!$K$7,D51)),SETTINGS!$L$7,IF(ISNUMBER(SEARCH(SETTINGS!$K$8,D51)),SETTINGS!$L$8,IF(ISNUMBER(SEARCH(SETTINGS!$K$9,D51)),SETTINGS!$L$9,IF(ISNUMBER(SEARCH(SETTINGS!$K$10,D51)),SETTINGS!$L$10,IF(ISNUMBER(SEARCH(SETTINGS!$K$11,D51)),SETTINGS!$L$11,IF(ISNUMBER(SEARCH(SETTINGS!$K$12,D51)),SETTINGS!$L$12,IF(ISNUMBER(SEARCH(SETTINGS!$K$13,D51)),SETTINGS!$L$13,IF(ISNUMBER(SEARCH(SETTINGS!$K$14,D51)),SETTINGS!$L$14,IF(ISNUMBER(SEARCH(SETTINGS!$K$15,D51)),SETTINGS!$L$15,IF(ISNUMBER(SEARCH(SETTINGS!$K$16,D51)),SETTINGS!$L$16,IF(ISNUMBER(SEARCH(SETTINGS!$K$17,D51)),SETTINGS!$L$17,IF(ISNUMBER(SEARCH(SETTINGS!$K$18,D51)),SETTINGS!$L$18,"Miscellaneous")))))))))))))))) | I51: =IF(B51="","",IF(G51<>"",G51,H51)) | U51: =IF(B51="","",IF(C51="Income","INC-",IF(C51="Expense","EXP-","TRX-"))&TEXT(YEAR(B51),"0000")&"-"&TEXT(ROW()-7,"0000")) | V51: =IF(B51="","",TEXT(B51,"mmmm")) | W51: =IF(B51="","",MONTH(B51)) | X51: =IF(B51="","",YEAR(B51)) | Y51: =IF(B51="","",DAY(B51)) | Z51: =IF(B51="","",IF(WEEKDAY(B51,2)>5,"Weekend","Weekday")) | AA51: =IF(B51="","",IF(COUNTIFS($B$8:$B$1007,B51,$E$8:$E$1007,E51,$D$8:$D$1007,D51,$I$8:$I$1007,I51)>1,"Possible Duplicate","OK")) | AB51: =IF(OR(B51="",C51<>"Expense"),"",IF(E51>IFERROR(AVERAGEIFS($E$8:$E$1007,$I$8:$I$1007,I51,$C$8:$C$1007,"Expense")*SETTINGS!$B$20,0),"Unusually High","Normal")) | AF51: =IF(A51<>"Yes","No",IF(AND(AC51="Yes",SETTINGS!$B$16="No"),"No","Yes")) -> No | AG51: =IF(A51<>"Yes","",IF(OR(B51="",D51="",E51<=0,F51="",I51=""),"Check Required Fields",IF(AA51="Possible Duplicate","Possible Duplicate",IF(E51>SETTINGS!$B$22,"Review Extreme Value","OK"))))
H52: =IF(D52="","",IF(ISNUMBER(SEARCH(SETTINGS!$K$4,D52)),SETTINGS!$L$4,IF(ISNUMBER(SEARCH(SETTINGS!$K$5,D52)),SETTINGS!$L$5,IF(ISNUMBER(SEARCH(SETTINGS!$K$6,D52)),SETTINGS!$L$6,IF(ISNUMBER(SEARCH(SETTINGS!$K$7,D52)),SETTINGS!$L$7,IF(ISNUMBER(SEARCH(SETTINGS!$K$8,D52)),SETTINGS!$L$8,IF(ISNUMBER(SEARCH(SETTINGS!$K$9,D52)),SETTINGS!$L$9,IF(ISNUMBER(SEARCH(SETTINGS!$K$10,D52)),SETTINGS!$L$10,IF(ISNUMBER(SEARCH(SETTINGS!$K$11,D52)),SETTINGS!$L$11,IF(ISNUMBER(SEARCH(SETTINGS!$K$12,D52)),SETTINGS!$L$12,IF(ISNUMBER(SEARCH(SETTINGS!$K$13,D52)),SETTINGS!$L$13,IF(ISNUMBER(SEARCH(SETTINGS!$K$14,D52)),SETTINGS!$L$14,IF(ISNUMBER(SEARCH(SETTINGS!$K$15,D52)),SETTINGS!$L$15,IF(ISNUMBER(SEARCH(SETTINGS!$K$16,D52)),SETTINGS!$L$16,IF(ISNUMBER(SEARCH(SETTINGS!$K$17,D52)),SETTINGS!$L$17,IF(ISNUMBER(SEARCH(SETTINGS!$K$18,D52)),SETTINGS!$L$18,"Miscellaneous")))))))))))))))) | I52: =IF(B52="","",IF(G52<>"",G52,H52)) | U52: =IF(B52="","",IF(C52="Income","INC-",IF(C52="Expense","EXP-","TRX-"))&TEXT(YEAR(B52),"0000")&"-"&TEXT(ROW()-7,"0000")) | V52: =IF(B52="","",TEXT(B52,"mmmm")) | W52: =IF(B52="","",MONTH(B52)) | X52: =IF(B52="","",YEAR(B52)) | Y52: =IF(B52="","",DAY(B52)) | Z52: =IF(B52="","",IF(WEEKDAY(B52,2)>5,"Weekend","Weekday")) | AA52: =IF(B52="","",IF(COUNTIFS($B$8:$B$1007,B52,$E$8:$E$1007,E52,$D$8:$D$1007,D52,$I$8:$I$1007,I52)>1,"Possible Duplicate","OK")) | AB52: =IF(OR(B52="",C52<>"Expense"),"",IF(E52>IFERROR(AVERAGEIFS($E$8:$E$1007,$I$8:$I$1007,I52,$C$8:$C$1007,"Expense")*SETTINGS!$B$20,0),"Unusually High","Normal")) | AF52: =IF(A52<>"Yes","No",IF(AND(AC52="Yes",SETTINGS!$B$16="No"),"No","Yes")) -> No | AG52: =IF(A52<>"Yes","",IF(OR(B52="",D52="",E52<=0,F52="",I52=""),"Check Required Fields",IF(AA52="Possible Duplicate","Possible Duplicate",IF(E52>SETTINGS!$B$22,"Review Extreme Value","OK"))))
H53: =IF(D53="","",IF(ISNUMBER(SEARCH(SETTINGS!$K$4,D53)),SETTINGS!$L$4,IF(ISNUMBER(SEARCH(SETTINGS!$K$5,D53)),SETTINGS!$L$5,IF(ISNUMBER(SEARCH(SETTINGS!$K$6,D53)),SETTINGS!$L$6,IF(ISNUMBER(SEARCH(SETTINGS!$K$7,D53)),SETTINGS!$L$7,IF(ISNUMBER(SEARCH(SETTINGS!$K$8,D53)),SETTINGS!$L$8,IF(ISNUMBER(SEARCH(SETTINGS!$K$9,D53)),SETTINGS!$L$9,IF(ISNUMBER(SEARCH(SETTINGS!$K$10,D53)),SETTINGS!$L$10,IF(ISNUMBER(SEARCH(SETTINGS!$K$11,D53)),SETTINGS!$L$11,IF(ISNUMBER(SEARCH(SETTINGS!$K$12,D53)),SETTINGS!$L$12,IF(ISNUMBER(SEARCH(SETTINGS!$K$13,D53)),SETTINGS!$L$13,IF(ISNUMBER(SEARCH(SETTINGS!$K$14,D53)),SETTINGS!$L$14,IF(ISNUMBER(SEARCH(SETTINGS!$K$15,D53)),SETTINGS!$L$15,IF(ISNUMBER(SEARCH(SETTINGS!$K$16,D53)),SETTINGS!$L$16,IF(ISNUMBER(SEARCH(SETTINGS!$K$17,D53)),SETTINGS!$L$17,IF(ISNUMBER(SEARCH(SETTINGS!$K$18,D53)),SETTINGS!$L$18,"Miscellaneous")))))))))))))))) | I53: =IF(B53="","",IF(G53<>"",G53,H53)) | U53: =IF(B53="","",IF(C53="Income","INC-",IF(C53="Expense","EXP-","TRX-"))&TEXT(YEAR(B53),"0000")&"-"&TEXT(ROW()-7,"0000")) | V53: =IF(B53="","",TEXT(B53,"mmmm")) | W53: =IF(B53="","",MONTH(B53)) | X53: =IF(B53="","",YEAR(B53)) | Y53: =IF(B53="","",DAY(B53)) | Z53: =IF(B53="","",IF(WEEKDAY(B53,2)>5,"Weekend","Weekday")) | AA53: =IF(B53="","",IF(COUNTIFS($B$8:$B$1007,B53,$E$8:$E$1007,E53,$D$8:$D$1007,D53,$I$8:$I$1007,I53)>1,"Possible Duplicate","OK")) | AB53: =IF(OR(B53="",C53<>"Expense"),"",IF(E53>IFERROR(AVERAGEIFS($E$8:$E$1007,$I$8:$I$1007,I53,$C$8:$C$1007,"Expense")*SETTINGS!$B$20,0),"Unusually High","Normal")) | AF53: =IF(A53<>"Yes","No",IF(AND(AC53="Yes",SETTINGS!$B$16="No"),"No","Yes")) -> No | AG53: =IF(A53<>"Yes","",IF(OR(B53="",D53="",E53<=0,F53="",I53=""),"Check Required Fields",IF(AA53="Possible Duplicate","Possible Duplicate",IF(E53>SETTINGS!$B$22,"Review Extreme Value","OK"))))
H54: =IF(D54="","",IF(ISNUMBER(SEARCH(SETTINGS!$K$4,D54)),SETTINGS!$L$4,IF(ISNUMBER(SEARCH(SETTINGS!$K$5,D54)),SETTINGS!$L$5,IF(ISNUMBER(SEARCH(SETTINGS!$K$6,D54)),SETTINGS!$L$6,IF(ISNUMBER(SEARCH(SETTINGS!$K$7,D54)),SETTINGS!$L$7,IF(ISNUMBER(SEARCH(SETTINGS!$K$8,D54)),SETTINGS!$L$8,IF(ISNUMBER(SEARCH(SETTINGS!$K$9,D54)),SETTINGS!$L$9,IF(ISNUMBER(SEARCH(SETTINGS!$K$10,D54)),SETTINGS!$L$10,IF(ISNUMBER(SEARCH(SETTINGS!$K$11,D54)),SETTINGS!$L$11,IF(ISNUMBER(SEARCH(SETTINGS!$K$12,D54)),SETTINGS!$L$12,IF(ISNUMBER(SEARCH(SETTINGS!$K$13,D54)),SETTINGS!$L$13,IF(ISNUMBER(SEARCH(SETTINGS!$K$14,D54)),SETTINGS!$L$14,IF(ISNUMBER(SEARCH(SETTINGS!$K$15,D54)),SETTINGS!$L$15,IF(ISNUMBER(SEARCH(SETTINGS!$K$16,D54)),SETTINGS!$L$16,IF(ISNUMBER(SEARCH(SETTINGS!$K$17,D54)),SETTINGS!$L$17,IF(ISNUMBER(SEARCH(SETTINGS!$K$18,D54)),SETTINGS!$L$18,"Miscellaneous")))))))))))))))) | I54: =IF(B54="","",IF(G54<>"",G54,H54)) | U54: =IF(B54="","",IF(C54="Income","INC-",IF(C54="Expense","EXP-","TRX-"))&TEXT(YEAR(B54),"0000")&"-"&TEXT(ROW()-7,"0000")) | V54: =IF(B54="","",TEXT(B54,"mmmm")) | W54: =IF(B54="","",MONTH(B54)) | X54: =IF(B54="","",YEAR(B54)) | Y54: =IF(B54="","",DAY(B54)) | Z54: =IF(B54="","",IF(WEEKDAY(B54,2)>5,"Weekend","Weekday")) | AA54: =IF(B54="","",IF(COUNTIFS($B$8:$B$1007,B54,$E$8:$E$1007,E54,$D$8:$D$1007,D54,$I$8:$I$1007,I54)>1,"Possible Duplicate","OK")) | AB54: =IF(OR(B54="",C54<>"Expense"),"",IF(E54>IFERROR(AVERAGEIFS($E$8:$E$1007,$I$8:$I$1007,I54,$C$8:$C$1007,"Expense")*SETTINGS!$B$20,0),"Unusually High","Normal")) | AF54: =IF(A54<>"Yes","No",IF(AND(AC54="Yes",SETTINGS!$B$16="No"),"No","Yes")) -> No | AG54: =IF(A54<>"Yes","",IF(OR(B54="",D54="",E54<=0,F54="",I54=""),"Check Required Fields",IF(AA54="Possible Duplicate","Possible Duplicate",IF(E54>SETTINGS!$B$22,"Review Extreme Value","OK"))))
H55: =IF(D55="","",IF(ISNUMBER(SEARCH(SETTINGS!$K$4,D55)),SETTINGS!$L$4,IF(ISNUMBER(SEARCH(SETTINGS!$K$5,D55)),SETTINGS!$L$5,IF(ISNUMBER(SEARCH(SETTINGS!$K$6,D55)),SETTINGS!$L$6,IF(ISNUMBER(SEARCH(SETTINGS!$K$7,D55)),SETTINGS!$L$7,IF(ISNUMBER(SEARCH(SETTINGS!$K$8,D55)),SETTINGS!$L$8,IF(ISNUMBER(SEARCH(SETTINGS!$K$9,D55)),SETTINGS!$L$9,IF(ISNUMBER(SEARCH(SETTINGS!$K$10,D55)),SETTINGS!$L$10,IF(ISNUMBER(SEARCH(SETTINGS!$K$11,D55)),SETTINGS!$L$11,IF(ISNUMBER(SEARCH(SETTINGS!$K$12,D55)),SETTINGS!$L$12,IF(ISNUMBER(SEARCH(SETTINGS!$K$13,D55)),SETTINGS!$L$13,IF(ISNUMBER(SEARCH(SETTINGS!$K$14,D55)),SETTINGS!$L$14,IF(ISNUMBER(SEARCH(SETTINGS!$K$15,D55)),SETTINGS!$L$15,IF(ISNUMBER(SEARCH(SETTINGS!$K$16,D55)),SETTINGS!$L$16,IF(ISNUMBER(SEARCH(SETTINGS!$K$17,D55)),SETTINGS!$L$17,IF(ISNUMBER(SEARCH(SETTINGS!$K$18,D55)),SETTINGS!$L$18,"Miscellaneous")))))))))))))))) | I55: =IF(B55="","",IF(G55<>"",G55,H55)) | U55: =IF(B55="","",IF(C55="Income","INC-",IF(C55="Expense","EXP-","TRX-"))&TEXT(YEAR(B55),"0000")&"-"&TEXT(ROW()-7,"0000")) | V55: =IF(B55="","",TEXT(B55,"mmmm")) | W55: =IF(B55="","",MONTH(B55)) | X55: =IF(B55="","",YEAR(B55)) | Y55: =IF(B55="","",DAY(B55)) | Z55: =IF(B55="","",IF(WEEKDAY(B55,2)>5,"Weekend","Weekday")) | AA55: =IF(B55="","",IF(COUNTIFS($B$8:$B$1007,B55,$E$8:$E$1007,E55,$D$8:$D$1007,D55,$I$8:$I$1007,I55)>1,"Possible Duplicate","OK")) | AB55: =IF(OR(B55="",C55<>"Expense"),"",IF(E55>IFERROR(AVERAGEIFS($E$8:$E$1007,$I$8:$I$1007,I55,$C$8:$C$1007,"Expense")*SETTINGS!$B$20,0),"Unusually High","Normal")) | AF55: =IF(A55<>"Yes","No",IF(AND(AC55="Yes",SETTINGS!$B$16="No"),"No","Yes")) -> No | AG55: =IF(A55<>"Yes","",IF(OR(B55="",D55="",E55<=0,F55="",I55=""),"Check Required Fields",IF(AA55="Possible Duplicate","Possible Duplicate",IF(E55>SETTINGS!$B$22,"Review Extreme Value","OK"))))
... H1007: =IF(D1007="","",IF(ISNUMBER(SEARCH(SETTINGS!$K$4,D1007)),SETTINGS!$L$4,IF(ISNUMBER(SEARCH(SETTINGS!$K$5,D1007)),SETTINGS!$L$5,IF(ISNUMBER(SEARCH(SETTINGS!$K$6,D1007)),SETTINGS!$L$6,IF(ISNUMBER(SEARCH(SETTINGS!$K$7,D1007)),SETTINGS!$L$7,IF(ISNUMBER(SEARCH(SETTINGS!$K$8,D1007)),SETTINGS!$L$8,IF(ISNUMBER(SEARCH(SETTINGS!$K$9,D1007)),SETTINGS!$L$9,IF(ISNUMBER(SEARCH(SETTINGS!$K$10,D1007)),SETTINGS!$L$10,IF(ISNUMBER(SEARCH(SETTINGS!$K$11,D1007)),SETTINGS!$L$11,IF(ISNUMBER(SEARCH(SETTINGS!$K$12,D1007)),SETTINGS!$L$12,IF(ISNUMBER(SEARCH(SETTINGS!$K$13,D1007)),SETTINGS!$L$13,IF(ISNUMBER(SEARCH(SETTINGS!$K$14,D1007)),SETTINGS!$L$14,IF(ISNUMBER(SEARCH(SETTINGS!$K$15,D1007)),SETTINGS!$L$15,IF(ISNUMBER(SEARCH(SETTINGS!$K$16,D1007)),SETTINGS!$L$16,IF(ISNUMBER(SEARCH(SETTINGS!$K$17,D1007)),SETTINGS!$L$17,IF(ISNUMBER(SEARCH(SETTINGS!$K$18,D1007)),SETTINGS!$L$18,"Miscellaneous")))))))))))))))) | I1007: =IF(B1007="","",IF(G1007<>"",G1007,H1007)) | U1007: =IF(B1007="","",IF(C1007="Income","INC-",IF(C1007="Expense","EXP-","TRX-"))&TEXT(YEAR(B1007),"0000")&"-"&TEXT(ROW()-7,"0000")) | V1007: =IF(B1007="","",TEXT(B1007,"mmmm")) | W1007: =IF(B1007="","",MONTH(B1007)) | X1007: =IF(B1007="","",YEAR(B1007)) | Y1007: =IF(B1007="","",DAY(B1007)) | Z1007: =IF(B1007="","",IF(WEEKDAY(B1007,2)>5,"Weekend","Weekday")) | AA1007: =IF(B1007="","",IF(COUNTIFS($B$8:$B$1007,B1007,$E$8:$E$1007,E1007,$D$8:$D$1007,D1007,$I$8:$I$1007,I1007)>1,"Possible Duplicate","OK")) | AB1007: =IF(OR(B1007="",C1007<>"Expense"),"",IF(E1007>IFERROR(AVERAGEIFS($E$8:$E$1007,$I$8:$I$1007,I1007,$C$8:$C$1007,"Expense")*SETTINGS!$B$20,0),"Unusually High","Normal")) | AF1007: =IF(A1007<>"Yes","No",IF(AND(AC1007="Yes",SETTINGS!$B$16="No"),"No","Yes")) -> No | AG1007: =IF(A1007<>"Yes","",IF(OR(B1007="",D1007="",E1007<=0,F1007="",I1007=""),"Check Required Fields",IF(AA1007="Possible Duplicate","Possible Duplicate",IF(E1007>SETTINGS!$B$22,"Review Extreme Value","OK"))))

Sheet TRANSACTIONS
A1: TRANSACTION AUDIT & SEARCH VIEW | B1: TRANSACTION AUDIT & SEARCH VIEW | C1: TRANSACTION AUDIT & SEARCH VIEW | D1: TRANSACTION AUDIT & SEARCH VIEW | E1: TRANSACTION AUDIT & SEARCH VIEW | F1: TRANSACTION AUDIT & SEARCH VIEW | G1: TRANSACTION AUDIT & SEARCH VIEW | H1: TRANSACTION AUDIT & SEARCH VIEW | I1: TRANSACTION AUDIT & SEARCH VIEW | J1: TRANSACTION AUDIT & SEARCH VIEW | K1: TRANSACTION AUDIT & SEARCH VIEW | L1: TRANSACTION AUDIT & SEARCH VIEW | M1: TRANSACTION AUDIT & SEARCH VIEW | N1: TRANSACTION AUDIT & SEARCH VIEW | O1: TRANSACTION AUDIT & SEARCH VIEW | P1: TRANSACTION AUDIT & SEARCH VIEW
A2: TRANSACTION AUDIT & SEARCH VIEW | B2: TRANSACTION AUDIT & SEARCH VIEW | C2: TRANSACTION AUDIT & SEARCH VIEW | D2: TRANSACTION AUDIT & SEARCH VIEW | E2: TRANSACTION AUDIT & SEARCH VIEW | F2: TRANSACTION AUDIT & SEARCH VIEW | G2: TRANSACTION AUDIT & SEARCH VIEW | H2: TRANSACTION AUDIT & SEARCH VIEW | I2: TRANSACTION AUDIT & SEARCH VIEW | J2: TRANSACTION AUDIT & SEARCH VIEW | K2: TRANSACTION AUDIT & SEARCH VIEW | L2: TRANSACTION AUDIT & SEARCH VIEW | M2: TRANSACTION AUDIT & SEARCH VIEW | N2: TRANSACTION AUDIT & SEARCH VIEW | O2: TRANSACTION AUDIT & SEARCH VIEW | P2: TRANSACTION AUDIT & SEARCH VIEW
A3: A formula-linked, filterable view of the master table. Enter or edit transactions only on QUICK ENTRY. | B3: A formula-linked, filterable view of the master table. Enter or edit transactions only on QUICK ENTRY. | C3: A formula-linked, filterable view of the master table. Enter or edit transactions only on QUICK ENTRY. | D3: A formula-linked, filterable view of the master table. Enter or edit transactions only on QUICK ENTRY. | E3: A formula-linked, filterable view of the master table. Enter or edit transactions only on QUICK ENTRY. | F3: A formula-linked, filterable view of the master table. Enter or edit transactions only on QUICK ENTRY. | G3: A formula-linked, filterable view of the master table. Enter or edit transactions only on QUICK ENTRY. | H3: A formula-linked, filterable view of the master table. Enter or edit transactions only on QUICK ENTRY. | I3: A formula-linked, filterable view of the master table. Enter or edit transactions only on QUICK ENTRY. | J3: A formula-linked, filterable view of the master table. Enter or edit transactions only on QUICK ENTRY. | K3: A formula-linked, filterable view of the master table. Enter or edit transactions only on QUICK ENTRY. | L3: A formula-linked, filterable view of the master table. Enter or edit transactions only on QUICK ENTRY. | M3: A formula-linked, filterable view of the master table. Enter or edit transactions only on QUICK ENTRY. | N3: A formula-linked, filterable view of the master table. Enter or edit transactions only on QUICK ENTRY. | O3: A formula-linked, filterable view of the master table. Enter or edit transactions only on QUICK ENTRY. | P3: A formula-linked, filterable view of the master table. Enter or edit transactions only on QUICK ENTRY.
A5: Use table filters to search by month, category, merchant, payment method, account, semester, tag or status. | B5: Use table filters to search by month, category, merchant, payment method, account, semester, tag or status. | C5: Use table filters to search by month, category, merchant, payment method, account, semester, tag or status. | D5: Use table filters to search by month, category, merchant, payment method, account, semester, tag or status. | E5: Use table filters to search by month, category, merchant, payment method, account, semester, tag or status. | F5: Use table filters to search by month, category, merchant, payment method, account, semester, tag or status. | G5: Use table filters to search by month, category, merchant, payment method, account, semester, tag or status. | H5: Use table filters to search by month, category, merchant, payment method, account, semester, tag or status. | I5: Use table filters to search by month, category, merchant, payment method, account, semester, tag or status. | J5: Use table filters to search by month, category, merchant, payment method, account, semester, tag or status. | K5: Use table filters to search by month, category, merchant, payment method, account, semester, tag or status. | L5: Use table filters to search by month, category, merchant, payment method, account, semester, tag or status. | M5: Use table filters to search by month, category, merchant, payment method, account, semester, tag or status. | N5: Use table filters to search by month, category, merchant, payment method, account, semester, tag or status. | O5: Use table filters to search by month, category, merchant, payment method, account, semester, tag or status. | P5: Use table filters to search by month, category, merchant, payment method, account, semester, tag or status.
A7: Transaction ID | B7: Date | C7: Type | D7: Category | E7: Description | F7: Merchant | G7: Amount | H7: Payment Method | I7: Account | J7: Need / Want | K7: Month | L7: Semester | M7: Status | N7: Duplicate | O7: Data Quality | P7: Report?
A8: =IF('QUICK ENTRY'!$B8="","",'QUICK ENTRY'!$U8) -> INC-2026-0001 | B8: =IF('QUICK ENTRY'!$B8="","",'QUICK ENTRY'!$B8) -> 46023 | C8: =IF('QUICK ENTRY'!$B8="","",'QUICK ENTRY'!$C8) -> Income | D8: =IF('QUICK ENTRY'!$B8="","",'QUICK ENTRY'!$I8) -> Miscellaneous | E8: =IF('QUICK ENTRY'!$B8="","",'QUICK ENTRY'!$D8) -> Monthly Allowance - January | F8: =IF('QUICK ENTRY'!$B8="","",'QUICK ENTRY'!$K8) -> 0 | G8: =IF('QUICK ENTRY'!$B8="","",'QUICK ENTRY'!$E8) -> 25000 | H8: =IF('QUICK ENTRY'!$B8="","",'QUICK ENTRY'!$F8) -> UPI | I8: =IF('QUICK ENTRY'!$B8="","",'QUICK ENTRY'!$L8) -> UPI-linked Bank | J8: =IF('QUICK ENTRY'!$B8="","",'QUICK ENTRY'!$M8) -> Essential | K8: =IF('QUICK ENTRY'!$B8="","",'QUICK ENTRY'!$V8) -> January | L8: =IF('QUICK ENTRY'!$B8="","",'QUICK ENTRY'!$R8) -> Not Applicable | M8: =IF('QUICK ENTRY'!$B8="","",'QUICK ENTRY'!$O8) -> Paid | N8: =IF('QUICK ENTRY'!$B8="","",'QUICK ENTRY'!$AA8) -> OK | O8: =IF('QUICK ENTRY'!$B8="","",'QUICK ENTRY'!$AG8) -> OK | P8: =IF('QUICK ENTRY'!$B8="","",'QUICK ENTRY'!$AF8) -> Yes
A9: =IF('QUICK ENTRY'!$B9="","",'QUICK ENTRY'!$U9) -> EXP-2026-0002 | B9: =IF('QUICK ENTRY'!$B9="","",'QUICK ENTRY'!$B9) -> 46027 | C9: =IF('QUICK ENTRY'!$B9="","",'QUICK ENTRY'!$C9) -> Expense | D9: =IF('QUICK ENTRY'!$B9="","",'QUICK ENTRY'!$I9) -> College Fees | E9: =IF('QUICK ENTRY'!$B9="","",'QUICK ENTRY'!$D9) -> Semester tuition installment | F9: =IF('QUICK ENTRY'!$B9="","",'QUICK ENTRY'!$K9) -> College | G9: =IF('QUICK ENTRY'!$B9="","",'QUICK ENTRY'!$E9) -> 4500 | H9: =IF('QUICK ENTRY'!$B9="","",'QUICK ENTRY'!$F9) -> Bank Transfer | I9: =IF('QUICK ENTRY'!$B9="","",'QUICK ENTRY'!$L9) -> UPI-linked Bank | J9: =IF('QUICK ENTRY'!$B9="","",'QUICK ENTRY'!$M9) -> Essential | K9: =IF('QUICK ENTRY'!$B9="","",'QUICK ENTRY'!$V9) -> January | L9: =IF('QUICK ENTRY'!$B9="","",'QUICK ENTRY'!$R9) -> Semester 1 | M9: =IF('QUICK ENTRY'!$B9="","",'QUICK ENTRY'!$O9) -> Paid | N9: =IF('QUICK ENTRY'!$B9="","",'QUICK ENTRY'!$AA9) -> OK | O9: =IF('QUICK ENTRY'!$B9="","",'QUICK ENTRY'!$AG9) -> OK | P9: =IF('QUICK ENTRY'!$B9="","",'QUICK ENTRY'!$AF9) -> Yes
A10: =IF('QUICK ENTRY'!$B10="","",'QUICK ENTRY'!$U10) -> EXP-2026-0003 | B10: =IF('QUICK ENTRY'!$B10="","",'QUICK ENTRY'!$B10) -> 46030 | C10: =IF('QUICK ENTRY'!$B10="","",'QUICK ENTRY'!$C10) -> Expense | D10: =IF('QUICK ENTRY'!$B10="","",'QUICK ENTRY'!$I10) -> Hostel | E10: =IF('QUICK ENTRY'!$B10="","",'QUICK ENTRY'!$D10) -> Hostel Fee | F10: =IF('QUICK ENTRY'!$B10="","",'QUICK ENTRY'!$K10) -> College Hostel | G10: =IF('QUICK ENTRY'!$B10="","",'QUICK ENTRY'!$E10) -> 3500 | H10: =IF('QUICK ENTRY'!$B10="","",'QUICK ENTRY'!$F10) -> Bank Transfer | I10: =IF('QUICK ENTRY'!$B10="","",'QUICK ENTRY'!$L10) -> UPI-linked Bank | J10: =IF('QUICK ENTRY'!$B10="","",'QUICK ENTRY'!$M10) -> Essential | K10: =IF('QUICK ENTRY'!$B10="","",'QUICK ENTRY'!$V10) -> January | L10: =IF('QUICK ENTRY'!$B10="","",'QUICK ENTRY'!$R10) -> Semester 1 | M10: =IF('QUICK ENTRY'!$B10="","",'QUICK ENTRY'!$O10) -> Paid | N10: =IF('QUICK ENTRY'!$B10="","",'QUICK ENTRY'!$AA10) -> OK | O10: =IF('QUICK ENTRY'!$B10="","",'QUICK ENTRY'!$AG10) -> OK | P10: =IF('QUICK ENTRY'!$B10="","",'QUICK ENTRY'!$AF10) -> Yes
A11: =IF('QUICK ENTRY'!$B11="","",'QUICK ENTRY'!$U11) -> INC-2026-0004 | B11: =IF('QUICK ENTRY'!$B11="","",'QUICK ENTRY'!$B11) -> 46054 | C11: =IF('QUICK ENTRY'!$B11="","",'QUICK ENTRY'!$C11) -> Income | D11: =IF('QUICK ENTRY'!$B11="","",'QUICK ENTRY'!$I11) -> Miscellaneous | E11: =IF('QUICK ENTRY'!$B11="","",'QUICK ENTRY'!$D11) -> Monthly Allowance - February | F11: =IF('QUICK ENTRY'!$B11="","",'QUICK ENTRY'!$K11) -> 0 | G11: =IF('QUICK ENTRY'!$B11="","",'QUICK ENTRY'!$E11) -> 25000 | H11: =IF('QUICK ENTRY'!$B11="","",'QUICK ENTRY'!$F11) -> UPI | I11: =IF('QUICK ENTRY'!$B11="","",'QUICK ENTRY'!$L11) -> UPI-linked Bank | J11: =IF('QUICK ENTRY'!$B11="","",'QUICK ENTRY'!$M11) -> Essential | K11: =IF('QUICK ENTRY'!$B11="","",'QUICK ENTRY'!$V11) -> February | L11: =IF('QUICK ENTRY'!$B11="","",'QUICK ENTRY'!$R11) -> Not Applicable | M11: =IF('QUICK ENTRY'!$B11="","",'QUICK ENTRY'!$O11) -> Paid | N11: =IF('QUICK ENTRY'!$B11="","",'QUICK ENTRY'!$AA11) -> OK | O11: =IF('QUICK ENTRY'!$B11="","",'QUICK ENTRY'!$AG11) -> OK | P11: =IF('QUICK ENTRY'!$B11="","",'QUICK ENTRY'!$AF11) -> Yes
A12: =IF('QUICK ENTRY'!$B12="","",'QUICK ENTRY'!$U12) -> EXP-2026-0005 | B12: =IF('QUICK ENTRY'!$B12="","",'QUICK ENTRY'!$B12) -> 46065 | C12: =IF('QUICK ENTRY'!$B12="","",'QUICK ENTRY'!$C12) -> Expense | D12: =IF('QUICK ENTRY'!$B12="","",'QUICK ENTRY'!$I12) -> Food | E12: =IF('QUICK ENTRY'!$B12="","",'QUICK ENTRY'!$D12) -> Groceries and fruit | F12: =IF('QUICK ENTRY'!$B12="","",'QUICK ENTRY'!$K12) -> Local Market | G12: =IF('QUICK ENTRY'!$B12="","",'QUICK ENTRY'!$E12) -> 3200 | H12: =IF('QUICK ENTRY'!$B12="","",'QUICK ENTRY'!$F12) -> UPI | I12: =IF('QUICK ENTRY'!$B12="","",'QUICK ENTRY'!$L12) -> UPI-linked Bank | J12: =IF('QUICK ENTRY'!$B12="","",'QUICK ENTRY'!$M12) -> Essential | K12: =IF('QUICK ENTRY'!$B12="","",'QUICK ENTRY'!$V12) -> February | L12: =IF('QUICK ENTRY'!$B12="","",'QUICK ENTRY'!$R12) -> Not Applicable | M12: =IF('QUICK ENTRY'!$B12="","",'QUICK ENTRY'!$O12) -> Paid | N12: =IF('QUICK ENTRY'!$B12="","",'QUICK ENTRY'!$AA12) -> OK | O12: =IF('QUICK ENTRY'!$B12="","",'QUICK ENTRY'!$AG12) -> OK | P12: =IF('QUICK ENTRY'!$B12="","",'QUICK ENTRY'!$AF12) -> Yes
A13: =IF('QUICK ENTRY'!$B13="","",'QUICK ENTRY'!$U13) -> EXP-2026-0006 | B13: =IF('QUICK ENTRY'!$B13="","",'QUICK ENTRY'!$B13) -> 46071 | C13: =IF('QUICK ENTRY'!$B13="","",'QUICK ENTRY'!$C13) -> Expense | D13: =IF('QUICK ENTRY'!$B13="","",'QUICK ENTRY'!$I13) -> Transport | E13: =IF('QUICK ENTRY'!$B13="","",'QUICK ENTRY'!$D13) -> Bus and metro commute | F13: =IF('QUICK ENTRY'!$B13="","",'QUICK ENTRY'!$K13) -> Transit | G13: =IF('QUICK ENTRY'!$B13="","",'QUICK ENTRY'!$E13) -> 1200 | H13: =IF('QUICK ENTRY'!$B13="","",'QUICK ENTRY'!$F13) -> UPI | I13: =IF('QUICK ENTRY'!$B13="","",'QUICK ENTRY'!$L13) -> UPI-linked Bank | J13: =IF('QUICK ENTRY'!$B13="","",'QUICK ENTRY'!$M13) -> Useful | K13: =IF('QUICK ENTRY'!$B13="","",'QUICK ENTRY'!$V13) -> February | L13: =IF('QUICK ENTRY'!$B13="","",'QUICK ENTRY'!$R13) -> Not Applicable | M13: =IF('QUICK ENTRY'!$B13="","",'QUICK ENTRY'!$O13) -> Paid | N13: =IF('QUICK ENTRY'!$B13="","",'QUICK ENTRY'!$AA13) -> OK | O13: =IF('QUICK ENTRY'!$B13="","",'QUICK ENTRY'!$AG13) -> OK | P13: =IF('QUICK ENTRY'!$B13="","",'QUICK ENTRY'!$AF13) -> Yes
A14: =IF('QUICK ENTRY'!$B14="","",'QUICK ENTRY'!$U14) -> INC-2026-0007 | B14: =IF('QUICK ENTRY'!$B14="","",'QUICK ENTRY'!$B14) -> 46082 | C14: =IF('QUICK ENTRY'!$B14="","",'QUICK ENTRY'!$C14) -> Income | D14: =IF('QUICK ENTRY'!$B14="","",'QUICK ENTRY'!$I14) -> Miscellaneous | E14: =IF('QUICK ENTRY'!$B14="","",'QUICK ENTRY'!$D14) -> Monthly Allowance - March | F14: =IF('QUICK ENTRY'!$B14="","",'QUICK ENTRY'!$K14) -> 0 | G14: =IF('QUICK ENTRY'!$B14="","",'QUICK ENTRY'!$E14) -> 25000 | H14: =IF('QUICK ENTRY'!$B14="","",'QUICK ENTRY'!$F14) -> UPI | I14: =IF('QUICK ENTRY'!$B14="","",'QUICK ENTRY'!$L14) -> UPI-linked Bank | J14: =IF('QUICK ENTRY'!$B14="","",'QUICK ENTRY'!$M14) -> Essential | K14: =IF('QUICK ENTRY'!$B14="","",'QUICK ENTRY'!$V14) -> March | L14: =IF('QUICK ENTRY'!$B14="","",'QUICK ENTRY'!$R14) -> Not Applicable | M14: =IF('QUICK ENTRY'!$B14="","",'QUICK ENTRY'!$O14) -> Paid | N14: =IF('QUICK ENTRY'!$B14="","",'QUICK ENTRY'!$AA14) -> OK | O14: =IF('QUICK ENTRY'!$B14="","",'QUICK ENTRY'!$AG14) -> OK | P14: =IF('QUICK ENTRY'!$B14="","",'QUICK ENTRY'!$AF14) -> Yes
A15: =IF('QUICK ENTRY'!$B15="","",'QUICK ENTRY'!$U15) -> EXP-2026-0008 | B15: =IF('QUICK ENTRY'!$B15="","",'QUICK ENTRY'!$B15) -> 46091 | C15: =IF('QUICK ENTRY'!$B15="","",'QUICK ENTRY'!$C15) -> Expense | D15: =IF('QUICK ENTRY'!$B15="","",'QUICK ENTRY'!$I15) -> Technology | E15: =IF('QUICK ENTRY'!$B15="","",'QUICK ENTRY'!$D15) -> Laptop repair and SSD | F15: =IF('QUICK ENTRY'!$B15="","",'QUICK ENTRY'!$K15) -> Computer Store | G15: =IF('QUICK ENTRY'!$B15="","",'QUICK ENTRY'!$E15) -> 2500 | H15: =IF('QUICK ENTRY'!$B15="","",'QUICK ENTRY'!$F15) -> Debit Card | I15: =IF('QUICK ENTRY'!$B15="","",'QUICK ENTRY'!$L15) -> UPI-linked Bank | J15: =IF('QUICK ENTRY'!$B15="","",'QUICK ENTRY'!$M15) -> Essential | K15: =IF('QUICK ENTRY'!$B15="","",'QUICK ENTRY'!$V15) -> March | L15: =IF('QUICK ENTRY'!$B15="","",'QUICK ENTRY'!$R15) -> Not Applicable | M15: =IF('QUICK ENTRY'!$B15="","",'QUICK ENTRY'!$O15) -> Paid | N15: =IF('QUICK ENTRY'!$B15="","",'QUICK ENTRY'!$AA15) -> OK | O15: =IF('QUICK ENTRY'!$B15="","",'QUICK ENTRY'!$AG15) -> OK | P15: =IF('QUICK ENTRY'!$B15="","",'QUICK ENTRY'!$AF15) -> Yes
A16: =IF('QUICK ENTRY'!$B16="","",'QUICK ENTRY'!$U16) -> EXP-2026-0009 | B16: =IF('QUICK ENTRY'!$B16="","",'QUICK ENTRY'!$B16) -> 46097 | C16: =IF('QUICK ENTRY'!$B16="","",'QUICK ENTRY'!$C16) -> Expense | D16: =IF('QUICK ENTRY'!$B16="","",'QUICK ENTRY'!$I16) -> Subscriptions | E16: =IF('QUICK ENTRY'!$B16="","",'QUICK ENTRY'!$D16) -> Netflix and cloud subscriptions | F16: =IF('QUICK ENTRY'!$B16="","",'QUICK ENTRY'!$K16) -> Netflix | G16: =IF('QUICK ENTRY'!$B16="","",'QUICK ENTRY'!$E16) -> 599 | H16: =IF('QUICK ENTRY'!$B16="","",'QUICK ENTRY'!$F16) -> UPI | I16: =IF('QUICK ENTRY'!$B16="","",'QUICK ENTRY'!$L16) -> UPI-linked Bank | J16: =IF('QUICK ENTRY'!$B16="","",'QUICK ENTRY'!$M16) -> Optional | K16: =IF('QUICK ENTRY'!$B16="","",'QUICK ENTRY'!$V16) -> March | L16: =IF('QUICK ENTRY'!$B16="","",'QUICK ENTRY'!$R16) -> Not Applicable | M16: =IF('QUICK ENTRY'!$B16="","",'QUICK ENTRY'!$O16) -> Paid | N16: =IF('QUICK ENTRY'!$B16="","",'QUICK ENTRY'!$AA16) -> OK | O16: =IF('QUICK ENTRY'!$B16="","",'QUICK ENTRY'!$AG16) -> OK | P16: =IF('QUICK ENTRY'!$B16="","",'QUICK ENTRY'!$AF16) -> Yes
A17: =IF('QUICK ENTRY'!$B17="","",'QUICK ENTRY'!$U17) -> INC-2026-0010 | B17: =IF('QUICK ENTRY'!$B17="","",'QUICK ENTRY'!$B17) -> 46113 | C17: =IF('QUICK ENTRY'!$B17="","",'QUICK ENTRY'!$C17) -> Income | D17: =IF('QUICK ENTRY'!$B17="","",'QUICK ENTRY'!$I17) -> Miscellaneous | E17: =IF('QUICK ENTRY'!$B17="","",'QUICK ENTRY'!$D17) -> Monthly Allowance - April | F17: =IF('QUICK ENTRY'!$B17="","",'QUICK ENTRY'!$K17) -> 0 | G17: =IF('QUICK ENTRY'!$B17="","",'QUICK ENTRY'!$E17) -> 25000 | H17: =IF('QUICK ENTRY'!$B17="","",'QUICK ENTRY'!$F17) -> UPI | I17: =IF('QUICK ENTRY'!$B17="","",'QUICK ENTRY'!$L17) -> UPI-linked Bank | J17: =IF('QUICK ENTRY'!$B17="","",'QUICK ENTRY'!$M17) -> Essential | K17: =IF('QUICK ENTRY'!$B17="","",'QUICK ENTRY'!$V17) -> April | L17: =IF('QUICK ENTRY'!$B17="","",'QUICK ENTRY'!$R17) -> Not Applicable | M17: =IF('QUICK ENTRY'!$B17="","",'QUICK ENTRY'!$O17) -> Paid | N17: =IF('QUICK ENTRY'!$B17="","",'QUICK ENTRY'!$AA17) -> OK | O17: =IF('QUICK ENTRY'!$B17="","",'QUICK ENTRY'!$AG17) -> OK | P17: =IF('QUICK ENTRY'!$B17="","",'QUICK ENTRY'!$AF17) -> Yes
A18: =IF('QUICK ENTRY'!$B18="","",'QUICK ENTRY'!$U18) -> EXP-2026-0011 | B18: =IF('QUICK ENTRY'!$B18="","",'QUICK ENTRY'!$B18) -> 46126 | C18: =IF('QUICK ENTRY'!$B18="","",'QUICK ENTRY'!$C18) -> Expense | D18: =IF('QUICK ENTRY'!$B18="","",'QUICK ENTRY'!$I18) -> Food | E18: =IF('QUICK ENTRY'!$B18="","",'QUICK ENTRY'!$D18) -> Mess and outside meals | F18: =IF('QUICK ENTRY'!$B18="","",'QUICK ENTRY'!$K18) -> Hostel Mess | G18: =IF('QUICK ENTRY'!$B18="","",'QUICK ENTRY'!$E18) -> 3700 | H18: =IF('QUICK ENTRY'!$B18="","",'QUICK ENTRY'!$F18) -> UPI | I18: =IF('QUICK ENTRY'!$B18="","",'QUICK ENTRY'!$L18) -> UPI-linked Bank | J18: =IF('QUICK ENTRY'!$B18="","",'QUICK ENTRY'!$M18) -> Essential | K18: =IF('QUICK ENTRY'!$B18="","",'QUICK ENTRY'!$V18) -> April | L18: =IF('QUICK ENTRY'!$B18="","",'QUICK ENTRY'!$R18) -> Not Applicable | M18: =IF('QUICK ENTRY'!$B18="","",'QUICK ENTRY'!$O18) -> Paid | N18: =IF('QUICK ENTRY'!$B18="","",'QUICK ENTRY'!$AA18) -> OK | O18: =IF('QUICK ENTRY'!$B18="","",'QUICK ENTRY'!$AG18) -> OK | P18: =IF('QUICK ENTRY'!$B18="","",'QUICK ENTRY'!$AF18) -> Yes
A19: =IF('QUICK ENTRY'!$B19="","",'QUICK ENTRY'!$U19) -> EXP-2026-0012 | B19: =IF('QUICK ENTRY'!$B19="","",'QUICK ENTRY'!$B19) -> 46134 | C19: =IF('QUICK ENTRY'!$B19="","",'QUICK ENTRY'!$C19) -> Expense | D19: =IF('QUICK ENTRY'!$B19="","",'QUICK ENTRY'!$I19) -> Personal Care | E19: =IF('QUICK ENTRY'!$B19="","",'QUICK ENTRY'!$D19) -> Haircut and toiletries | F19: =IF('QUICK ENTRY'!$B19="","",'QUICK ENTRY'!$K19) -> Local Shop | G19: =IF('QUICK ENTRY'!$B19="","",'QUICK ENTRY'!$E19) -> 1200 | H19: =IF('QUICK ENTRY'!$B19="","",'QUICK ENTRY'!$F19) -> UPI | I19: =IF('QUICK ENTRY'!$B19="","",'QUICK ENTRY'!$L19) -> UPI-linked Bank | J19: =IF('QUICK ENTRY'!$B19="","",'QUICK ENTRY'!$M19) -> Useful | K19: =IF('QUICK ENTRY'!$B19="","",'QUICK ENTRY'!$V19) -> April | L19: =IF('QUICK ENTRY'!$B19="","",'QUICK ENTRY'!$R19) -> Not Applicable | M19: =IF('QUICK ENTRY'!$B19="","",'QUICK ENTRY'!$O19) -> Paid | N19: =IF('QUICK ENTRY'!$B19="","",'QUICK ENTRY'!$AA19) -> OK | O19: =IF('QUICK ENTRY'!$B19="","",'QUICK ENTRY'!$AG19) -> OK | P19: =IF('QUICK ENTRY'!$B19="","",'QUICK ENTRY'!$AF19) -> Yes
... A307: =IF('QUICK ENTRY'!$B307="","",'QUICK ENTRY'!$U307) | B307: =IF('QUICK ENTRY'!$B307="","",'QUICK ENTRY'!$B307) | C307: =IF('QUICK ENTRY'!$B307="","",'QUICK ENTRY'!$C307) | D307: =IF('QUICK ENTRY'!$B307="","",'QUICK ENTRY'!$I307) | E307: =IF('QUICK ENTRY'!$B307="","",'QUICK ENTRY'!$D307) | F307: =IF('QUICK ENTRY'!$B307="","",'QUICK ENTRY'!$K307) | G307: =IF('QUICK ENTRY'!$B307="","",'QUICK ENTRY'!$E307) | H307: =IF('QUICK ENTRY'!$B307="","",'QUICK ENTRY'!$F307) | I307: =IF('QUICK ENTRY'!$B307="","",'QUICK ENTRY'!$L307) | J307: =IF('QUICK ENTRY'!$B307="","",'QUICK ENTRY'!$M307) | K307: =IF('QUICK ENTRY'!$B307="","",'QUICK ENTRY'!$V307) | L307: =IF('QUICK ENTRY'!$B307="","",'QUICK ENTRY'!$R307) | M307: =IF('QUICK ENTRY'!$B307="","",'QUICK ENTRY'!$O307) | N307: =IF('QUICK ENTRY'!$B307="","",'QUICK ENTRY'!$AA307) | O307: =IF('QUICK ENTRY'!$B307="","",'QUICK ENTRY'!$AG307) | P307: =IF('QUICK ENTRY'!$B307="","",'QUICK ENTRY'!$AF307)

Sheet MONTHLY BUDGET
A1: MONTHLY BUDGET PLANNER | B1: MONTHLY BUDGET PLANNER | C1: MONTHLY BUDGET PLANNER | D1: MONTHLY BUDGET PLANNER | E1: MONTHLY BUDGET PLANNER | F1: MONTHLY BUDGET PLANNER | G1: MONTHLY BUDGET PLANNER | H1: MONTHLY BUDGET PLANNER | I1: MONTHLY BUDGET PLANNER | J1: MONTHLY BUDGET PLANNER | K1: MONTHLY BUDGET PLANNER | L1: MONTHLY BUDGET PLANNER | M1: MONTHLY BUDGET PLANNER | N1: MONTHLY BUDGET PLANNER | O1: MONTHLY BUDGET PLANNER | P1: MONTHLY BUDGET PLANNER | Q1: MONTHLY BUDGET PLANNER | R1: MONTHLY BUDGET PLANNER | S1: MONTHLY BUDGET PLANNER | T1: MONTHLY BUDGET PLANNER | U1: MONTHLY BUDGET PLANNER | V1: MONTHLY BUDGET PLANNER | W1: MONTHLY BUDGET PLANNER | X1: MONTHLY BUDGET PLANNER
A2: MONTHLY BUDGET PLANNER | B2: MONTHLY BUDGET PLANNER | C2: MONTHLY BUDGET PLANNER | D2: MONTHLY BUDGET PLANNER | E2: MONTHLY BUDGET PLANNER | F2: MONTHLY BUDGET PLANNER | G2: MONTHLY BUDGET PLANNER | H2: MONTHLY BUDGET PLANNER | I2: MONTHLY BUDGET PLANNER | J2: MONTHLY BUDGET PLANNER | K2: MONTHLY BUDGET PLANNER | L2: MONTHLY BUDGET PLANNER | M2: MONTHLY BUDGET PLANNER | N2: MONTHLY BUDGET PLANNER | O2: MONTHLY BUDGET PLANNER | P2: MONTHLY BUDGET PLANNER | Q2: MONTHLY BUDGET PLANNER | R2: MONTHLY BUDGET PLANNER | S2: MONTHLY BUDGET PLANNER | T2: MONTHLY BUDGET PLANNER | U2: MONTHLY BUDGET PLANNER | V2: MONTHLY BUDGET PLANNER | W2: MONTHLY BUDGET PLANNER | X2: MONTHLY BUDGET PLANNER
A3: Plan once, track automatically. Monthly budgets are editable; actuals, forecasts and alerts are fed by the master transaction table. | B3: Plan once, track automatically. Monthly budgets are editable; actuals, forecasts and alerts are fed by the master transaction table. | C3: Plan once, track automatically. Monthly budgets are editable; actuals, forecasts and alerts are fed by the master transaction table. | D3: Plan once, track automatically. Monthly budgets are editable; actuals, forecasts and alerts are fed by the master transaction table. | E3: Plan once, track automatically. Monthly budgets are editable; actuals, forecasts and alerts are fed by the master transaction table. | F3: Plan once, track automatically. Monthly budgets are editable; actuals, forecasts and alerts are fed by the master transaction table. | G3: Plan once, track automatically. Monthly budgets are editable; actuals, forecasts and alerts are fed by the master transaction table. | H3: Plan once, track automatically. Monthly budgets are editable; actuals, forecasts and alerts are fed by the master transaction table. | I3: Plan once, track automatically. Monthly budgets are editable; actuals, forecasts and alerts are fed by the master transaction table. | J3: Plan once, track automatically. Monthly budgets are editable; actuals, forecasts and alerts are fed by the master transaction table. | K3: Plan once, track automatically. Monthly budgets are editable; actuals, forecasts and alerts are fed by the master transaction table. | L3: Plan once, track automatically. Monthly budgets are editable; actuals, forecasts and alerts are fed by the master transaction table. | M3: Plan once, track automatically. Monthly budgets are editable; actuals, forecasts and alerts are fed by the master transaction table. | N3: Plan once, track automatically. Monthly budgets are editable; actuals, forecasts and alerts are fed by the master transaction table. | O3: Plan once, track automatically. Monthly budgets are editable; actuals, forecasts and alerts are fed by the master transaction table. | P3: Plan once, track automatically. Monthly budgets are editable; actuals, forecasts and alerts are fed by the master transaction table. | Q3: Plan once, track automatically. Monthly budgets are editable; actuals, forecasts and alerts are fed by the master transaction table. | R3: Plan once, track automatically. Monthly budgets are editable; actuals, forecasts and alerts are fed by the master transaction table. | S3: Plan once, track automatically. Monthly budgets are editable; actuals, forecasts and alerts are fed by the master transaction table. | T3: Plan once, track automatically. Monthly budgets are editable; actuals, forecasts and alerts are fed by the master transaction table. | U3: Plan once, track automatically. Monthly budgets are editable; actuals, forecasts and alerts are fed by the master transaction table. | V3: Plan once, track automatically. Monthly budgets are editable; actuals, forecasts and alerts are fed by the master transaction table. | W3: Plan once, track automatically. Monthly budgets are editable; actuals, forecasts and alerts are fed by the master transaction table. | X3: Plan once, track automatically. Monthly budgets are editable; actuals, forecasts and alerts are fed by the master transaction table.
A4: Selected dashboard period | B4: Selected dashboard period | C4: Selected dashboard period | D4: Selected dashboard period | E4: Selected dashboard period | F4: Selected dashboard period | G4: =DASHBOARD!$C$3&" "&TEXT(DASHBOARD!$C$4,"0") -> September 2026 | K4: Budget status: 0–70% Safe · 71–90% Watch · 91–100% Near Limit · Above 100% Over Budget | L4: Budget status: 0–70% Safe · 71–90% Watch · 91–100% Near Limit · Above 100% Over Budget | M4: Budget status: 0–70% Safe · 71–90% Watch · 91–100% Near Limit · Above 100% Over Budget | N4: Budget status: 0–70% Safe · 71–90% Watch · 91–100% Near Limit · Above 100% Over Budget | O4: Budget status: 0–70% Safe · 71–90% Watch · 91–100% Near Limit · Above 100% Over Budget | P4: Budget status: 0–70% Safe · 71–90% Watch · 91–100% Near Limit · Above 100% Over Budget | Q4: Budget status: 0–70% Safe · 71–90% Watch · 91–100% Near Limit · Above 100% Over Budget | R4: Budget status: 0–70% Safe · 71–90% Watch · 91–100% Near Limit · Above 100% Over Budget | S4: Budget status: 0–70% Safe · 71–90% Watch · 91–100% Near Limit · Above 100% Over Budget | T4: Budget status: 0–70% Safe · 71–90% Watch · 91–100% Near Limit · Above 100% Over Budget | U4: Budget status: 0–70% Safe · 71–90% Watch · 91–100% Near Limit · Above 100% Over Budget | V4: Budget status: 0–70% Safe · 71–90% Watch · 91–100% Near Limit · Above 100% Over Budget | W4: Budget status: 0–70% Safe · 71–90% Watch · 91–100% Near Limit · Above 100% Over Budget | X4: Budget status: 0–70% Safe · 71–90% Watch · 91–100% Near Limit · Above 100% Over Budget
A5: Selected dashboard period | B5: Selected dashboard period | C5: Selected dashboard period | D5: Selected dashboard period | E5: Selected dashboard period | F5: Selected dashboard period | K5: Budget status: 0–70% Safe · 71–90% Watch · 91–100% Near Limit · Above 100% Over Budget | L5: Budget status: 0–70% Safe · 71–90% Watch · 91–100% Near Limit · Above 100% Over Budget | M5: Budget status: 0–70% Safe · 71–90% Watch · 91–100% Near Limit · Above 100% Over Budget | N5: Budget status: 0–70% Safe · 71–90% Watch · 91–100% Near Limit · Above 100% Over Budget | O5: Budget status: 0–70% Safe · 71–90% Watch · 91–100% Near Limit · Above 100% Over Budget | P5: Budget status: 0–70% Safe · 71–90% Watch · 91–100% Near Limit · Above 100% Over Budget | Q5: Budget status: 0–70% Safe · 71–90% Watch · 91–100% Near Limit · Above 100% Over Budget | R5: Budget status: 0–70% Safe · 71–90% Watch · 91–100% Near Limit · Above 100% Over Budget | S5: Budget status: 0–70% Safe · 71–90% Watch · 91–100% Near Limit · Above 100% Over Budget | T5: Budget status: 0–70% Safe · 71–90% Watch · 91–100% Near Limit · Above 100% Over Budget | U5: Budget status: 0–70% Safe · 71–90% Watch · 91–100% Near Limit · Above 100% Over Budget | V5: Budget status: 0–70% Safe · 71–90% Watch · 91–100% Near Limit · Above 100% Over Budget | W5: Budget status: 0–70% Safe · 71–90% Watch · 91–100% Near Limit · Above 100% Over Budget | X5: Budget status: 0–70% Safe · 71–90% Watch · 91–100% Near Limit · Above 100% Over Budget
A7: Category | B7: Priority | C7: Cost Type | D7: Need Class | E7: Domain | F7: Default Budget | G7: January | H7: February | I7: March | J7: April | K7: May | L7: June | M7: July | N7: August | O7: September | P7: October | Q7: November | R7: December | S7: Selected Budget | T7: Actual | U7: Difference | V7: % Used | W7: Projected | X7: Status
A8: =SETTINGS!$A$33 -> College Fees | B8: =SETTINGS!$C$33 -> Priority 1 | C8: =SETTINGS!$D$33 -> Fixed | D8: =SETTINGS!$E$33 -> Essential | E8: =SETTINGS!$F$33 -> Education | F8: =SETTINGS!$B$33 -> 4500 | G8: =$F8 -> 4500 | H8: =$F8 -> 4500 | I8: =$F8 -> 4500 | J8: =$F8 -> 4500 | K8: =$F8 -> 4500 | L8: =$F8 -> 4500 | M8: =$F8 -> 4500 | N8: =$F8 -> 4500 | ... R8: =$F8 -> 4500 | S8: =IFERROR(INDEX($G8:$R8,1,MATCH(DASHBOARD!$C$3,$G$7:$R$7,0)),0) -> 4500 | T8: =SUMIFS('QUICK ENTRY'!$E$8:$E$1007,'QUICK ENTRY'!$AF$8:$AF$1007,"Yes",'QUICK ENTRY'!$C$8:$C$1007,IF($A8="Savings","Savings Transfer","Expense"),'QUICK ENTRY'!$I$8:$I$1007,$A8,'QUICK ENTRY'!$V$8:$V$1007,DASHBOARD!$C$3,'QUICK ENTRY'!$X$8:$X$1007,DASHBOARD!$C$4) -> 0 | U8: =$S8-$T8 -> 4500 | V8: =IFERROR($T8/$S8,0) -> 0 | W8: =IF($T8=0,0,IF($A8="Savings",$T8,IF(AND(DASHBOARD!$C$4=YEAR(TODAY()),MATCH(DASHBOARD!$C$3,SETTINGS!$K$21:$K$32,0)=MONTH(TODAY())),MIN($T8/MAX(1,DAY(TODAY()))*DAY(DATE(DASHBOARD!$C$4,MATCH(DASHBOARD!$C$3,SETTINGS!$K$21:$K$32,0)+1,0)),MAX($T8,$S8*1.5)),$T8))) -> 0 | X8: =IF($S8=0,IF($T8=0,"No Budget","Over Budget"),IF($V8<=SETTINGS!$E$5,"Safe",IF($V8<=SETTINGS!$E$6,"Watch Spending",IF($V8<=SETTINGS!$E$7,"Near Limit","Over Budget")))) -> Safe
A9: =SETTINGS!$A$34 -> Hostel | B9: =SETTINGS!$C$34 -> Priority 1 | C9: =SETTINGS!$D$34 -> Fixed | D9: =SETTINGS!$E$34 -> Essential | E9: =SETTINGS!$F$34 -> Living | F9: =SETTINGS!$B$34 -> 3500 | G9: =$F9 -> 3500 | H9: =$F9 -> 3500 | I9: =$F9 -> 3500 | J9: =$F9 -> 3500 | K9: =$F9 -> 3500 | L9: =$F9 -> 3500 | M9: =$F9 -> 3500 | N9: =$F9 -> 3500 | ... R9: =$F9 -> 3500 | S9: =IFERROR(INDEX($G9:$R9,1,MATCH(DASHBOARD!$C$3,$G$7:$R$7,0)),0) -> 3500 | T9: =SUMIFS('QUICK ENTRY'!$E$8:$E$1007,'QUICK ENTRY'!$AF$8:$AF$1007,"Yes",'QUICK ENTRY'!$C$8:$C$1007,IF($A9="Savings","Savings Transfer","Expense"),'QUICK ENTRY'!$I$8:$I$1007,$A9,'QUICK ENTRY'!$V$8:$V$1007,DASHBOARD!$C$3,'QUICK ENTRY'!$X$8:$X$1007,DASHBOARD!$C$4) -> 3200 | U9: =$S9-$T9 -> 300 | V9: =IFERROR($T9/$S9,0) -> 0.91428571 | W9: =IF($T9=0,0,IF($A9="Savings",$T9,IF(AND(DASHBOARD!$C$4=YEAR(TODAY()),MATCH(DASHBOARD!$C$3,SETTINGS!$K$21:$K$32,0)=MONTH(TODAY())),MIN($T9/MAX(1,DAY(TODAY()))*DAY(DATE(DASHBOARD!$C$4,MATCH(DASHBOARD!$C$3,SETTINGS!$K$21:$K$32,0)+1,0)),MAX($T9,$S9*1.5)),$T9))) -> 3200 | X9: =IF($S9=0,IF($T9=0,"No Budget","Over Budget"),IF($V9<=SETTINGS!$E$5,"Safe",IF($V9<=SETTINGS!$E$6,"Watch Spending",IF($V9<=SETTINGS!$E$7,"Near Limit","Over Budget")))) -> Near Limit
A10: =SETTINGS!$A$35 -> Food | B10: =SETTINGS!$C$35 -> Priority 1 | C10: =SETTINGS!$D$35 -> Variable | D10: =SETTINGS!$E$35 -> Essential | E10: =SETTINGS!$F$35 -> Living | F10: =SETTINGS!$B$35 -> 4000 | G10: =$F10 -> 4000 | H10: =$F10 -> 4000 | I10: =$F10 -> 4000 | J10: =$F10 -> 4000 | K10: =$F10 -> 4000 | L10: =$F10 -> 4000 | M10: =$F10 -> 4000 | N10: =$F10 -> 4000 | ... R10: =$F10 -> 4000 | S10: =IFERROR(INDEX($G10:$R10,1,MATCH(DASHBOARD!$C$3,$G$7:$R$7,0)),0) -> 4000 | T10: =SUMIFS('QUICK ENTRY'!$E$8:$E$1007,'QUICK ENTRY'!$AF$8:$AF$1007,"Yes",'QUICK ENTRY'!$C$8:$C$1007,IF($A10="Savings","Savings Transfer","Expense"),'QUICK ENTRY'!$I$8:$I$1007,$A10,'QUICK ENTRY'!$V$8:$V$1007,DASHBOARD!$C$3,'QUICK ENTRY'!$X$8:$X$1007,DASHBOARD!$C$4) -> 620 | U10: =$S10-$T10 -> 3380 | V10: =IFERROR($T10/$S10,0) -> 0.155 | W10: =IF($T10=0,0,IF($A10="Savings",$T10,IF(AND(DASHBOARD!$C$4=YEAR(TODAY()),MATCH(DASHBOARD!$C$3,SETTINGS!$K$21:$K$32,0)=MONTH(TODAY())),MIN($T10/MAX(1,DAY(TODAY()))*DAY(DATE(DASHBOARD!$C$4,MATCH(DASHBOARD!$C$3,SETTINGS!$K$21:$K$32,0)+1,0)),MAX($T10,$S10*1.5)),$T10))) -> 620 | X10: =IF($S10=0,IF($T10=0,"No Budget","Over Budget"),IF($V10<=SETTINGS!$E$5,"Safe",IF($V10<=SETTINGS!$E$6,"Watch Spending",IF($V10<=SETTINGS!$E$7,"Near Limit","Over Budget")))) -> Safe
A11: =SETTINGS!$A$36 -> Transport | B11: =SETTINGS!$C$36 -> Priority 2 | C11: =SETTINGS!$D$36 -> Variable | D11: =SETTINGS!$E$36 -> Useful | E11: =SETTINGS!$F$36 -> Living | F11: =SETTINGS!$B$36 -> 1500 | G11: =$F11 -> 1500 | H11: =$F11 -> 1500 | I11: =$F11 -> 1500 | J11: =$F11 -> 1500 | K11: =$F11 -> 1500 | L11: =$F11 -> 1500 | M11: =$F11 -> 1500 | N11: =$F11 -> 1500 | ... R11: =$F11 -> 1500 | S11: =IFERROR(INDEX($G11:$R11,1,MATCH(DASHBOARD!$C$3,$G$7:$R$7,0)),0) -> 1500 | T11: =SUMIFS('QUICK ENTRY'!$E$8:$E$1007,'QUICK ENTRY'!$AF$8:$AF$1007,"Yes",'QUICK ENTRY'!$C$8:$C$1007,IF($A11="Savings","Savings Transfer","Expense"),'QUICK ENTRY'!$I$8:$I$1007,$A11,'QUICK ENTRY'!$V$8:$V$1007,DASHBOARD!$C$3,'QUICK ENTRY'!$X$8:$X$1007,DASHBOARD!$C$4) -> 350 | U11: =$S11-$T11 -> 1150 | V11: =IFERROR($T11/$S11,0) -> 0.23333333 | W11: =IF($T11=0,0,IF($A11="Savings",$T11,IF(AND(DASHBOARD!$C$4=YEAR(TODAY()),MATCH(DASHBOARD!$C$3,SETTINGS!$K$21:$K$32,0)=MONTH(TODAY())),MIN($T11/MAX(1,DAY(TODAY()))*DAY(DATE(DASHBOARD!$C$4,MATCH(DASHBOARD!$C$3,SETTINGS!$K$21:$K$32,0)+1,0)),MAX($T11,$S11*1.5)),$T11))) -> 350 | X11: =IF($S11=0,IF($T11=0,"No Budget","Over Budget"),IF($V11<=SETTINGS!$E$5,"Safe",IF($V11<=SETTINGS!$E$6,"Watch Spending",IF($V11<=SETTINGS!$E$7,"Near Limit","Over Budget")))) -> Safe
A12: =SETTINGS!$A$37 -> Technology | B12: =SETTINGS!$C$37 -> Priority 2 | C12: =SETTINGS!$D$37 -> Variable | D12: =SETTINGS!$E$37 -> Useful | E12: =SETTINGS!$F$37 -> Education | F12: =SETTINGS!$B$37 -> 1500 | G12: =$F12 -> 1500 | H12: =$F12 -> 1500 | I12: =$F12 -> 1500 | J12: =$F12 -> 1500 | K12: =$F12 -> 1500 | L12: =$F12 -> 1500 | M12: =$F12 -> 1500 | N12: =$F12 -> 1500 | ... R12: =$F12 -> 1500 | S12: =IFERROR(INDEX($G12:$R12,1,MATCH(DASHBOARD!$C$3,$G$7:$R$7,0)),0) -> 1500 | T12: =SUMIFS('QUICK ENTRY'!$E$8:$E$1007,'QUICK ENTRY'!$AF$8:$AF$1007,"Yes",'QUICK ENTRY'!$C$8:$C$1007,IF($A12="Savings","Savings Transfer","Expense"),'QUICK ENTRY'!$I$8:$I$1007,$A12,'QUICK ENTRY'!$V$8:$V$1007,DASHBOARD!$C$3,'QUICK ENTRY'!$X$8:$X$1007,DASHBOARD!$C$4) -> 0 | U12: =$S12-$T12 -> 1500 | V12: =IFERROR($T12/$S12,0) -> 0 | W12: =IF($T12=0,0,IF($A12="Savings",$T12,IF(AND(DASHBOARD!$C$4=YEAR(TODAY()),MATCH(DASHBOARD!$C$3,SETTINGS!$K$21:$K$32,0)=MONTH(TODAY())),MIN($T12/MAX(1,DAY(TODAY()))*DAY(DATE(DASHBOARD!$C$4,MATCH(DASHBOARD!$C$3,SETTINGS!$K$21:$K$32,0)+1,0)),MAX($T12,$S12*1.5)),$T12))) -> 0 | X12: =IF($S12=0,IF($T12=0,"No Budget","Over Budget"),IF($V12<=SETTINGS!$E$5,"Safe",IF($V12<=SETTINGS!$E$6,"Watch Spending",IF($V12<=SETTINGS!$E$7,"Near Limit","Over Budget")))) -> Safe
A13: =SETTINGS!$A$38 -> AI-ML Learning | B13: =SETTINGS!$C$38 -> Priority 2 | C13: =SETTINGS!$D$38 -> Variable | D13: =SETTINGS!$E$38 -> Useful | E13: =SETTINGS!$F$38 -> Education | F13: =SETTINGS!$B$38 -> 1000 | G13: =$F13 -> 1000 | H13: =$F13 -> 1000 | I13: =$F13 -> 1000 | J13: =$F13 -> 1000 | K13: =$F13 -> 1000 | L13: =$F13 -> 1000 | M13: =$F13 -> 1000 | N13: =$F13 -> 1000 | ... R13: =$F13 -> 1000 | S13: =IFERROR(INDEX($G13:$R13,1,MATCH(DASHBOARD!$C$3,$G$7:$R$7,0)),0) -> 1000 | T13: =SUMIFS('QUICK ENTRY'!$E$8:$E$1007,'QUICK ENTRY'!$AF$8:$AF$1007,"Yes",'QUICK ENTRY'!$C$8:$C$1007,IF($A13="Savings","Savings Transfer","Expense"),'QUICK ENTRY'!$I$8:$I$1007,$A13,'QUICK ENTRY'!$V$8:$V$1007,DASHBOARD!$C$3,'QUICK ENTRY'!$X$8:$X$1007,DASHBOARD!$C$4) -> 1499 | U13: =$S13-$T13 -> -499 | V13: =IFERROR($T13/$S13,0) -> 1.499 | W13: =IF($T13=0,0,IF($A13="Savings",$T13,IF(AND(DASHBOARD!$C$4=YEAR(TODAY()),MATCH(DASHBOARD!$C$3,SETTINGS!$K$21:$K$32,0)=MONTH(TODAY())),MIN($T13/MAX(1,DAY(TODAY()))*DAY(DATE(DASHBOARD!$C$4,MATCH(DASHBOARD!$C$3,SETTINGS!$K$21:$K$32,0)+1,0)),MAX($T13,$S13*1.5)),$T13))) -> 1499 | X13: =IF($S13=0,IF($T13=0,"No Budget","Over Budget"),IF($V13<=SETTINGS!$E$5,"Safe",IF($V13<=SETTINGS!$E$6,"Watch Spending",IF($V13<=SETTINGS!$E$7,"Near Limit","Over Budget")))) -> Over Budget
A14: =SETTINGS!$A$39 -> Books & Stationery | B14: =SETTINGS!$C$39 -> Priority 2 | C14: =SETTINGS!$D$39 -> Variable | D14: =SETTINGS!$E$39 -> Useful | E14: =SETTINGS!$F$39 -> Education | F14: =SETTINGS!$B$39 -> 500 | G14: =$F14 -> 500 | H14: =$F14 -> 500 | I14: =$F14 -> 500 | J14: =$F14 -> 500 | K14: =$F14 -> 500 | L14: =$F14 -> 500 | M14: =$F14 -> 500 | N14: =$F14 -> 500 | ... R14: =$F14 -> 500 | S14: =IFERROR(INDEX($G14:$R14,1,MATCH(DASHBOARD!$C$3,$G$7:$R$7,0)),0) -> 500 | T14: =SUMIFS('QUICK ENTRY'!$E$8:$E$1007,'QUICK ENTRY'!$AF$8:$AF$1007,"Yes",'QUICK ENTRY'!$C$8:$C$1007,IF($A14="Savings","Savings Transfer","Expense"),'QUICK ENTRY'!$I$8:$I$1007,$A14,'QUICK ENTRY'!$V$8:$V$1007,DASHBOARD!$C$3,'QUICK ENTRY'!$X$8:$X$1007,DASHBOARD!$C$4) -> 280 | U14: =$S14-$T14 -> 220 | V14: =IFERROR($T14/$S14,0) -> 0.56 | W14: =IF($T14=0,0,IF($A14="Savings",$T14,IF(AND(DASHBOARD!$C$4=YEAR(TODAY()),MATCH(DASHBOARD!$C$3,SETTINGS!$K$21:$K$32,0)=MONTH(TODAY())),MIN($T14/MAX(1,DAY(TODAY()))*DAY(DATE(DASHBOARD!$C$4,MATCH(DASHBOARD!$C$3,SETTINGS!$K$21:$K$32,0)+1,0)),MAX($T14,$S14*1.5)),$T14))) -> 280 | X14: =IF($S14=0,IF($T14=0,"No Budget","Over Budget"),IF($V14<=SETTINGS!$E$5,"Safe",IF($V14<=SETTINGS!$E$6,"Watch Spending",IF($V14<=SETTINGS!$E$7,"Near Limit","Over Budget")))) -> Safe
A15: =SETTINGS!$A$40 -> Subscriptions | B15: =SETTINGS!$C$40 -> Priority 3 | C15: =SETTINGS!$D$40 -> Fixed | D15: =SETTINGS!$E$40 -> Optional | E15: =SETTINGS!$F$40 -> Lifestyle | F15: =SETTINGS!$B$40 -> 600 | G15: =$F15 -> 600 | H15: =$F15 -> 600 | I15: =$F15 -> 600 | J15: =$F15 -> 600 | K15: =$F15 -> 600 | L15: =$F15 -> 600 | M15: =$F15 -> 600 | N15: =$F15 -> 600 | ... R15: =$F15 -> 600 | S15: =IFERROR(INDEX($G15:$R15,1,MATCH(DASHBOARD!$C$3,$G$7:$R$7,0)),0) -> 600 | T15: =SUMIFS('QUICK ENTRY'!$E$8:$E$1007,'QUICK ENTRY'!$AF$8:$AF$1007,"Yes",'QUICK ENTRY'!$C$8:$C$1007,IF($A15="Savings","Savings Transfer","Expense"),'QUICK ENTRY'!$I$8:$I$1007,$A15,'QUICK ENTRY'!$V$8:$V$1007,DASHBOARD!$C$3,'QUICK ENTRY'!$X$8:$X$1007,DASHBOARD!$C$4) -> 199 | U15: =$S15-$T15 -> 401 | V15: =IFERROR($T15/$S15,0) -> 0.33166667 | W15: =IF($T15=0,0,IF($A15="Savings",$T15,IF(AND(DASHBOARD!$C$4=YEAR(TODAY()),MATCH(DASHBOARD!$C$3,SETTINGS!$K$21:$K$32,0)=MONTH(TODAY())),MIN($T15/MAX(1,DAY(TODAY()))*DAY(DATE(DASHBOARD!$C$4,MATCH(DASHBOARD!$C$3,SETTINGS!$K$21:$K$32,0)+1,0)),MAX($T15,$S15*1.5)),$T15))) -> 199 | X15: =IF($S15=0,IF($T15=0,"No Budget","Over Budget"),IF($V15<=SETTINGS!$E$5,"Safe",IF($V15<=SETTINGS!$E$6,"Watch Spending",IF($V15<=SETTINGS!$E$7,"Near Limit","Over Budget")))) -> Safe
A16: =SETTINGS!$A$41 -> Mobile & Internet | B16: =SETTINGS!$C$41 -> Priority 1 | C16: =SETTINGS!$D$41 -> Fixed | D16: =SETTINGS!$E$41 -> Essential | E16: =SETTINGS!$F$41 -> Living | F16: =SETTINGS!$B$41 -> 400 | G16: =$F16 -> 400 | H16: =$F16 -> 400 | I16: =$F16 -> 400 | J16: =$F16 -> 400 | K16: =$F16 -> 400 | L16: =$F16 -> 400 | M16: =$F16 -> 400 | N16: =$F16 -> 400 | ... R16: =$F16 -> 400 | S16: =IFERROR(INDEX($G16:$R16,1,MATCH(DASHBOARD!$C$3,$G$7:$R$7,0)),0) -> 400 | T16: =SUMIFS('QUICK ENTRY'!$E$8:$E$1007,'QUICK ENTRY'!$AF$8:$AF$1007,"Yes",'QUICK ENTRY'!$C$8:$C$1007,IF($A16="Savings","Savings Transfer","Expense"),'QUICK ENTRY'!$I$8:$I$1007,$A16,'QUICK ENTRY'!$V$8:$V$1007,DASHBOARD!$C$3,'QUICK ENTRY'!$X$8:$X$1007,DASHBOARD!$C$4) -> 349 | U16: =$S16-$T16 -> 51 | V16: =IFERROR($T16/$S16,0) -> 0.8725 | W16: =IF($T16=0,0,IF($A16="Savings",$T16,IF(AND(DASHBOARD!$C$4=YEAR(TODAY()),MATCH(DASHBOARD!$C$3,SETTINGS!$K$21:$K$32,0)=MONTH(TODAY())),MIN($T16/MAX(1,DAY(TODAY()))*DAY(DATE(DASHBOARD!$C$4,MATCH(DASHBOARD!$C$3,SETTINGS!$K$21:$K$32,0)+1,0)),MAX($T16,$S16*1.5)),$T16))) -> 349 | X16: =IF($S16=0,IF($T16=0,"No Budget","Over Budget"),IF($V16<=SETTINGS!$E$5,"Safe",IF($V16<=SETTINGS!$E$6,"Watch Spending",IF($V16<=SETTINGS!$E$7,"Near Limit","Over Budget")))) -> Watch Spending
A17: =SETTINGS!$A$42 -> Personal Care | B17: =SETTINGS!$C$42 -> Priority 2 | C17: =SETTINGS!$D$42 -> Variable | D17: =SETTINGS!$E$42 -> Useful | E17: =SETTINGS!$F$42 -> Lifestyle | F17: =SETTINGS!$B$42 -> 500 | G17: =$F17 -> 500 | H17: =$F17 -> 500 | I17: =$F17 -> 500 | J17: =$F17 -> 500 | K17: =$F17 -> 500 | L17: =$F17 -> 500 | M17: =$F17 -> 500 | N17: =$F17 -> 500 | ... R17: =$F17 -> 500 | S17: =IFERROR(INDEX($G17:$R17,1,MATCH(DASHBOARD!$C$3,$G$7:$R$7,0)),0) -> 500 | T17: =SUMIFS('QUICK ENTRY'!$E$8:$E$1007,'QUICK ENTRY'!$AF$8:$AF$1007,"Yes",'QUICK ENTRY'!$C$8:$C$1007,IF($A17="Savings","Savings Transfer","Expense"),'QUICK ENTRY'!$I$8:$I$1007,$A17,'QUICK ENTRY'!$V$8:$V$1007,DASHBOARD!$C$3,'QUICK ENTRY'!$X$8:$X$1007,DASHBOARD!$C$4) -> 0 | U17: =$S17-$T17 -> 500 | V17: =IFERROR($T17/$S17,0) -> 0 | W17: =IF($T17=0,0,IF($A17="Savings",$T17,IF(AND(DASHBOARD!$C$4=YEAR(TODAY()),MATCH(DASHBOARD!$C$3,SETTINGS!$K$21:$K$32,0)=MONTH(TODAY())),MIN($T17/MAX(1,DAY(TODAY()))*DAY(DATE(DASHBOARD!$C$4,MATCH(DASHBOARD!$C$3,SETTINGS!$K$21:$K$32,0)+1,0)),MAX($T17,$S17*1.5)),$T17))) -> 0 | X17: =IF($S17=0,IF($T17=0,"No Budget","Over Budget"),IF($V17<=SETTINGS!$E$5,"Safe",IF($V17<=SETTINGS!$E$6,"Watch Spending",IF($V17<=SETTINGS!$E$7,"Near Limit","Over Budget")))) -> Safe
A18: =SETTINGS!$A$43 -> Clothing | B18: =SETTINGS!$C$43 -> Priority 3 | C18: =SETTINGS!$D$43 -> Variable | D18: =SETTINGS!$E$43 -> Optional | E18: =SETTINGS!$F$43 -> Lifestyle | F18: =SETTINGS!$B$43 -> 500 | G18: =$F18 -> 500 | H18: =$F18 -> 500 | I18: =$F18 -> 500 | J18: =$F18 -> 500 | K18: =$F18 -> 500 | L18: =$F18 -> 500 | M18: =$F18 -> 500 | N18: =$F18 -> 500 | ... R18: =$F18 -> 500 | S18: =IFERROR(INDEX($G18:$R18,1,MATCH(DASHBOARD!$C$3,$G$7:$R$7,0)),0) -> 500 | T18: =SUMIFS('QUICK ENTRY'!$E$8:$E$1007,'QUICK ENTRY'!$AF$8:$AF$1007,"Yes",'QUICK ENTRY'!$C$8:$C$1007,IF($A18="Savings","Savings Transfer","Expense"),'QUICK ENTRY'!$I$8:$I$1007,$A18,'QUICK ENTRY'!$V$8:$V$1007,DASHBOARD!$C$3,'QUICK ENTRY'!$X$8:$X$1007,DASHBOARD!$C$4) -> 0 | U18: =$S18-$T18 -> 500 | V18: =IFERROR($T18/$S18,0) -> 0 | W18: =IF($T18=0,0,IF($A18="Savings",$T18,IF(AND(DASHBOARD!$C$4=YEAR(TODAY()),MATCH(DASHBOARD!$C$3,SETTINGS!$K$21:$K$32,0)=MONTH(TODAY())),MIN($T18/MAX(1,DAY(TODAY()))*DAY(DATE(DASHBOARD!$C$4,MATCH(DASHBOARD!$C$3,SETTINGS!$K$21:$K$32,0)+1,0)),MAX($T18,$S18*1.5)),$T18))) -> 0 | X18: =IF($S18=0,IF($T18=0,"No Budget","Over Budget"),IF($V18<=SETTINGS!$E$5,"Safe",IF($V18<=SETTINGS!$E$6,"Watch Spending",IF($V18<=SETTINGS!$E$7,"Near Limit","Over Budget")))) -> Safe
A19: =SETTINGS!$A$44 -> Entertainment | B19: =SETTINGS!$C$44 -> Priority 4 | C19: =SETTINGS!$D$44 -> Variable | D19: =SETTINGS!$E$44 -> Optional | E19: =SETTINGS!$F$44 -> Lifestyle | F19: =SETTINGS!$B$44 -> 1000 | G19: =$F19 -> 1000 | H19: =$F19 -> 1000 | I19: =$F19 -> 1000 | J19: =$F19 -> 1000 | K19: =$F19 -> 1000 | L19: =$F19 -> 1000 | M19: =$F19 -> 1000 | N19: =$F19 -> 1000 | ... R19: =$F19 -> 1000 | S19: =IFERROR(INDEX($G19:$R19,1,MATCH(DASHBOARD!$C$3,$G$7:$R$7,0)),0) -> 1000 | T19: =SUMIFS('QUICK ENTRY'!$E$8:$E$1007,'QUICK ENTRY'!$AF$8:$AF$1007,"Yes",'QUICK ENTRY'!$C$8:$C$1007,IF($A19="Savings","Savings Transfer","Expense"),'QUICK ENTRY'!$I$8:$I$1007,$A19,'QUICK ENTRY'!$V$8:$V$1007,DASHBOARD!$C$3,'QUICK ENTRY'!$X$8:$X$1007,DASHBOARD!$C$4) -> 0 | U19: =$S19-$T19 -> 1000 | V19: =IFERROR($T19/$S19,0) -> 0 | W19: =IF($T19=0,0,IF($A19="Savings",$T19,IF(AND(DASHBOARD!$C$4=YEAR(TODAY()),MATCH(DASHBOARD!$C$3,SETTINGS!$K$21:$K$32,0)=MONTH(TODAY())),MIN($T19/MAX(1,DAY(TODAY()))*DAY(DATE(DASHBOARD!$C$4,MATCH(DASHBOARD!$C$3,SETTINGS!$K$21:$K$32,0)+1,0)),MAX($T19,$S19*1.5)),$T19))) -> 0 | X19: =IF($S19=0,IF($T19=0,"No Budget","Over Budget"),IF($V19<=SETTINGS!$E$5,"Safe",IF($V19<=SETTINGS!$E$6,"Watch Spending",IF($V19<=SETTINGS!$E$7,"Near Limit","Over Budget")))) -> Safe
A20: =SETTINGS!$A$45 -> Travel Home | B20: =SETTINGS!$C$45 -> Priority 2 | C20: =SETTINGS!$D$45 -> Variable | D20: =SETTINGS!$E$45 -> Useful | E20: =SETTINGS!$F$45 -> Living | F20: =SETTINGS!$B$45 -> 1000 | G20: =$F20 -> 1000 | H20: =$F20 -> 1000 | I20: =$F20 -> 1000 | J20: =$F20 -> 1000 | K20: =$F20 -> 1000 | L20: =$F20 -> 1000 | M20: =$F20 -> 1000 | N20: =$F20 -> 1000 | ... R20: =$F20 -> 1000 | S20: =IFERROR(INDEX($G20:$R20,1,MATCH(DASHBOARD!$C$3,$G$7:$R$7,0)),0) -> 1000 | T20: =SUMIFS('QUICK ENTRY'!$E$8:$E$1007,'QUICK ENTRY'!$AF$8:$AF$1007,"Yes",'QUICK ENTRY'!$C$8:$C$1007,IF($A20="Savings","Savings Transfer","Expense"),'QUICK ENTRY'!$I$8:$I$1007,$A20,'QUICK ENTRY'!$V$8:$V$1007,DASHBOARD!$C$3,'QUICK ENTRY'!$X$8:$X$1007,DASHBOARD!$C$4) -> 0 | U20: =$S20-$T20 -> 1000 | V20: =IFERROR($T20/$S20,0) -> 0 | W20: =IF($T20=0,0,IF($A20="Savings",$T20,IF(AND(DASHBOARD!$C$4=YEAR(TODAY()),MATCH(DASHBOARD!$C$3,SETTINGS!$K$21:$K$32,0)=MONTH(TODAY())),MIN($T20/MAX(1,DAY(TODAY()))*DAY(DATE(DASHBOARD!$C$4,MATCH(DASHBOARD!$C$3,SETTINGS!$K$21:$K$32,0)+1,0)),MAX($T20,$S20*1.5)),$T20))) -> 0 | X20: =IF($S20=0,IF($T20=0,"No Budget","Over Budget"),IF($V20<=SETTINGS!$E$5,"Safe",IF($V20<=SETTINGS!$E$6,"Watch Spending",IF($V20<=SETTINGS!$E$7,"Near Limit","Over Budget")))) -> Safe
A21: =SETTINGS!$A$46 -> Health & Fitness | B21: =SETTINGS!$C$46 -> Priority 2 | C21: =SETTINGS!$D$46 -> Variable | D21: =SETTINGS!$E$46 -> Essential | E21: =SETTINGS!$F$46 -> Living | F21: =SETTINGS!$B$46 -> 700 | G21: =$F21 -> 700 | H21: =$F21 -> 700 | I21: =$F21 -> 700 | J21: =$F21 -> 700 | K21: =$F21 -> 700 | L21: =$F21 -> 700 | M21: =$F21 -> 700 | N21: =$F21 -> 700 | ... R21: =$F21 -> 700 | S21: =IFERROR(INDEX($G21:$R21,1,MATCH(DASHBOARD!$C$3,$G$7:$R$7,0)),0) -> 700 | T21: =SUMIFS('QUICK ENTRY'!$E$8:$E$1007,'QUICK ENTRY'!$AF$8:$AF$1007,"Yes",'QUICK ENTRY'!$C$8:$C$1007,IF($A21="Savings","Savings Transfer","Expense"),'QUICK ENTRY'!$I$8:$I$1007,$A21,'QUICK ENTRY'!$V$8:$V$1007,DASHBOARD!$C$3,'QUICK ENTRY'!$X$8:$X$1007,DASHBOARD!$C$4) -> 700 | U21: =$S21-$T21 -> 0 | V21: =IFERROR($T21/$S21,0) -> 1 | W21: =IF($T21=0,0,IF($A21="Savings",$T21,IF(AND(DASHBOARD!$C$4=YEAR(TODAY()),MATCH(DASHBOARD!$C$3,SETTINGS!$K$21:$K$32,0)=MONTH(TODAY())),MIN($T21/MAX(1,DAY(TODAY()))*DAY(DATE(DASHBOARD!$C$4,MATCH(DASHBOARD!$C$3,SETTINGS!$K$21:$K$32,0)+1,0)),MAX($T21,$S21*1.5)),$T21))) -> 700 | X21: =IF($S21=0,IF($T21=0,"No Budget","Over Budget"),IF($V21<=SETTINGS!$E$5,"Safe",IF($V21<=SETTINGS!$E$6,"Watch Spending",IF($V21<=SETTINGS!$E$7,"Near Limit","Over Budget")))) -> Near Limit
A22: =SETTINGS!$A$47 -> Shopping & Gifts | B22: =SETTINGS!$C$47 -> Priority 4 | C22: =SETTINGS!$D$47 -> Variable | D22: =SETTINGS!$E$47 -> Optional | E22: =SETTINGS!$F$47 -> Lifestyle | F22: =SETTINGS!$B$47 -> 1000 | G22: =$F22 -> 1000 | H22: =$F22 -> 1000 | I22: =$F22 -> 1000 | J22: =$F22 -> 1000 | K22: =$F22 -> 1000 | L22: =$F22 -> 1000 | M22: =$F22 -> 1000 | N22: =$F22 -> 1000 | ... R22: =$F22 -> 1000 | S22: =IFERROR(INDEX($G22:$R22,1,MATCH(DASHBOARD!$C$3,$G$7:$R$7,0)),0) -> 1000 | T22: =SUMIFS('QUICK ENTRY'!$E$8:$E$1007,'QUICK ENTRY'!$AF$8:$AF$1007,"Yes",'QUICK ENTRY'!$C$8:$C$1007,IF($A22="Savings","Savings Transfer","Expense"),'QUICK ENTRY'!$I$8:$I$1007,$A22,'QUICK ENTRY'!$V$8:$V$1007,DASHBOARD!$C$3,'QUICK ENTRY'!$X$8:$X$1007,DASHBOARD!$C$4) -> 0 | U22: =$S22-$T22 -> 1000 | V22: =IFERROR($T22/$S22,0) -> 0 | W22: =IF($T22=0,0,IF($A22="Savings",$T22,IF(AND(DASHBOARD!$C$4=YEAR(TODAY()),MATCH(DASHBOARD!$C$3,SETTINGS!$K$21:$K$32,0)=MONTH(TODAY())),MIN($T22/MAX(1,DAY(TODAY()))*DAY(DATE(DASHBOARD!$C$4,MATCH(DASHBOARD!$C$3,SETTINGS!$K$21:$K$32,0)+1,0)),MAX($T22,$S22*1.5)),$T22))) -> 0 | X22: =IF($S22=0,IF($T22=0,"No Budget","Over Budget"),IF($V22<=SETTINGS!$E$5,"Safe",IF($V22<=SETTINGS!$E$6,"Watch Spending",IF($V22<=SETTINGS!$E$7,"Near Limit","Over Budget")))) -> Safe
A23: =SETTINGS!$A$48 -> Emergency | B23: =SETTINGS!$C$48 -> Priority 1 | C23: =SETTINGS!$D$48 -> Variable | D23: =SETTINGS!$E$48 -> Essential | E23: =SETTINGS!$F$48 -> Living | F23: =SETTINGS!$B$48 -> 500 | G23: =$F23 -> 500 | H23: =$F23 -> 500 | I23: =$F23 -> 500 | J23: =$F23 -> 500 | K23: =$F23 -> 500 | L23: =$F23 -> 500 | M23: =$F23 -> 500 | N23: =$F23 -> 500 | ... R23: =$F23 -> 500 | S23: =IFERROR(INDEX($G23:$R23,1,MATCH(DASHBOARD!$C$3,$G$7:$R$7,0)),0) -> 500 | T23: =SUMIFS('QUICK ENTRY'!$E$8:$E$1007,'QUICK ENTRY'!$AF$8:$AF$1007,"Yes",'QUICK ENTRY'!$C$8:$C$1007,IF($A23="Savings","Savings Transfer","Expense"),'QUICK ENTRY'!$I$8:$I$1007,$A23,'QUICK ENTRY'!$V$8:$V$1007,DASHBOARD!$C$3,'QUICK ENTRY'!$X$8:$X$1007,DASHBOARD!$C$4) -> 0 | U23: =$S23-$T23 -> 500 | V23: =IFERROR($T23/$S23,0) -> 0 | W23: =IF($T23=0,0,IF($A23="Savings",$T23,IF(AND(DASHBOARD!$C$4=YEAR(TODAY()),MATCH(DASHBOARD!$C$3,SETTINGS!$K$21:$K$32,0)=MONTH(TODAY())),MIN($T23/MAX(1,DAY(TODAY()))*DAY(DATE(DASHBOARD!$C$4,MATCH(DASHBOARD!$C$3,SETTINGS!$K$21:$K$32,0)+1,0)),MAX($T23,$S23*1.5)),$T23))) -> 0 | X23: =IF($S23=0,IF($T23=0,"No Budget","Over Budget"),IF($V23<=SETTINGS!$E$5,"Safe",IF($V23<=SETTINGS!$E$6,"Watch Spending",IF($V23<=SETTINGS!$E$7,"Near Limit","Over Budget")))) -> Safe
